Workbook

Sheet Inputs
B2: Inputs | J2: Legend
J3: User input, hard-coded default value | K3: Value
C4: General Inputs | J4: User input, calculated default value (user can over ride | K4: Value
C5: Analysis Period (Project Life) | D5: 25 | E5: years (40 max) | J5: User input, drop down selection | K5: Value
C6: Discount Rate | D6: 0.07 | E6: % per annum | J6: Input not applicable (user can over ride) | K6: Value
C7: Inflation Rate | D7: 0.02 | E7: % per annum | J7: Read-only output | K7: Value
C8: Desired Confidence that Reserve Covers Cost | D8: 0.92
C9: Working Hours/year | D9: 2080
C11: Plant Inputs
C12: Plant Name | D12: Ground Mount Fixed Tilt
C13: Location | D13: Denver, CO
C14: Plant Size (kWp DC) | D14: 10000
C15: Plant Size (Wp DC) | D15: =D14*1000 -> 10000000
C16: Energy Yield Year 1 (kWh/kWp/year) | D16: 1400
C17: Plant Installed Cost | D17: 3000000
C18: Module Efficiency | D18: 0.16
C19: Module Power (W STC) | D19: 305
C20: Array Area (m2) | D20: =D15/1000/D18 -> 62500
C21: Number of Modules | D21: =ROUNDUP(D15/D19,0) -> 32787
C22: Module Type/ Degradation | D22: Mono-crystal silicon: 0.36%/year
C23: Degradation Rate per year | D23: =VLOOKUP(D22,Lists!D2:E8,2,FALSE) -> 0.0036
C24: Modules per String | D24: 14
C25: Number of Strings | D25: =D15/D19/D24 -> 2341.9204
C26: Strings per Combiner Box | D26: 15
C27: Number of Combiner Boxes | D27: =IF(D26=0,0,ROUNDUP(D25/D26,0)) -> 157
C28: Combiner boxes per DC disconnect | D28: 1
C29: Number of DC Disconnects | D29: =IF(D27=0,1,IF(D28=0,1,ROUNDUP(D27/D28,0))) -> 157
C30: Inverter Type | D30: Central Inverter
C31: Inverter Replacement Cost/ Wp | D31: =VLOOKUP($D$30,Lists!M2:N5,2,FALSE) -> 0.19
C32: Number of Inverters | D32: 10
C33: Inverter Capacity (kWp) | D33: 1000
C34: Number of Transformers | D34: 10
C36: Inverter Warranty (years) | D36: 10
C37: PV Module Product Warranty (years) | D37: 20
C38: Other equipment (EPC) Warranty (years) | D38: 1
C39: Purchased monitoring contract (years) | D39: 0 | E39: Enter '0' if not applicable
C41: Market Sector | D41: Utility (1 MW)
C42: Mounting Location | D42: Ground Mount
C43: Roof Slope | D43: Sloped, 4:12
C44: Roof Type | D44: Composite Shingle
C45: Mounting Type | D45: Attached
C46: Inspection technique | D46: Arial
C47: Array Area per Roof Attachment (m2) | D47: 2
C48: Number of Roof Attachments | D48: =IF(D45=Lists!Y3,0,D20/D47) -> 31250
C49: Ground Coverage Ratio (GCR) | D49: 0.33
C50: Site Area (acres) | D50: =(1.94/D19)*(273/D49)*D15/1000000 -> 52.61997
C52: Modules/Row | D52: 200
C53: Total Rows: | D53: =D55*D56 -> 163.93443
C54: Tracking or Fixed | D54: 1-axis Tracking
C55: Rows per Tracked Block:(ignore untracked) | D55: 16
C56: Total Tracking Blocks:(ignore untracked) | D56: =D15/(D55*D52*D19) -> 10.245902
C57: Foundations per row: (ignore rooftop) | D57: 10
C60: Environmental Conditions
C61: Indicate "1" if condition applies to project, "0" if not applicable
C62: Snow | D62: 0
C63: Pollen | D63: 0
C64: Bird Populations | D64: 0 | F64: (reduce efficiency 2.67% for central, 0.18% for string inverter, Wang et al 2012)
C65: Sand/Dust | D65: 0 | F65: (reduce efficiency 1%/g, Wang et al 2012)
C66: Humid | D66: 0
C67: Hot | D67: 0
C68: High Wind | D68: 0
C69: Hail | D69: 0
C70: Salt Air | D70: 0 | F70: (reduce efficiency 1%/g, Wang et al 2012)
C71: Diesel Soot | D71: 0 | F71: (reduce efficiency 1%/g, Wang et al 2012)
C72: Industrial Emissions | D72: 0
C73: Construction Site Nearby | D73: 0
C74: High Insolation | D74: 0 | F74: (reduce availability 0.83%, Wang et al 2012)

Sheet Report
A1: Plant Name | B1: =Inputs!D12 -> Ground Mount Fixed Tilt | D1: Lifetime NPV by Service Provider | I1: Lifetime NPV by O&M Category | N1: Year | O1: ='Detailed Measures'!AA2 -> 1 | P1: ='Detailed Measures'!AB2 -> 2 | Q1: ='Detailed Measures'!AC2 -> 3 | R1: ='Detailed Measures'!AD2 -> 4 | S1: ='Detailed Measures'!AE2 -> 5 | T1: ='Detailed Measures'!AF2 -> 6 | U1: ='Detailed Measures'!AG2 -> 7 | V1: ='Detailed Measures'!AH2 -> 8 | ... BB1: ='Detailed Measures'!BN2 -> 40
D2: Service Provider | E2: Avg. Cost/Yr | F2: NPV (Life) | G2: % of Total | I2: O&M Category | J2: Avg. Cost/Yr | K2: NPV (Life) | L2: % of Total | N2: Annual Cash Flow | O2: ='Detailed Measures'!AA137 -> 60724.044 | P2: ='Detailed Measures'!AB137 -> 92998.134 | Q2: ='Detailed Measures'!AC137 -> 93544.663 | R2: ='Detailed Measures'!AD137 -> 96139.882 | S2: ='Detailed Measures'!AE137 -> 126946.47 | T2: ='Detailed Measures'!AF137 -> 100090.6 | U2: ='Detailed Measures'!AG137 -> 101371.86 | V2: ='Detailed Measures'!AH137 -> 104857.33 | ... BB2: ='Detailed Measures'!BN137 -> 0
A3: Results | D3: Administrator | E3: =SUMIF('Detailed Measures'!$J$3:$J$136,D3,'Detailed Measures'!$X$3:$X$136) -> 7717.4876 | F3: =SUMIF('Detailed Measures'!$J$3:$J$136,D3,'Detailed Measures'!$Y$3:$Y$136) -> 88635.448 | G3: =F3/$F$18 -> 0.041804805 | I3: =Lists!C3 -> AC Wiring | J3: =SUMIF('Detailed Measures'!$D$3:$D$136,I3,'Detailed Measures'!$X$3:$X$136) -> 2054.8769 | K3: =SUMIF('Detailed Measures'!$D$3:$D$136,I3,'Detailed Measures'!$Y$3:$Y$136) -> 22299.464 | L3: =K3/$K$18 -> 0.010519486 | N3: Reserve Account Amount | O3: ='Detailed Measures'!BQ137 -> 61847.328 | P3: ='Detailed Measures'!BR137 -> 155324.23 | Q3: ='Detailed Measures'!BS137 -> 150035.1 | R3: ='Detailed Measures'!BT137 -> 146930.98 | S3: ='Detailed Measures'!BU137 -> 172198.29 | T3: ='Detailed Measures'!BV137 -> 139985.54 | U3: ='Detailed Measures'!BW137 -> 136113.01 | V3: ='Detailed Measures'!BX137 -> 135394.43 | ... BB3: ='Detailed Measures'!DD137 -> 0
A4: Annualized O&M Costs ($/year) | B4: =B7/(((1+Inputs!D7)/(Inputs!D6-Inputs!D7)*(1-((1+Inputs!D7)/(1+Inputs!D6))^Inputs!D5))) -> 148960.15 | D4: Cleaner | E4: =SUMIF('Detailed Measures'!$J$3:$J$136,D4,'Detailed Measures'!$X$3:$X$136) -> 23710.307 | F4: =SUMIF('Detailed Measures'!$J$3:$J$136,D4,'Detailed Measures'!$Y$3:$Y$136) -> 272344.67 | G4: =F4/$F$18 -> 0.12845104 | I4: =Lists!C4 -> DC Wiring | J4: =SUMIF('Detailed Measures'!$D$3:$D$136,I4,'Detailed Measures'!$X$3:$X$136) -> 32954.81 | K4: =SUMIF('Detailed Measures'!$D$3:$D$136,I4,'Detailed Measures'!$Y$3:$Y$136) -> 416042.67 | L4: =K4/$K$18 -> 0.19626278
A5: Annualized Unit O&M Costs ($/kW/year) | B5: =B4/(Inputs!D15/1000) -> 14.896015 | D5: Inverter specialist | E5: =SUMIF('Detailed Measures'!$J$3:$J$136,D5,'Detailed Measures'!$X$3:$X$136) -> 29782.305 | F5: =SUMIF('Detailed Measures'!$J$3:$J$136,D5,'Detailed Measures'!$Y$3:$Y$136) -> 268749.26 | G5: =F5/$F$18 -> 0.12675527 | I5: =Lists!C5 -> Asset Management | J5: =SUMIF('Detailed Measures'!$D$3:$D$136,I5,'Detailed Measures'!$X$3:$X$136) -> 4548.8299 | K5: =SUMIF('Detailed Measures'!$D$3:$D$136,I5,'Detailed Measures'!$Y$3:$Y$136) -> 52249.412 | L5: =K5/$K$18 -> 0.024647988
A6: Maximum Reserve Account | B6: =MAX('Detailed Measures'!BQ137:DD137) -> 1519994.1 | D6: Inspector | E6: =SUMIF('Detailed Measures'!$J$3:$J$136,D6,'Detailed Measures'!$X$3:$X$136) -> 25548.641 | F6: =SUMIF('Detailed Measures'!$J$3:$J$136,D6,'Detailed Measures'!$Y$3:$Y$136) -> 287353.09 | G6: =F6/$F$18 -> 0.13552974 | I6: =Lists!C6 -> Documents | J6: =SUMIF('Detailed Measures'!$D$3:$D$136,I6,'Detailed Measures'!$X$3:$X$136) -> 3115.3948 | K6: =SUMIF('Detailed Measures'!$D$3:$D$136,I6,'Detailed Measures'!$Y$3:$Y$136) -> 35784.488 | L6: =K6/$K$18 -> 0.016880872
A7: Net Present Value O&M Costs (project life) | B7: ='Detailed Measures'!Y137 -> 2120221.6 | D7: Journeyman electrician | E7: =SUMIF('Detailed Measures'!$J$3:$J$136,D7,'Detailed Measures'!$X$3:$X$136) -> 11209.753 | F7: =SUMIF('Detailed Measures'!$J$3:$J$136,D7,'Detailed Measures'!$Y$3:$Y$136) -> 577876.97 | G7: =F7/$F$18 -> 0.27255499 | I7: =Lists!C7 -> Electrical | J7: =SUMIF('Detailed Measures'!$D$3:$D$136,I7,'Detailed Measures'!$X$3:$X$136) -> 1795.7882 | K7: =SUMIF('Detailed Measures'!$D$3:$D$136,I7,'Detailed Measures'!$Y$3:$Y$136) -> 20350.664 | L7: =K7/$K$18 -> 0.0096001644
A8: Net Present Value (project life) per Wp | B8: =B7/Inputs!D15 -> 0.21202216 | D8: PV module/array Specialist | E8: =SUMIF('Detailed Measures'!$J$3:$J$136,D8,'Detailed Measures'!$X$3:$X$136) -> 26303.453 | F8: =SUMIF('Detailed Measures'!$J$3:$J$136,D8,'Detailed Measures'!$Y$3:$Y$136) -> 318732.32 | G8: =F8/$F$18 -> 0.15032972 | I8: =Lists!C8 -> Mechanical | J8: =SUMIF('Detailed Measures'!$D$3:$D$136,I8,'Detailed Measures'!$X$3:$X$136) -> 5316.9973 | K8: =SUMIF('Detailed Measures'!$D$3:$D$136,I8,'Detailed Measures'!$Y$3:$Y$136) -> 53304.223 | L8: =K8/$K$18 -> 0.025145582
A9: NPV Annual O&M Cost per kWh | B9: =B7/NPV(Inputs!D6,'Detailed Measures'!AA138:BM138) -> 0.013451288 | D9: Network/IT | E9: =SUMIF('Detailed Measures'!$J$3:$J$136,D9,'Detailed Measures'!$X$3:$X$136) -> 152.40949 | F9: =SUMIF('Detailed Measures'!$J$3:$J$136,D9,'Detailed Measures'!$Y$3:$Y$136) -> 1530.5846 | G9: =F9/$F$18 -> 0.00072189844 | I9: =Lists!C9 -> Inverter | J9: =SUMIF('Detailed Measures'!$D$3:$D$136,I9,'Detailed Measures'!$X$3:$X$136) -> 30636.999 | K9: =SUMIF('Detailed Measures'!$D$3:$D$136,I9,'Detailed Measures'!$Y$3:$Y$136) -> 277163.57 | L9: =K9/$K$18 -> 0.13074835
D10: Master electrician | E10: =SUMIF('Detailed Measures'!$J$3:$J$136,D10,'Detailed Measures'!$X$3:$X$136) -> 4790.3476 | F10: =SUMIF('Detailed Measures'!$J$3:$J$136,D10,'Detailed Measures'!$Y$3:$Y$136) -> 53383.212 | G10: =F10/$F$18 -> 0.025178129 | I10: =Lists!C10 -> Meter | J10: =SUMIF('Detailed Measures'!$D$3:$D$136,I10,'Detailed Measures'!$X$3:$X$136) -> 17.809584 | K10: =SUMIF('Detailed Measures'!$D$3:$D$136,I10,'Detailed Measures'!$Y$3:$Y$136) -> 204.56695 | L10: =K10/$K$18 -> 9.6501831e-05
D11: Mechanic | E11: =SUMIF('Detailed Measures'!$J$3:$J$136,D11,'Detailed Measures'!$X$3:$X$136) -> 2207.3313 | F11: =SUMIF('Detailed Measures'!$J$3:$J$136,D11,'Detailed Measures'!$Y$3:$Y$136) -> 54081.586 | G11: =F11/$F$18 -> 0.025507516 | I11: =Lists!C11 -> Monitoring | J11: =SUMIF('Detailed Measures'!$D$3:$D$136,I11,'Detailed Measures'!$X$3:$X$136) -> 3.4091348 | K11: =SUMIF('Detailed Measures'!$D$3:$D$136,I11,'Detailed Measures'!$Y$3:$Y$136) -> 17.619704 | L11: =K11/$K$18 -> 8.3118691e-06
D12: Designer | E12: =SUMIF('Detailed Measures'!$J$3:$J$136,D12,'Detailed Measures'!$X$3:$X$136) -> 0 | F12: =SUMIF('Detailed Measures'!$J$3:$J$136,D12,'Detailed Measures'!$Y$3:$Y$136) -> 0 | G12: =F12/$F$18 -> 0 | I12: =Lists!C12 -> Roof | J12: =SUMIF('Detailed Measures'!$D$3:$D$136,I12,'Detailed Measures'!$X$3:$X$136) -> 0 | K12: =SUMIF('Detailed Measures'!$D$3:$D$136,I12,'Detailed Measures'!$Y$3:$Y$136) -> 0 | L12: =K12/$K$18 -> 0
D13: Pest control | E13: =SUMIF('Detailed Measures'!$J$3:$J$136,D13,'Detailed Measures'!$X$3:$X$136) -> 1613.7533 | F13: =SUMIF('Detailed Measures'!$J$3:$J$136,D13,'Detailed Measures'!$Y$3:$Y$136) -> 18536.12 | G13: =F13/$F$18 -> 0.0087425393 | I13: =Lists!C13 -> Rack | J13: =SUMIF('Detailed Measures'!$D$3:$D$136,I13,'Detailed Measures'!$X$3:$X$136) -> 105.71335 | K13: =SUMIF('Detailed Measures'!$D$3:$D$136,I13,'Detailed Measures'!$Y$3:$Y$136) -> 1220.7685 | L13: =K13/$K$18 -> 0.00057588183
D14: Roofing | E14: =SUMIF('Detailed Measures'!$J$3:$J$136,D14,'Detailed Measures'!$X$3:$X$136) -> 0 | F14: =SUMIF('Detailed Measures'!$J$3:$J$136,D14,'Detailed Measures'!$Y$3:$Y$136) -> 0 | G14: =F14/$F$18 -> 0 | I14: =Lists!C14 -> PV Module | J14: =SUMIF('Detailed Measures'!$D$3:$D$136,I14,'Detailed Measures'!$X$3:$X$136) -> 56090.654 | K14: =SUMIF('Detailed Measures'!$D$3:$D$136,I14,'Detailed Measures'!$Y$3:$Y$136) -> 1105116.1 | L14: =K14/$K$18 -> 0.52132431
D15: Structural engineer | E15: =SUMIF('Detailed Measures'!$J$3:$J$136,D15,'Detailed Measures'!$X$3:$X$136) -> 5.9545299 | F15: =SUMIF('Detailed Measures'!$J$3:$J$136,D15,'Detailed Measures'!$Y$3:$Y$136) -> 69.390865 | G15: =F15/$F$18 -> 3.2728119e-05 | I15: =Lists!C15 -> Tracker | J15: =SUMIF('Detailed Measures'!$D$3:$D$136,I15,'Detailed Measures'!$X$3:$X$136) -> 7547.5399 | K15: =SUMIF('Detailed Measures'!$D$3:$D$136,I15,'Detailed Measures'!$Y$3:$Y$136) -> 86693.618 | L15: =K15/$K$18 -> 0.0408966
D16: Mower/Trimmer | E16: =SUMIF('Detailed Measures'!$J$3:$J$136,D16,'Detailed Measures'!$X$3:$X$136) -> 15573.664 | F16: =SUMIF('Detailed Measures'!$J$3:$J$136,D16,'Detailed Measures'!$Y$3:$Y$136) -> 178884.42 | G16: =F16/$F$18 -> 0.084370626 | I16: =Lists!C16 -> Transformer | J16: =SUMIF('Detailed Measures'!$D$3:$D$136,I16,'Detailed Measures'!$X$3:$X$136) -> 4395.4969 | K16: =SUMIF('Detailed Measures'!$D$3:$D$136,I16,'Detailed Measures'!$Y$3:$Y$136) -> 49377.432 | L16: =K16/$K$18 -> 0.023293169
D17: Utilities locator | E17: =SUMIF('Detailed Measures'!$J$3:$J$136,D17,'Detailed Measures'!$X$3:$X$136) -> 4.3650024 | F17: =SUMIF('Detailed Measures'!$J$3:$J$136,D17,'Detailed Measures'!$Y$3:$Y$136) -> 44.497299 | G17: =F17/$F$18 -> 2.0987099e-05 | I17: =Lists!C17 -> Whole System | J17: =SUMIF('Detailed Measures'!$D$3:$D$136,I17,'Detailed Measures'!$X$3:$X$136) -> 35.453297 | K17: =SUMIF('Detailed Measures'!$D$3:$D$136,I17,'Detailed Measures'!$Y$3:$Y$136) -> 396.98139 | L17: =K17/$K$18 -> 0.00018727087
D18: Total | E18: =SUM(E3:E17) -> 148619.77 | F18: =SUM(F3:F17) -> 2120221.6 | G18: =SUM(G3:G17) -> 1 | I18: Total | J18: =SUM(J3:J16) -> 148584.32 | K18: =SUM(K3:K16) -> 2119824.6 | L18: =SUM(L3:L16) -> 1

Sheet Detailed Measures
A1: Detailed Measures | Y1: Annual Cash Flow | AA1: Annual Cash Flow | BO1: Reserve Account | BQ1: Reserve Account
A2: Service Description | B2: O&M Type | C2: Service Category | D2: O&M Category | E2: Applicable ? (1= yes, 0 = no) | F2: Covered by Warranty - Materials (1=yes, 0=no) | G2: Covered by Warranty - Labor (1=yes, 0=no) | H2: Warranty or Service Package Type | I2: Applicable Unit | J2: Service Provider | K2: Labor Rate per Hour | L2: Mean Interval (years) | M2: Weibull or Lognormal Shape Factor | N2: Type of Distribution | O2: Approx. Number of Units | P2: Labor hrs per unit | Q2: Total Labor Hours/year (not used, just for check) | R2: Material/ Other Cost per unit | S2: Total Labor Cost | T2: Total Matl and Other Cost | U2: Total Cost for Measure | V2: Notes | W2: Reference | X2: Average Annual Expense | Y2: NPV (Project Life) | Z2: % of Total NPV | AA2: 1 | AB2: 2 | AC2: 3 | AD2: 4 | AE2: 5 | AF2: 6 | AG2: 7 | AH2: 8 | AI2: 9 | AJ2: 10 | AK2: 11 | AL2: 12 | AM2: 13 | AN2: 14 | AO2: 15 | AP2: 16 | AQ2: 17 | AR2: 18 | AS2: 19 | AT2: 20 | AU2: 21 | AV2: 22 | AW2: 23 | AX2: 24 | AY2: 25 | AZ2: 26 | BA2: 27 | BB2: 28 | BC2: 29 | BD2: 30 | BE2: 31 | BF2: 32 | BG2: 33 | BH2: 34 | BI2: 35 | BJ2: 36 | BK2: 37 | BL2: 38 | BM2: 39 | BN2: 40 | BO2: NPV (Project Life) | BP2: % of Total NPV | BQ2: 1 | BR2: 2 | BS2: 3 | BT2: 4 | BU2: 5 | BV2: 6 | BW2: 7 | BX2: 8 | BY2: 9 | BZ2: 10 | CA2: 11 | CB2: 12 | CC2: 13 | CD2: 14 | CE2: 15 | CF2: 16 | CG2: 17 | CH2: 18 | CI2: 19 | CJ2: 20 | CK2: 21 | CL2: 22 | CM2: 23 | CN2: 24 | CO2: 25 | CP2: 26 | CQ2: 27 | CR2: 28 | CS2: 29 | CT2: 30 | CU2: 31 | CV2: 32 | CW2: 33 | CX2: 34 | CY2: 35 | CZ2: 36 | DA2: 37 | DB2: 38 | DC2: 39 | DD2: 40
A3: Insurance Premium | B3: Administration | C3: Management | D3: Asset Management | E3: 1 | F3: 0 | G3: 0 | H3: N/A | I3: percent of initial cost | J3: Administrator | K3: =VLOOKUP(J3,'Labor Rates'!$A$1:$F$16,2) -> 22.995577 | L3: 1 | M3: 1 | N3: interval | O3: 1 | P3: 0 | Q3: =O3*P3/L3 -> 0 | R3: =0.001*Inputs!D17 -> 3000 | S3: =P3*O3*K3 -> 0 | T3: =R3*O3 -> 3000 | U3: =E3*(T3+S3) -> 3000 | V3: premium percent of intial cost.04% | W3: David Walters, Hartford Steam Boiler, 6/7/2014 | X3: =AVERAGE(AA3:AT3) -> 3717.4976 | Y3: =NPV(Inputs!$D$6,AA3:BN3) -> 42700.445 | Z3: =Y3/SUM($Y$3:$Y$136) -> 0.020139615 | AA3: =$E3*IF(AA$2>Inputs!$D$5,0,IF(AA$2>VLOOKUP($H3,Lists!$P$3:$Q$7,2),IF($N3=Lists!$K$3,IF($L3<1,(($U3/$L3)*((1+Inputs!$D$7)^AA$2)),((INT(AA$2/$L3)-INT((AA$2-1)/$L3))*$U3*((1+Inputs!$D$7)^AA$2))),(_xlfn.WEIBULL.DIST(AA$2,$M3,$L3,FALSE)*$U3*((1+Inputs!$D$7)^AA$2))),IF($N3=Lists!$K$3,IF($L3<1,((($T3*(1-$F3)+$S3*(1-$G3))/$L3)*((1+Inputs!$D$7)^AA$2)),((INT(AA$2/$L3)-INT((AA$2-1)/$L3))*($T3*(1-$F3)+$S3*(1-$G3))*((1+Inputs!$D$7)^AA$2))),((_xlfn.WEIBULL.DIST(AA$2,$M3,$L3,FALSE)*($T3*(1-$F3)+$S3*(1-$G3))*((1+Inputs!$D$7)^AA$2)))))) -> 3060 | AB3: =$E3*IF(AB$2>Inputs!$D$5,0,IF(AB$2>VLOOKUP($H3,Lists!$P$3:$Q$7,2),IF($N3=Lists!$K$3,IF($L3<1,(($U3/$L3)*((1+Inputs!$D$7)^AB$2)),((INT(AB$2/$L3)-INT((AB$2-1)/$L3))*$U3*((1+Inputs!$D$7)^AB$2))),(_xlfn.WEIBULL.DIST(AB$2,$M3,$L3,FALSE)*$U3*((1+Inputs!$D$7)^AB$2))),IF($N3=Lists!$K$3,IF($L3<1,((($T3*(1-$F3)+$S3*(1-$G3))/$L3)*((1+Inputs!$D$7)^AB$2)),((INT(AB$2/$L3)-INT((AB$2-1)/$L3))*($T3*(1-$F3)+$S3*(1-$G3))*((1+Inputs!$D$7)^AB$2))),((_xlfn.WEIBULL.DIST(AB$2,$M3,$L3,FALSE)*($T3*(1-$F3)+$S3*(1-$G3))*((1+Inputs!$D$7)^AB$2)))))) -> 3121.2 | AC3: =$E3*IF(AC$2>Inputs!$D$5,0,IF(AC$2>VLOOKUP($H3,Lists!$P$3:$Q$7,2),IF($N3=Lists!$K$3,IF($L3<1,(($U3/$L3)*((1+Inputs!$D$7)^AC$2)),((INT(AC$2/$L3)-INT((AC$2-1)/$L3))*$U3*((1+Inputs!$D$7)^AC$2))),(_xlfn.WEIBULL.DIST(AC$2,$M3,$L3,FALSE)*$U3*((1+Inputs!$D$7)^AC$2))),IF($N3=Lists!$K$3,IF($L3<1,((($T3*(1-$F3)+$S3*(1-$G3))/$L3)*((1+Inputs!$D$7)^AC$2)),((INT(AC$2/$L3)-INT((AC$2-1)/$L3))*($T3*(1-$F3)+$S3*(1-$G3))*((1+Inputs!$D$7)^AC$2))),((_xlfn.WEIBULL.DIST(AC$2,$M3,$L3,FALSE)*($T3*(1-$F3)+$S3*(1-$G3))*((1+Inputs!$D$7)^AC$2)))))) -> 3183.624 | AD3: =$E3*IF(AD$2>Inputs!$D$5,0,IF(AD$2>VLOOKUP($H3,Lists!$P$3:$Q$7,2),IF($N3=Lists!$K$3,IF($L3<1,(($U3/$L3)*((1+Inputs!$D$7)^AD$2)),((INT(AD$2/$L3)-INT((AD$2-1)/$L3))*$U3*((1+Inputs!$D$7)^AD$2))),Inputs!$D$85^((1-_xlfn.WEIBULL.DIST(AD$2,$M3,$L3,FALSE))/_xlfn.WEIBULL.DIST(AD$2,$M3,$L3,FALSE)*$U3*((1+Inputs!$D$7)^AD$2))),IF($N3=Lists!$K$3,IF($L3<1,((($T3*(1-$F3)+$S3*(1-$G3))/$L3)*((1+Inputs!$D$7)^AD$2)),((INT(AD$2/$L3)-INT((AD$2-1)/$L3))*($T3*(1-$F3)+$S3*(1-$G3))*((1+Inputs!$D$7)^AD$2))),((Inputs!$D$85^((1-_xlfn.WEIBULL.DIST(AD$2,$M3,$L3,FALSE))/_xlfn.WEIBULL.DIST(AD$2,$M3,$L3,FALSE)*($T3*(1-$F3)+$S3*(1-$G3))*((1+Inputs!$D$7)^AD$2))))))) -> 3247.2965 | AE3: =$E3*IF(AE$2>Inputs!$D$5,0,IF(AE$2>VLOOKUP($H3,Lists!$P$3:$Q$7,2),IF($N3=Lists!$K$3,IF($L3<1,(($U3/$L3)*((1+Inputs!$D$7)^AE$2)),((INT(AE$2/$L3)-INT((AE$2-1)/$L3))*$U3*((1+Inputs!$D$7)^AE$2))),(_xlfn.WEIBULL.DIST(AE$2,$M3,$L3,FALSE)*$U3*((1+Inputs!$D$7)^AE$2))),IF($N3=Lists!$K$3,IF($L3<1,((($T3*(1-$F3)+$S3*(1-$G3))/$L3)*((1+Inputs!$D$7)^AE$2)),((INT(AE$2/$L3)-INT((AE$2-1)/$L3))*($T3*(1-$F3)+$S3*(1-$G3))*((1+Inputs!$D$7)^AE$2))),((_xlfn.WEIBULL.DIST(AE$2,$M3,$L3,FALSE)*($T3*(1-$F3)+$S3*(1-$G3))*((1+Inputs!$D$7)^AE$2)))))) -> 3312.2424 | AF3: =$E3*IF(AF$2>Inputs!$D$5,0,IF(AF$2>VLOOKUP($H3,Lists!$P$3:$Q$7,2),IF($N3=Lists!$K$3,IF($L3<1,(($U3/$L3)*((1+Inputs!$D$7)^AF$2)),((INT(AF$2/$L3)-INT((AF$2-1)/$L3))*$U3*((1+Inputs!$D$7)^AF$2))),(_xlfn.WEIBULL.DIST(AF$2,$M3,$L3,FALSE)*$U3*((1+Inputs!$D$7)^AF$2))),IF($N3=Lists!$K$3,IF($L3<1,((($T3*(1-$F3)+$S3*(1-$G3))/$L3)*((1+Inputs!$D$7)^AF$2)),((INT(AF$2/$L3)-INT((AF$2-1)/$L3))*($T3*(1-$F3)+$S3*(1-$G3))*((1+Inputs!$D$7)^AF$2))),((_xlfn.WEIBULL.DIST(AF$2,$M3,$L3,FALSE)*($T3*(1-$F3)+$S3*(1-$G3))*((1+Inputs!$D$7)^AF$2)))))) -> 3378.4873 | AG3: =$E3*IF(AG$2>Inputs!$D$5,0,IF(AG$2>VLOOKUP($H3,Lists!$P$3:$Q$7,2),IF($N3=Lists!$K$3,IF($L3<1,(($U3/$L3)*((1+Inputs!$D$7)^AG$2)),((INT(AG$2/$L3)-INT((AG$2-1)/$L3))*$U3*((1+Inputs!$D$7)^AG$2))),(_xlfn.WEIBULL.DIST(AG$2,$M3,$L3,FALSE)*$U3*((1+Inputs!$D$7)^AG$2))),IF($N3=Lists!$K$3,IF($L3<1,((($T3*(1-$F3)+$S3*(1-$G3))/$L3)*((1+Inputs!$D$7)^AG$2)),((INT(AG$2/$L3)-INT((AG$2-1)/$L3))*($T3*(1-$F3)+$S3*(1-$G3))*((1+Inputs!$D$7)^AG$2))),((_xlfn.WEIBULL.DIST(AG$2,$M3,$L3,FALSE)*($T3*(1-$F3)+$S3*(1-$G3))*((1+Inputs!$D$7)^AG$2)))))) -> 3446.057 | AH3: =$E3*IF(AH$2>Inputs!$D$5,0,IF(AH$2>VLOOKUP($H3,Lists!$P$3:$Q$7,2),IF($N3=Lists!$K$3,IF($L3<1,(($U3/$L3)*((1+Inputs!$D$7)^AH$2)),((INT(AH$2/$L3)-INT((AH$2-1)/$L3))*$U3*((1+Inputs!$D$7)^AH$2))),(_xlfn.WEIBULL.DIST(AH$2,$M3,$L3,FALSE)*$U3*((1+Inputs!$D$7)^AH$2))),IF($N3=Lists!$K$3,IF($L3<1,((($T3*(1-$F3)+$S3*(1-$G3))/$L3)*((1+Inputs!$D$7)^AH$2)),((INT(AH$2/$L3)-INT((AH$2-1)/$L3))*($T3*(1-$F3)+$S3*(1-$G3))*((1+Inputs!$D$7)^AH$2))),((_xlfn.WEIBULL.DIST(AH$2,$M3,$L3,FALSE)*($T3*(1-$F3)+$S3*(1-$G3))*((1+Inputs!$D$7)^AH$2)))))) -> 3514.9781 | AI3: =$E3*IF(AI$2>Inputs!$D$5,0,IF(AI$2>VLOOKUP($H3,Lists!$P$3:$Q$7,2),IF($N3=Lists!$K$3,IF($L3<1,(($U3/$L3)*((1+Inputs!$D$7)^AI$2)),((INT(AI$2/$L3)-INT((AI$2-1)/$L3))*$U3*((1+Inputs!$D$7)^AI$2))),(_xlfn.WEIBULL.DIST(AI$2,$M3,$L3,FALSE)*$U3*((1+Inputs!$D$7)^AI$2))),IF($N3=Lists!$K$3,IF($L3<1,((($T3*(1-$F3)+$S3*(1-$G3))/$L3)*((1+Inputs!$D$7)^AI$2)),((INT(AI$2/$L3)-INT((AI$2-1)/$L3))*($T3*(1-$F3)+$S3*(1-$G3))*((1+Inputs!$D$7)^AI$2))),((_xlfn.WEIBULL.DIST(AI$2,$M3,$L3,FALSE)*($T3*(1-$F3)+$S3*(1-$G3))*((1+Inputs!$D$7)^AI$2)))))) -> 3585.2777 | AJ3: =$E3*IF(AJ$2>Inputs!$D$5,0,IF(AJ$2>VLOOKUP($H3,Lists!$P$3:$Q$7,2),IF($N3=Lists!$K$3,IF($L3<1,(($U3/$L3)*((1+Inputs!$D$7)^AJ$2)),((INT(AJ$2/$L3)-INT((AJ$2-1)/$L3))*$U3*((1+Inputs!$D$7)^AJ$2))),(_xlfn.WEIBULL.DIST(AJ$2,$M3,$L3,FALSE)*$U3*((1+Inputs!$D$7)^AJ$2))),IF($N3=Lists!$K$3,IF($L3<1,((($T3*(1-$F3)+$S3*(1-$G3))/$L3)*((1+Inputs!$D$7)^AJ$2)),((INT(AJ$2/$L3)-INT((AJ$2-1)/$L3))*($T3*(1-$F3)+$S3*(1-$G3))*((1+Inputs!$D$7)^AJ$2))),((_xlfn.WEIBULL.DIST(AJ$2,$M3,$L3,FALSE)*($T3*(1-$F3)+$S3*(1-$G3))*((1+Inputs!$D$7)^AJ$2)))))) -> 3656.9833 | AK3: =$E3*IF(AK$2>Inputs!$D$5,0,IF(AK$2>VLOOKUP($H3,Lists!$P$3:$Q$7,2),IF($N3=Lists!$K$3,IF($L3<1,(($U3/$L3)*((1+Inputs!$D$7)^AK$2)),((INT(AK$2/$L3)-INT((AK$2-1)/$L3))*$U3*((1+Inputs!$D$7)^AK$2))),(_xlfn.WEIBULL.DIST(AK$2,$M3,$L3,FALSE)*$U3*((1+Inputs!$D$7)^AK$2))),IF($N3=Lists!$K$3,IF($L3<1,((($T3*(1-$F3)+$S3*(1-$G3))/$L3)*((1+Inputs!$D$7)^AK$2)),((INT(AK$2/$L3)-INT((AK$2-1)/$L3))*($T3*(1-$F3)+$S3*(1-$G3))*((1+Inputs!$D$7)^AK$2))),((_xlfn.WEIBULL.DIST(AK$2,$M3,$L3,FALSE)*($T3*(1-$F3)+$S3*(1-$G3))*((1+Inputs!$D$7)^AK$2)))))) -> 3730.1229 | AL3: =$E3*IF(AL$2>Inputs!$D$5,0,IF(AL$2>VLOOKUP($H3,Lists!$P$3:$Q$7,2),IF($N3=Lists!$K$3,IF($L3<1,(($U3/$L3)*((1+Inputs!$D$7)^AL$2)),((INT(AL$2/$L3)-INT((AL$2-1)/$L3))*$U3*((1+Inputs!$D$7)^AL$2))),(_xlfn.WEIBULL.DIST(AL$2,$M3,$L3,FALSE)*$U3*((1+Inputs!$D$7)^AL$2))),IF($N3=Lists!$K$3,IF($L3<1,((($T3*(1-$F3)+$S3*(1-$G3))/$L3)*((1+Inputs!$D$7)^AL$2)),((INT(AL$2/$L3)-INT((AL$2-1)/$L3))*($T3*(1-$F3)+$S3*(1-$G3))*((1+Inputs!$D$7)^AL$2))),((_xlfn.WEIBULL.DIST(AL$2,$M3,$L3,FALSE)*($T3*(1-$F3)+$S3*(1-$G3))*((1+Inputs!$D$7)^AL$2)))))) -> 3804.7254 | ... BN3: =$E3*IF(BN$2>Inputs!$D$5,0,IF(BN$2>VLOOKUP($H3,Lists!$P$3:$Q$7,2),IF($N3=Lists!$K$3,IF($L3<1,(($U3/$L3)*((1+Inputs!$D$7)^BN$2)),((INT(BN$2/$L3)-INT((BN$2-1)/$L3))*$U3*((1+Inputs!$D$7)^BN$2))),(_xlfn.WEIBULL.DIST(BN$2,$M3,$L3,FALSE)*$U3*((1+Inputs!$D$7)^BN$2))),IF($N3=Lists!$K$3,IF($L3<1,((($T3*(1-$F3)+$S3*(1-$G3))/$L3)*((1+Inputs!$D$7)^BN$2)),((INT(BN$2/$L3)-INT((BN$2-1)/$L3))*($T3*(1-$F3)+$S3*(1-$G3))*((1+Inputs!$D$7)^BN$2))),((_xlfn.WEIBULL.DIST(BN$2,$M3,$L3,FALSE)*($T3*(1-$F3)+$S3*(1-$G3))*((1+Inputs!$D$7)^BN$2)))))) -> 0 | BO3: =NPV(Inputs!$D$6,BQ3:DD3) -> 42700.445 | BP3: =BO3/SUM($Y$3:$Y$136) -> 0.020139615 | BQ3: =MAX(AA3,($E3*IF(BQ$2>Inputs!$D$5,0,IF(BQ$2>VLOOKUP($H3,Lists!$P$3:$Q$7,2),IF($N3=Lists!$K$3,IF($L3<1,(($U3/$L3)*((1+Inputs!$D$7)^BQ$2)),((INT(BQ$2/$L3)-INT((BQ$2-1)/$L3))*$U3*((1+Inputs!$D$7)^BQ$2))),(Inputs!$D$8^((1-_xlfn.WEIBULL.DIST(BQ$2,$M3,$L3,FALSE))/_xlfn.WEIBULL.DIST(BQ$2,$M3,$L3,FALSE))*$U3*((1+Inputs!$D$7)^BQ$2))),IF($N3=Lists!$K$3,IF($L3<1,((($T3*(1-$F3)+$S3*(1-$G3))/$L3)*((1+Inputs!$D$7)^BQ$2)),((INT(BQ$2/$L3)-INT((BQ$2-1)/$L3))*($T3*(1-$F3)+$S3*(1-$G3))*((1+Inputs!$D$7)^BQ$2))),((Inputs!$D$8^((1-_xlfn.WEIBULL.DIST(BQ$2,$M3,$L3,FALSE))/_xlfn.WEIBULL.DIST(BQ$2,$M3,$L3,FALSE))*($T3*(1-$F3)+$S3*(1-$G3))*((1+Inputs!$D$7)^BQ$2)))))))) -> 3060 | BR3: =MAX(AB3,($E3*IF(BR$2>Inputs!$D$5,0,IF(BR$2>VLOOKUP($H3,Lists!$P$3:$Q$7,2),IF($N3=Lists!$K$3,IF($L3<1,(($U3/$L3)*((1+Inputs!$D$7)^BR$2)),((INT(BR$2/$L3)-INT((BR$2-1)/$L3))*$U3*((1+Inputs!$D$7)^BR$2))),(Inputs!$D$8^((1-_xlfn.WEIBULL.DIST(BR$2,$M3,$L3,FALSE))/_xlfn.WEIBULL.DIST(BR$2,$M3,$L3,FALSE))*$U3*((1+Inputs!$D$7)^BR$2))),IF($N3=Lists!$K$3,IF($L3<1,((($T3*(1-$F3)+$S3*(1-$G3))/$L3)*((1+Inputs!$D$7)^BR$2)),((INT(BR$2/$L3)-INT((BR$2-1)/$L3))*($T3*(1-$F3)+$S3*(1-$G3))*((1+Inputs!$D$7)^BR$2))),((Inputs!$D$8^((1-_xlfn.WEIBULL.DIST(BR$2,$M3,$L3,FALSE))/_xlfn.WEIBULL.DIST(BR$2,$M3,$L3,FALSE))*($T3*(1-$F3)+$S3*(1-$G3))*((1+Inputs!$D$7)^BR$2)))))))) -> 3121.2 | BS3: =MAX(AC3,($E3*IF(BS$2>Inputs!$D$5,0,IF(BS$2>VLOOKUP($H3,Lists!$P$3:$Q$7,2),IF($N3=Lists!$K$3,IF($L3<1,(($U3/$L3)*((1+Inputs!$D$7)^BS$2)),((INT(BS$2/$L3)-INT((BS$2-1)/$L3))*$U3*((1+Inputs!$D$7)^BS$2))),(Inputs!$D$8^((1-_xlfn.WEIBULL.DIST(BS$2,$M3,$L3,FALSE))/_xlfn.WEIBULL.DIST(BS$2,$M3,$L3,FALSE))*$U3*((1+Inputs!$D$7)^BS$2))),IF($N3=Lists!$K$3,IF($L3<1,((($T3*(1-$F3)+$S3*(1-$G3))/$L3)*((1+Inputs!$D$7)^BS$2)),((INT(BS$2/$L3)-INT((BS$2-1)/$L3))*($T3*(1-$F3)+$S3*(1-$G3))*((1+Inputs!$D$7)^BS$2))),((Inputs!$D$8^((1-_xlfn.WEIBULL.DIST(BS$2,$M3,$L3,FALSE))/_xlfn.WEIBULL.DIST(BS$2,$M3,$L3,FALSE))*($T3*(1-$F3)+$S3*(1-$G3))*((1+Inputs!$D$7)^BS$2)))))))) -> 3183.624 | BT3: =MAX(AD3,($E3*IF(BT$2>Inputs!$D$5,0,IF(BT$2>VLOOKUP($H3,Lists!$P$3:$Q$7,2),IF($N3=Lists!$K$3,IF($L3<1,(($U3/$L3)*((1+Inputs!$D$7)^BT$2)),((INT(BT$2/$L3)-INT((BT$2-1)/$L3))*$U3*((1+Inputs!$D$7)^BT$2))),(Inputs!$D$8^((1-_xlfn.WEIBULL.DIST(BT$2,$M3,$L3,FALSE))/_xlfn.WEIBULL.DIST(BT$2,$M3,$L3,FALSE))*$U3*((1+Inputs!$D$7)^BT$2))),IF($N3=Lists!$K$3,IF($L3<1,((($T3*(1-$F3)+$S3*(1-$G3))/$L3)*((1+Inputs!$D$7)^BT$2)),((INT(BT$2/$L3)-INT((BT$2-1)/$L3))*($T3*(1-$F3)+$S3*(1-$G3))*((1+Inputs!$D$7)^BT$2))),((Inputs!$D$8^((1-_xlfn.WEIBULL.DIST(BT$2,$M3,$L3,FALSE))/_xlfn.WEIBULL.DIST(BT$2,$M3,$L3,FALSE))*($T3*(1-$F3)+$S3*(1-$G3))*((1+Inputs!$D$7)^BT$2)))))))) -> 3247.2965 | BU3: =MAX(AE3,($E3*IF(BU$2>Inputs!$D$5,0,IF(BU$2>VLOOKUP($H3,Lists!$P$3:$Q$7,2),IF($N3=Lists!$K$3,IF($L3<1,(($U3/$L3)*((1+Inputs!$D$7)^BU$2)),((INT(BU$2/$L3)-INT((BU$2-1)/$L3))*$U3*((1+Inputs!$D$7)^BU$2))),(Inputs!$D$8^((1-_xlfn.WEIBULL.DIST(BU$2,$M3,$L3,FALSE))/_xlfn.WEIBULL.DIST(BU$2,$M3,$L3,FALSE))*$U3*((1+Inputs!$D$7)^BU$2))),IF($N3=Lists!$K$3,IF($L3<1,((($T3*(1-$F3)+$S3*(1-$G3))/$L3)*((1+Inputs!$D$7)^BU$2)),((INT(BU$2/$L3)-INT((BU$2-1)/$L3))*($T3*(1-$F3)+$S3*(1-$G3))*((1+Inputs!$D$7)^BU$2))),((Inputs!$D$8^((1-_xlfn.WEIBULL.DIST(BU$2,$M3,$L3,FALSE))/_xlfn.WEIBULL.DIST(BU$2,$M3,$L3,FALSE))*($T3*(1-$F3)+$S3*(1-$G3))*((1+Inputs!$D$7)^BU$2)))))))) -> 3312.2424 | BV3: =MAX(AF3,($E3*IF(BV$2>Inputs!$D$5,0,IF(BV$2>VLOOKUP($H3,Lists!$P$3:$Q$7,2),IF($N3=Lists!$K$3,IF($L3<1,(($U3/$L3)*((1+Inputs!$D$7)^BV$2)),((INT(BV$2/$L3)-INT((BV$2-1)/$L3))*$U3*((1+Inputs!$D$7)^BV$2))),(Inputs!$D$8^((1-_xlfn.WEIBULL.DIST(BV$2,$M3,$L3,FALSE))/_xlfn.WEIBULL.DIST(BV$2,$M3,$L3,FALSE))*$U3*((1+Inputs!$D$7)^BV$2))),IF($N3=Lists!$K$3,IF($L3<1,((($T3*(1-$F3)+$S3*(1-$G3))/$L3)*((1+Inputs!$D$7)^BV$2)),((INT(BV$2/$L3)-INT((BV$2-1)/$L3))*($T3*(1-$F3)+$S3*(1-$G3))*((1+Inputs!$D$7)^BV$2))),((Inputs!$D$8^((1-_xlfn.WEIBULL.DIST(BV$2,$M3,$L3,FALSE))/_xlfn.WEIBULL.DIST(BV$2,$M3,$L3,FALSE))*($T3*(1-$F3)+$S3*(1-$G3))*((1+Inputs!$D$7)^BV$2)))))))) -> 3378.4873 | BW3: =MAX(AG3,($E3*IF(BW$2>Inputs!$D$5,0,IF(BW$2>VLOOKUP($H3,Lists!$P$3:$Q$7,2),IF($N3=Lists!$K$3,IF($L3<1,(($U3/$L3)*((1+Inputs!$D$7)^BW$2)),((INT(BW$2/$L3)-INT((BW$2-1)/$L3))*$U3*((1+Inputs!$D$7)^BW$2))),(Inputs!$D$8^((1-_xlfn.WEIBULL.DIST(BW$2,$M3,$L3,FALSE))/_xlfn.WEIBULL.DIST(BW$2,$M3,$L3,FALSE))*$U3*((1+Inputs!$D$7)^BW$2))),IF($N3=Lists!$K$3,IF($L3<1,((($T3*(1-$F3)+$S3*(1-$G3))/$L3)*((1+Inputs!$D$7)^BW$2)),((INT(BW$2/$L3)-INT((BW$2-1)/$L3))*($T3*(1-$F3)+$S3*(1-$G3))*((1+Inputs!$D$7)^BW$2))),((Inputs!$D$8^((1-_xlfn.WEIBULL.DIST(BW$2,$M3,$L3,FALSE))/_xlfn.WEIBULL.DIST(BW$2,$M3,$L3,FALSE))*($T3*(1-$F3)+$S3*(1-$G3))*((1+Inputs!$D$7)^BW$2)))))))) -> 3446.057 | BX3: =MAX(AH3,($E3*IF(BX$2>Inputs!$D$5,0,IF(BX$2>VLOOKUP($H3,Lists!$P$3:$Q$7,2),IF($N3=Lists!$K$3,IF($L3<1,(($U3/$L3)*((1+Inputs!$D$7)^BX$2)),((INT(BX$2/$L3)-INT((BX$2-1)/$L3))*$U3*((1+Inputs!$D$7)^BX$2))),(Inputs!$D$8^((1-_xlfn.WEIBULL.DIST(BX$2,$M3,$L3,FALSE))/_xlfn.WEIBULL.DIST(BX$2,$M3,$L3,FALSE))*$U3*((1+Inputs!$D$7)^BX$2))),IF($N3=Lists!$K$3,IF($L3<1,((($T3*(1-$F3)+$S3*(1-$G3))/$L3)*((1+Inputs!$D$7)^BX$2)),((INT(BX$2/$L3)-INT((BX$2-1)/$L3))*($T3*(1-$F3)+$S3*(1-$G3))*((1+Inputs!$D$7)^BX$2))),((Inputs!$D$8^((1-_xlfn.WEIBULL.DIST(BX$2,$M3,$L3,FALSE))/_xlfn.WEIBULL.DIST(BX$2,$M3,$L3,FALSE))*($T3*(1-$F3)+$S3*(1-$G3))*((1+Inputs!$D$7)^BX$2)))))))) -> 3514.9781 | ... DD3: =MAX(BN3,($E3*IF(DD$2>Inputs!$D$5,0,IF(DD$2>VLOOKUP($H3,Lists!$P$3:$Q$7,2),IF($N3=Lists!$K$3,IF($L3<1,(($U3/$L3)*((1+Inputs!$D$7)^DD$2)),((INT(DD$2/$L3)-INT((DD$2-1)/$L3))*$U3*((1+Inputs!$D$7)^DD$2))),(Inputs!$D$8^((1-_xlfn.WEIBULL.DIST(DD$2,$M3,$L3,FALSE))/_xlfn.WEIBULL.DIST(DD$2,$M3,$L3,FALSE))*$U3*((1+Inputs!$D$7)^DD$2))),IF($N3=Lists!$K$3,IF($L3<1,((($T3*(1-$F3)+$S3*(1-$G3))/$L3)*((1+Inputs!$D$7)^DD$2)),((INT(DD$2/$L3)-INT((DD$2-1)/$L3))*($T3*(1-$F3)+$S3*(1-$G3))*((1+Inputs!$D$7)^DD$2))),((Inputs!$D$8^((1-_xlfn.WEIBULL.DIST(DD$2,$M3,$L3,FALSE))/_xlfn.WEIBULL.DIST(DD$2,$M3,$L3,FALSE))*($T3*(1-$F3)+$S3*(1-$G3))*((1+Inputs!$D$7)^DD$2)))))))) -> 0
A4: Manage inventory of spare parts | B4: Administration | C4: Management | D4: Asset Management | E4: =IF(Inputs!$D$41=Lists!$I$4,0,1) -> 1 | F4: 0 | G4: 0 | H4: Monitoring | J4: Administrator | K4: =VLOOKUP(J4,'Labor Rates'!$A$1:$F$16,2) -> 22.995577 | L4: 0.5 | M4: 1 | N4: interval | O4: 1 | P4: 1 | Q4: =O4*P4/L4 -> 2 | R4: 0 | S4: =P4*O4*K4 -> 22.995577 | T4: =R4*O4 -> 0 | U4: =E4*(T4+S4) -> 22.995577 | X4: =AVERAGE(AA4:AT4) -> 56.990668 | Y4: =NPV(Inputs!$D$6,AA4:BN4) -> 654.61425 | Z4: =Y4/SUM($Y$3:$Y$136) -> 0.00030874804 | AA4: =$E4*IF(AA$2>Inputs!$D$5,0,IF(AA$2>VLOOKUP($H4,Lists!$P$3:$Q$7,2),IF($N4=Lists!$K$3,IF($L4<1,(($U4/$L4)*((1+Inputs!$D$7)^AA$2)),((INT(AA$2/$L4)-INT((AA$2-1)/$L4))*$U4*((1+Inputs!$D$7)^AA$2))),(_xlfn.WEIBULL.DIST(AA$2,$M4,$L4,FALSE)*$U4*((1+Inputs!$D$7)^AA$2))),IF($N4=Lists!$K$3,IF($L4<1,((($T4*(1-$F4)+$S4*(1-$G4))/$L4)*((1+Inputs!$D$7)^AA$2)),((INT(AA$2/$L4)-INT((AA$2-1)/$L4))*($T4*(1-$F4)+$S4*(1-$G4))*((1+Inputs!$D$7)^AA$2))),((_xlfn.WEIBULL.DIST(AA$2,$M4,$L4,FALSE)*($T4*(1-$F4)+$S4*(1-$G4))*((1+Inputs!$D$7)^AA$2)))))) -> 46.910977 | AB4: =$E4*IF(AB$2>Inputs!$D$5,0,IF(AB$2>VLOOKUP($H4,Lists!$P$3:$Q$7,2),IF($N4=Lists!$K$3,IF($L4<1,(($U4/$L4)*((1+Inputs!$D$7)^AB$2)),((INT(AB$2/$L4)-INT((AB$2-1)/$L4))*$U4*((1+Inputs!$D$7)^AB$2))),(_xlfn.WEIBULL.DIST(AB$2,$M4,$L4,FALSE)*$U4*((1+Inputs!$D$7)^AB$2))),IF($N4=Lists!$K$3,IF($L4<1,((($T4*(1-$F4)+$S4*(1-$G4))/$L4)*((1+Inputs!$D$7)^AB$2)),((INT(AB$2/$L4)-INT((AB$2-1)/$L4))*($T4*(1-$F4)+$S4*(1-$G4))*((1+Inputs!$D$7)^AB$2))),((_xlfn.WEIBULL.DIST(AB$2,$M4,$L4,FALSE)*($T4*(1-$F4)+$S4*(1-$G4))*((1+Inputs!$D$7)^AB$2)))))) -> 47.849196 | AC4: =$E4*IF(AC$2>Inputs!$D$5,0,IF(AC$2>VLOOKUP($H4,Lists!$P$3:$Q$7,2),IF($N4=Lists!$K$3,IF($L4<1,(($U4/$L4)*((1+Inputs!$D$7)^AC$2)),((INT(AC$2/$L4)-INT((AC$2-1)/$L4))*$U4*((1+Inputs!$D$7)^AC$2))),(_xlfn.WEIBULL.DIST(AC$2,$M4,$L4,FALSE)*$U4*((1+Inputs!$D$7)^AC$2))),IF($N4=Lists!$K$3,IF($L4<1,((($T4*(1-$F4)+$S4*(1-$G4))/$L4)*((1+Inputs!$D$7)^AC$2)),((INT(AC$2/$L4)-INT((AC$2-1)/$L4))*($T4*(1-$F4)+$S4*(1-$G4))*((1+Inputs!$D$7)^AC$2))),((_xlfn.WEIBULL.DIST(AC$2,$M4,$L4,FALSE)*($T4*(1-$F4)+$S4*(1-$G4))*((1+Inputs!$D$7)^AC$2)))))) -> 48.80618 | AD4: =$E4*IF(AD$2>Inputs!$D$5,0,IF(AD$2>VLOOKUP($H4,Lists!$P$3:$Q$7,2),IF($N4=Lists!$K$3,IF($L4<1,(($U4/$L4)*((1+Inputs!$D$7)^AD$2)),((INT(AD$2/$L4)-INT((AD$2-1)/$L4))*$U4*((1+Inputs!$D$7)^AD$2))),(_xlfn.WEIBULL.DIST(AD$2,$M4,$L4,FALSE)*$U4*((1+Inputs!$D$7)^AD$2))),IF($N4=Lists!$K$3,IF($L4<1,((($T4*(1-$F4)+$S4*(1-$G4))/$L4)*((1+Inputs!$D$7)^AD$2)),((INT(AD$2/$L4)-INT((AD$2-1)/$L4))*($T4*(1-$F4)+$S4*(1-$G4))*((1+Inputs!$D$7)^AD$2))),((_xlfn.WEIBULL.DIST(AD$2,$M4,$L4,FALSE)*($T4*(1-$F4)+$S4*(1-$G4))*((1+Inputs!$D$7)^AD$2)))))) -> 49.782304 | AE4: =$E4*IF(AE$2>Inputs!$D$5,0,IF(AE$2>VLOOKUP($H4,Lists!$P$3:$Q$7,2),IF($N4=Lists!$K$3,IF($L4<1,(($U4/$L4)*((1+Inputs!$D$7)^AE$2)),((INT(AE$2/$L4)-INT((AE$2-1)/$L4))*$U4*((1+Inputs!$D$7)^AE$2))),(_xlfn.WEIBULL.DIST(AE$2,$M4,$L4,FALSE)*$U4*((1+Inputs!$D$7)^AE$2))),IF($N4=Lists!$K$3,IF($L4<1,((($T4*(1-$F4)+$S4*(1-$G4))/$L4)*((1+Inputs!$D$7)^AE$2)),((INT(AE$2/$L4)-INT((AE$2-1)/$L4))*($T4*(1-$F4)+$S4*(1-$G4))*((1+Inputs!$D$7)^AE$2))),((_xlfn.WEIBULL.DIST(AE$2,$M4,$L4,FALSE)*($T4*(1-$F4)+$S4*(1-$G4))*((1+Inputs!$D$7)^AE$2)))))) -> 50.77795 | AF4: =$E4*IF(AF$2>Inputs!$D$5,0,IF(AF$2>VLOOKUP($H4,Lists!$P$3:$Q$7,2),IF($N4=Lists!$K$3,IF($L4<1,(($U4/$L4)*((1+Inputs!$D$7)^AF$2)),((INT(AF$2/$L4)-INT((AF$2-1)/$L4))*$U4*((1+Inputs!$D$7)^AF$2))),(_xlfn.WEIBULL.DIST(AF$2,$M4,$L4,FALSE)*$U4*((1+Inputs!$D$7)^AF$2))),IF($N4=Lists!$K$3,IF($L4<1,((($T4*(1-$F4)+$S4*(1-$G4))/$L4)*((1+Inputs!$D$7)^AF$2)),((INT(AF$2/$L4)-INT((AF$2-1)/$L4))*($T4*(1-$F4)+$S4*(1-$G4))*((1+Inputs!$D$7)^AF$2))),((_xlfn.WEIBULL.DIST(AF$2,$M4,$L4,FALSE)*($T4*(1-$F4)+$S4*(1-$G4))*((1+Inputs!$D$7)^AF$2)))))) -> 51.793509 | AG4: =$E4*IF(AG$2>Inputs!$D$5,0,IF(AG$2>VLOOKUP($H4,Lists!$P$3:$Q$7,2),IF($N4=Lists!$K$3,IF($L4<1,(($U4/$L4)*((1+Inputs!$D$7)^AG$2)),((INT(AG$2/$L4)-INT((AG$2-1)/$L4))*$U4*((1+Inputs!$D$7)^AG$2))),(_xlfn.WEIBULL.DIST(AG$2,$M4,$L4,FALSE)*$U4*((1+Inputs!$D$7)^AG$2))),IF($N4=Lists!$K$3,IF($L4<1,((($T4*(1-$F4)+$S4*(1-$G4))/$L4)*((1+Inputs!$D$7)^AG$2)),((INT(AG$2/$L4)-INT((AG$2-1)/$L4))*($T4*(1-$F4)+$S4*(1-$G4))*((1+Inputs!$D$7)^AG$2))),((_xlfn.WEIBULL.DIST(AG$2,$M4,$L4,FALSE)*($T4*(1-$F4)+$S4*(1-$G4))*((1+Inputs!$D$7)^AG$2)))))) -> 52.829379 | AH4: =$E4*IF(AH$2>Inputs!$D$5,0,IF(AH$2>VLOOKUP($H4,Lists!$P$3:$Q$7,2),IF($N4=Lists!$K$3,IF($L4<1,(($U4/$L4)*((1+Inputs!$D$7)^AH$2)),((INT(AH$2/$L4)-INT((AH$2-1)/$L4))*$U4*((1+Inputs!$D$7)^AH$2))),(_xlfn.WEIBULL.DIST(AH$2,$M4,$L4,FALSE)*$U4*((1+Inputs!$D$7)^AH$2))),IF($N4=Lists!$K$3,IF($L4<1,((($T4*(1-$F4)+$S4*(1-$G4))/$L4)*((1+Inputs!$D$7)^AH$2)),((INT(AH$2/$L4)-INT((AH$2-1)/$L4))*($T4*(1-$F4)+$S4*(1-$G4))*((1+Inputs!$D$7)^AH$2))),((_xlfn.WEIBULL.DIST(AH$2,$M4,$L4,FALSE)*($T4*(1-$F4)+$S4*(1-$G4))*((1+Inputs!$D$7)^AH$2)))))) -> 53.885967 | ... BN4: =$E4*IF(BN$2>Inputs!$D$5,0,IF(BN$2>VLOOKUP($H4,Lists!$P$3:$Q$7,2),IF($N4=Lists!$K$3,IF($L4<1,(($U4/$L4)*((1+Inputs!$D$7)^BN$2)),((INT(BN$2/$L4)-INT((BN$2-1)/$L4))*$U4*((1+Inputs!$D$7)^BN$2))),(_xlfn.WEIBULL.DIST(BN$2,$M4,$L4,FALSE)*$U4*((1+Inputs!$D$7)^BN$2))),IF($N4=Lists!$K$3,IF($L4<1,((($T4*(1-$F4)+$S4*(1-$G4))/$L4)*((1+Inputs!$D$7)^BN$2)),((INT(BN$2/$L4)-INT((BN$2-1)/$L4))*($T4*(1-$F4)+$S4*(1-$G4))*((1+Inputs!$D$7)^BN$2))),((_xlfn.WEIBULL.DIST(BN$2,$M4,$L4,FALSE)*($T4*(1-$F4)+$S4*(1-$G4))*((1+Inputs!$D$7)^BN$2)))))) -> 0 | BO4: =NPV(Inputs!$D$6,BQ4:DD4) -> 654.61425 | BP4: =BO4/SUM($Y$3:$Y$136) -> 0.00030874804 | BQ4: =MAX(AA4,($E4*IF(BQ$2>Inputs!$D$5,0,IF(BQ$2>VLOOKUP($H4,Lists!$P$3:$Q$7,2),IF($N4=Lists!$K$3,IF($L4<1,(($U4/$L4)*((1+Inputs!$D$7)^BQ$2)),((INT(BQ$2/$L4)-INT((BQ$2-1)/$L4))*$U4*((1+Inputs!$D$7)^BQ$2))),(Inputs!$D$8^((1-_xlfn.WEIBULL.DIST(BQ$2,$M4,$L4,FALSE))/_xlfn.WEIBULL.DIST(BQ$2,$M4,$L4,FALSE))*$U4*((1+Inputs!$D$7)^BQ$2))),IF($N4=Lists!$K$3,IF($L4<1,((($T4*(1-$F4)+$S4*(1-$G4))/$L4)*((1+Inputs!$D$7)^BQ$2)),((INT(BQ$2/$L4)-INT((BQ$2-1)/$L4))*($T4*(1-$F4)+$S4*(1-$G4))*((1+Inputs!$D$7)^BQ$2))),((Inputs!$D$8^((1-_xlfn.WEIBULL.DIST(BQ$2,$M4,$L4,FALSE))/_xlfn.WEIBULL.DIST(BQ$2,$M4,$L4,FALSE))*($T4*(1-$F4)+$S4*(1-$G4))*((1+Inputs!$D$7)^BQ$2)))))))) -> 46.910977 | BR4: =MAX(AB4,($E4*IF(BR$2>Inputs!$D$5,0,IF(BR$2>VLOOKUP($H4,Lists!$P$3:$Q$7,2),IF($N4=Lists!$K$3,IF($L4<1,(($U4/$L4)*((1+Inputs!$D$7)^BR$2)),((INT(BR$2/$L4)-INT((BR$2-1)/$L4))*$U4*((1+Inputs!$D$7)^BR$2))),(Inputs!$D$8^((1-_xlfn.WEIBULL.DIST(BR$2,$M4,$L4,FALSE))/_xlfn.WEIBULL.DIST(BR$2,$M4,$L4,FALSE))*$U4*((1+Inputs!$D$7)^BR$2))),IF($N4=Lists!$K$3,IF($L4<1,((($T4*(1-$F4)+$S4*(1-$G4))/$L4)*((1+Inputs!$D$7)^BR$2)),((INT(BR$2/$L4)-INT((BR$2-1)/$L4))*($T4*(1-$F4)+$S4*(1-$G4))*((1+Inputs!$D$7)^BR$2))),((Inputs!$D$8^((1-_xlfn.WEIBULL.DIST(BR$2,$M4,$L4,FALSE))/_xlfn.WEIBULL.DIST(BR$2,$M4,$L4,FALSE))*($T4*(1-$F4)+$S4*(1-$G4))*((1+Inputs!$D$7)^BR$2)))))))) -> 47.849196 | BS4: =MAX(AC4,($E4*IF(BS$2>Inputs!$D$5,0,IF(BS$2>VLOOKUP($H4,Lists!$P$3:$Q$7,2),IF($N4=Lists!$K$3,IF($L4<1,(($U4/$L4)*((1+Inputs!$D$7)^BS$2)),((INT(BS$2/$L4)-INT((BS$2-1)/$L4))*$U4*((1+Inputs!$D$7)^BS$2))),(Inputs!$D$8^((1-_xlfn.WEIBULL.DIST(BS$2,$M4,$L4,FALSE))/_xlfn.WEIBULL.DIST(BS$2,$M4,$L4,FALSE))*$U4*((1+Inputs!$D$7)^BS$2))),IF($N4=Lists!$K$3,IF($L4<1,((($T4*(1-$F4)+$S4*(1-$G4))/$L4)*((1+Inputs!$D$7)^BS$2)),((INT(BS$2/$L4)-INT((BS$2-1)/$L4))*($T4*(1-$F4)+$S4*(1-$G4))*((1+Inputs!$D$7)^BS$2))),((Inputs!$D$8^((1-_xlfn.WEIBULL.DIST(BS$2,$M4,$L4,FALSE))/_xlfn.WEIBULL.DIST(BS$2,$M4,$L4,FALSE))*($T4*(1-$F4)+$S4*(1-$G4))*((1+Inputs!$D$7)^BS$2)))))))) -> 48.80618 | BT4: =MAX(AD4,($E4*IF(BT$2>Inputs!$D$5,0,IF(BT$2>VLOOKUP($H4,Lists!$P$3:$Q$7,2),IF($N4=Lists!$K$3,IF($L4<1,(($U4/$L4)*((1+Inputs!$D$7)^BT$2)),((INT(BT$2/$L4)-INT((BT$2-1)/$L4))*$U4*((1+Inputs!$D$7)^BT$2))),(Inputs!$D$8^((1-_xlfn.WEIBULL.DIST(BT$2,$M4,$L4,FALSE))/_xlfn.WEIBULL.DIST(BT$2,$M4,$L4,FALSE))*$U4*((1+Inputs!$D$7)^BT$2))),IF($N4=Lists!$K$3,IF($L4<1,((($T4*(1-$F4)+$S4*(1-$G4))/$L4)*((1+Inputs!$D$7)^BT$2)),((INT(BT$2/$L4)-INT((BT$2-1)/$L4))*($T4*(1-$F4)+$S4*(1-$G4))*((1+Inputs!$D$7)^BT$2))),((Inputs!$D$8^((1-_xlfn.WEIBULL.DIST(BT$2,$M4,$L4,FALSE))/_xlfn.WEIBULL.DIST(BT$2,$M4,$L4,FALSE))*($T4*(1-$F4)+$S4*(1-$G4))*((1+Inputs!$D$7)^BT$2)))))))) -> 49.782304 | BU4: =MAX(AE4,($E4*IF(BU$2>Inputs!$D$5,0,IF(BU$2>VLOOKUP($H4,Lists!$P$3:$Q$7,2),IF($N4=Lists!$K$3,IF($L4<1,(($U4/$L4)*((1+Inputs!$D$7)^BU$2)),((INT(BU$2/$L4)-INT((BU$2-1)/$L4))*$U4*((1+Inputs!$D$7)^BU$2))),(Inputs!$D$8^((1-_xlfn.WEIBULL.DIST(BU$2,$M4,$L4,FALSE))/_xlfn.WEIBULL.DIST(BU$2,$M4,$L4,FALSE))*$U4*((1+Inputs!$D$7)^BU$2))),IF($N4=Lists!$K$3,IF($L4<1,((($T4*(1-$F4)+$S4*(1-$G4))/$L4)*((1+Inputs!$D$7)^BU$2)),((INT(BU$2/$L4)-INT((BU$2-1)/$L4))*($T4*(1-$F4)+$S4*(1-$G4))*((1+Inputs!$D$7)^BU$2))),((Inputs!$D$8^((1-_xlfn.WEIBULL.DIST(BU$2,$M4,$L4,FALSE))/_xlfn.WEIBULL.DIST(BU$2,$M4,$L4,FALSE))*($T4*(1-$F4)+$S4*(1-$G4))*((1+Inputs!$D$7)^BU$2)))))))) -> 50.77795 | BV4: =MAX(AF4,($E4*IF(BV$2>Inputs!$D$5,0,IF(BV$2>VLOOKUP($H4,Lists!$P$3:$Q$7,2),IF($N4=Lists!$K$3,IF($L4<1,(($U4/$L4)*((1+Inputs!$D$7)^BV$2)),((INT(BV$2/$L4)-INT((BV$2-1)/$L4))*$U4*((1+Inputs!$D$7)^BV$2))),(Inputs!$D$8^((1-_xlfn.WEIBULL.DIST(BV$2,$M4,$L4,FALSE))/_xlfn.WEIBULL.DIST(BV$2,$M4,$L4,FALSE))*$U4*((1+Inputs!$D$7)^BV$2))),IF($N4=Lists!$K$3,IF($L4<1,((($T4*(1-$F4)+$S4*(1-$G4))/$L4)*((1+Inputs!$D$7)^BV$2)),((INT(BV$2/$L4)-INT((BV$2-1)/$L4))*($T4*(1-$F4)+$S4*(1-$G4))*((1+Inputs!$D$7)^BV$2))),((Inputs!$D$8^((1-_xlfn.WEIBULL.DIST(BV$2,$M4,$L4,FALSE))/_xlfn.WEIBULL.DIST(BV$2,$M4,$L4,FALSE))*($T4*(1-$F4)+$S4*(1-$G4))*((1+Inputs!$D$7)^BV$2)))))))) -> 51.793509 | BW4: =MAX(AG4,($E4*IF(BW$2>Inputs!$D$5,0,IF(BW$2>VLOOKUP($H4,Lists!$P$3:$Q$7,2),IF($N4=Lists!$K$3,IF($L4<1,(($U4/$L4)*((1+Inputs!$D$7)^BW$2)),((INT(BW$2/$L4)-INT((BW$2-1)/$L4))*$U4*((1+Inputs!$D$7)^BW$2))),(Inputs!$D$8^((1-_xlfn.WEIBULL.DIST(BW$2,$M4,$L4,FALSE))/_xlfn.WEIBULL.DIST(BW$2,$M4,$L4,FALSE))*$U4*((1+Inputs!$D$7)^BW$2))),IF($N4=Lists!$K$3,IF($L4<1,((($T4*(1-$F4)+$S4*(1-$G4))/$L4)*((1+Inputs!$D$7)^BW$2)),((INT(BW$2/$L4)-INT((BW$2-1)/$L4))*($T4*(1-$F4)+$S4*(1-$G4))*((1+Inputs!$D$7)^BW$2))),((Inputs!$D$8^((1-_xlfn.WEIBULL.DIST(BW$2,$M4,$L4,FALSE))/_xlfn.WEIBULL.DIST(BW$2,$M4,$L4,FALSE))*($T4*(1-$F4)+$S4*(1-$G4))*((1+Inputs!$D$7)^BW$2)))))))) -> 52.829379 | BX4: =MAX(AH4,($E4*IF(BX$2>Inputs!$D$5,0,IF(BX$2>VLOOKUP($H4,Lists!$P$3:$Q$7,2),IF($N4=Lists!$K$3,IF($L4<1,(($U4/$L4)*((1+Inputs!$D$7)^BX$2)),((INT(BX$2/$L4)-INT((BX$2-1)/$L4))*$U4*((1+Inputs!$D$7)^BX$2))),(Inputs!$D$8^((1-_xlfn.WEIBULL.DIST(BX$2,$M4,$L4,FALSE))/_xlfn.WEIBULL.DIST(BX$2,$M4,$L4,FALSE))*$U4*((1+Inputs!$D$7)^BX$2))),IF($N4=Lists!$K$3,IF($L4<1,((($T4*(1-$F4)+$S4*(1-$G4))/$L4)*((1+Inputs!$D$7)^BX$2)),((INT(BX$2/$L4)-INT((BX$2-1)/$L4))*($T4*(1-$F4)+$S4*(1-$G4))*((1+Inputs!$D$7)^BX$2))),((Inputs!$D$8^((1-_xlfn.WEIBULL.DIST(BX$2,$M4,$L4,FALSE))/_xlfn.WEIBULL.DIST(BX$2,$M4,$L4,FALSE))*($T4*(1-$F4)+$S4*(1-$G4))*((1+Inputs!$D$7)^BX$2)))))))) -> 53.885967 | ... DD4: =MAX(BN4,($E4*IF(DD$2>Inputs!$D$5,0,IF(DD$2>VLOOKUP($H4,Lists!$P$3:$Q$7,2),IF($N4=Lists!$K$3,IF($L4<1,(($U4/$L4)*((1+Inputs!$D$7)^DD$2)),((INT(DD$2/$L4)-INT((DD$2-1)/$L4))*$U4*((1+Inputs!$D$7)^DD$2))),(Inputs!$D$8^((1-_xlfn.WEIBULL.DIST(DD$2,$M4,$L4,FALSE))/_xlfn.WEIBULL.DIST(DD$2,$M4,$L4,FALSE))*$U4*((1+Inputs!$D$7)^DD$2))),IF($N4=Lists!$K$3,IF($L4<1,((($T4*(1-$F4)+$S4*(1-$G4))/$L4)*((1+Inputs!$D$7)^DD$2)),((INT(DD$2/$L4)-INT((DD$2-1)/$L4))*($T4*(1-$F4)+$S4*(1-$G4))*((1+Inputs!$D$7)^DD$2))),((Inputs!$D$8^((1-_xlfn.WEIBULL.DIST(DD$2,$M4,$L4,FALSE))/_xlfn.WEIBULL.DIST(DD$2,$M4,$L4,FALSE))*($T4*(1-$F4)+$S4*(1-$G4))*((1+Inputs!$D$7)^DD$2)))))))) -> 0
A5: Meet with key site staff to continue awareness, question any issues, and report on findings. | B5: Administration | C5: Management | D5: Documents | E5: =IF(Inputs!D41=Lists!I4,0,1) -> 1 | F5: 0 | G5: 0 | H5: N/A | J5: Administrator | K5: =VLOOKUP(J5,'Labor Rates'!$A$1:$F$16,2) -> 22.995577 | L5: 1 | M5: 1 | N5: interval | O5: 1 | P5: 2 | Q5: =O5*P5/L5 -> 2 | R5: 0 | S5: =P5*O5*K5 -> 45.991154 | T5: =R5*O5 -> 0 | U5: =E5*(T5+S5) -> 45.991154 | X5: =AVERAGE(AA5:AT5) -> 56.990668 | Y5: =NPV(Inputs!$D$6,AA5:BN5) -> 654.61425 | Z5: =Y5/SUM($Y$3:$Y$136) -> 0.00030874804 | AA5: =$E5*IF(AA$2>Inputs!$D$5,0,IF(AA$2>VLOOKUP($H5,Lists!$P$3:$Q$7,2),IF($N5=Lists!$K$3,IF($L5<1,(($U5/$L5)*((1+Inputs!$D$7)^AA$2)),((INT(AA$2/$L5)-INT((AA$2-1)/$L5))*$U5*((1+Inputs!$D$7)^AA$2))),(_xlfn.WEIBULL.DIST(AA$2,$M5,$L5,FALSE)*$U5*((1+Inputs!$D$7)^AA$2))),IF($N5=Lists!$K$3,IF($L5<1,((($T5*(1-$F5)+$S5*(1-$G5))/$L5)*((1+Inputs!$D$7)^AA$2)),((INT(AA$2/$L5)-INT((AA$2-1)/$L5))*($T5*(1-$F5)+$S5*(1-$G5))*((1+Inputs!$D$7)^AA$2))),((_xlfn.WEIBULL.DIST(AA$2,$M5,$L5,FALSE)*($T5*(1-$F5)+$S5*(1-$G5))*((1+Inputs!$D$7)^AA$2)))))) -> 46.910977 | AB5: =$E5*IF(AB$2>Inputs!$D$5,0,IF(AB$2>VLOOKUP($H5,Lists!$P$3:$Q$7,2),IF($N5=Lists!$K$3,IF($L5<1,(($U5/$L5)*((1+Inputs!$D$7)^AB$2)),((INT(AB$2/$L5)-INT((AB$2-1)/$L5))*$U5*((1+Inputs!$D$7)^AB$2))),(_xlfn.WEIBULL.DIST(AB$2,$M5,$L5,FALSE)*$U5*((1+Inputs!$D$7)^AB$2))),IF($N5=Lists!$K$3,IF($L5<1,((($T5*(1-$F5)+$S5*(1-$G5))/$L5)*((1+Inputs!$D$7)^AB$2)),((INT(AB$2/$L5)-INT((AB$2-1)/$L5))*($T5*(1-$F5)+$S5*(1-$G5))*((1+Inputs!$D$7)^AB$2))),((_xlfn.WEIBULL.DIST(AB$2,$M5,$L5,FALSE)*($T5*(1-$F5)+$S5*(1-$G5))*((1+Inputs!$D$7)^AB$2)))))) -> 47.849196 | AC5: =$E5*IF(AC$2>Inputs!$D$5,0,IF(AC$2>VLOOKUP($H5,Lists!$P$3:$Q$7,2),IF($N5=Lists!$K$3,IF($L5<1,(($U5/$L5)*((1+Inputs!$D$7)^AC$2)),((INT(AC$2/$L5)-INT((AC$2-1)/$L5))*$U5*((1+Inputs!$D$7)^AC$2))),(_xlfn.WEIBULL.DIST(AC$2,$M5,$L5,FALSE)*$U5*((1+Inputs!$D$7)^AC$2))),IF($N5=Lists!$K$3,IF($L5<1,((($T5*(1-$F5)+$S5*(1-$G5))/$L5)*((1+Inputs!$D$7)^AC$2)),((INT(AC$2/$L5)-INT((AC$2-1)/$L5))*($T5*(1-$F5)+$S5*(1-$G5))*((1+Inputs!$D$7)^AC$2))),((_xlfn.WEIBULL.DIST(AC$2,$M5,$L5,FALSE)*($T5*(1-$F5)+$S5*(1-$G5))*((1+Inputs!$D$7)^AC$2)))))) -> 48.80618 | AD5: =$E5*IF(AD$2>Inputs!$D$5,0,IF(AD$2>VLOOKUP($H5,Lists!$P$3:$Q$7,2),IF($N5=Lists!$K$3,IF($L5<1,(($U5/$L5)*((1+Inputs!$D$7)^AD$2)),((INT(AD$2/$L5)-INT((AD$2-1)/$L5))*$U5*((1+Inputs!$D$7)^AD$2))),(_xlfn.WEIBULL.DIST(AD$2,$M5,$L5,FALSE)*$U5*((1+Inputs!$D$7)^AD$2))),IF($N5=Lists!$K$3,IF($L5<1,((($T5*(1-$F5)+$S5*(1-$G5))/$L5)*((1+Inputs!$D$7)^AD$2)),((INT(AD$2/$L5)-INT((AD$2-1)/$L5))*($T5*(1-$F5)+$S5*(1-$G5))*((1+Inputs!$D$7)^AD$2))),((_xlfn.WEIBULL.DIST(AD$2,$M5,$L5,FALSE)*($T5*(1-$F5)+$S5*(1-$G5))*((1+Inputs!$D$7)^AD$2)))))) -> 49.782304 | AE5: =$E5*IF(AE$2>Inputs!$D$5,0,IF(AE$2>VLOOKUP($H5,Lists!$P$3:$Q$7,2),IF($N5=Lists!$K$3,IF($L5<1,(($U5/$L5)*((1+Inputs!$D$7)^AE$2)),((INT(AE$2/$L5)-INT((AE$2-1)/$L5))*$U5*((1+Inputs!$D$7)^AE$2))),(_xlfn.WEIBULL.DIST(AE$2,$M5,$L5,FALSE)*$U5*((1+Inputs!$D$7)^AE$2))),IF($N5=Lists!$K$3,IF($L5<1,((($T5*(1-$F5)+$S5*(1-$G5))/$L5)*((1+Inputs!$D$7)^AE$2)),((INT(AE$2/$L5)-INT((AE$2-1)/$L5))*($T5*(1-$F5)+$S5*(1-$G5))*((1+Inputs!$D$7)^AE$2))),((_xlfn.WEIBULL.DIST(AE$2,$M5,$L5,FALSE)*($T5*(1-$F5)+$S5*(1-$G5))*((1+Inputs!$D$7)^AE$2)))))) -> 50.77795 | AF5: =$E5*IF(AF$2>Inputs!$D$5,0,IF(AF$2>VLOOKUP($H5,Lists!$P$3:$Q$7,2),IF($N5=Lists!$K$3,IF($L5<1,(($U5/$L5)*((1+Inputs!$D$7)^AF$2)),((INT(AF$2/$L5)-INT((AF$2-1)/$L5))*$U5*((1+Inputs!$D$7)^AF$2))),(_xlfn.WEIBULL.DIST(AF$2,$M5,$L5,FALSE)*$U5*((1+Inputs!$D$7)^AF$2))),IF($N5=Lists!$K$3,IF($L5<1,((($T5*(1-$F5)+$S5*(1-$G5))/$L5)*((1+Inputs!$D$7)^AF$2)),((INT(AF$2/$L5)-INT((AF$2-1)/$L5))*($T5*(1-$F5)+$S5*(1-$G5))*((1+Inputs!$D$7)^AF$2))),((_xlfn.WEIBULL.DIST(AF$2,$M5,$L5,FALSE)*($T5*(1-$F5)+$S5*(1-$G5))*((1+Inputs!$D$7)^AF$2)))))) -> 51.793509 | AG5: =$E5*IF(AG$2>Inputs!$D$5,0,IF(AG$2>VLOOKUP($H5,Lists!$P$3:$Q$7,2),IF($N5=Lists!$K$3,IF($L5<1,(($U5/$L5)*((1+Inputs!$D$7)^AG$2)),((INT(AG$2/$L5)-INT((AG$2-1)/$L5))*$U5*((1+Inputs!$D$7)^AG$2))),(_xlfn.WEIBULL.DIST(AG$2,$M5,$L5,FALSE)*$U5*((1+Inputs!$D$7)^AG$2))),IF($N5=Lists!$K$3,IF($L5<1,((($T5*(1-$F5)+$S5*(1-$G5))/$L5)*((1+Inputs!$D$7)^AG$2)),((INT(AG$2/$L5)-INT((AG$2-1)/$L5))*($T5*(1-$F5)+$S5*(1-$G5))*((1+Inputs!$D$7)^AG$2))),((_xlfn.WEIBULL.DIST(AG$2,$M5,$L5,FALSE)*($T5*(1-$F5)+$S5*(1-$G5))*((1+Inputs!$D$7)^AG$2)))))) -> 52.829379 | AH5: =$E5*IF(AH$2>Inputs!$D$5,0,IF(AH$2>VLOOKUP($H5,Lists!$P$3:$Q$7,2),IF($N5=Lists!$K$3,IF($L5<1,(($U5/$L5)*((1+Inputs!$D$7)^AH$2)),((INT(AH$2/$L5)-INT((AH$2-1)/$L5))*$U5*((1+Inputs!$D$7)^AH$2))),(_xlfn.WEIBULL.DIST(AH$2,$M5,$L5,FALSE)*$U5*((1+Inputs!$D$7)^AH$2))),IF($N5=Lists!$K$3,IF($L5<1,((($T5*(1-$F5)+$S5*(1-$G5))/$L5)*((1+Inputs!$D$7)^AH$2)),((INT(AH$2/$L5)-INT((AH$2-1)/$L5))*($T5*(1-$F5)+$S5*(1-$G5))*((1+Inputs!$D$7)^AH$2))),((_xlfn.WEIBULL.DIST(AH$2,$M5,$L5,FALSE)*($T5*(1-$F5)+$S5*(1-$G5))*((1+Inputs!$D$7)^AH$2)))))) -> 53.885967 | ... BN5: =$E5*IF(BN$2>Inputs!$D$5,0,IF(BN$2>VLOOKUP($H5,Lists!$P$3:$Q$7,2),IF($N5=Lists!$K$3,IF($L5<1,(($U5/$L5)*((1+Inputs!$D$7)^BN$2)),((INT(BN$2/$L5)-INT((BN$2-1)/$L5))*$U5*((1+Inputs!$D$7)^BN$2))),(_xlfn.WEIBULL.DIST(BN$2,$M5,$L5,FALSE)*$U5*((1+Inputs!$D$7)^BN$2))),IF($N5=Lists!$K$3,IF($L5<1,((($T5*(1-$F5)+$S5*(1-$G5))/$L5)*((1+Inputs!$D$7)^BN$2)),((INT(BN$2/$L5)-INT((BN$2-1)/$L5))*($T5*(1-$F5)+$S5*(1-$G5))*((1+Inputs!$D$7)^BN$2))),((_xlfn.WEIBULL.DIST(BN$2,$M5,$L5,FALSE)*($T5*(1-$F5)+$S5*(1-$G5))*((1+Inputs!$D$7)^BN$2)))))) -> 0 | BO5: =NPV(Inputs!$D$6,BQ5:DD5) -> 654.61425 | BP5: =BO5/SUM($Y$3:$Y$136) -> 0.00030874804 | BQ5: =MAX(AA5,($E5*IF(BQ$2>Inputs!$D$5,0,IF(BQ$2>VLOOKUP($H5,Lists!$P$3:$Q$7,2),IF($N5=Lists!$K$3,IF($L5<1,(($U5/$L5)*((1+Inputs!$D$7)^BQ$2)),((INT(BQ$2/$L5)-INT((BQ$2-1)/$L5))*$U5*((1+Inputs!$D$7)^BQ$2))),(Inputs!$D$8^((1-_xlfn.WEIBULL.DIST(BQ$2,$M5,$L5,FALSE))/_xlfn.WEIBULL.DIST(BQ$2,$M5,$L5,FALSE))*$U5*((1+Inputs!$D$7)^BQ$2))),IF($N5=Lists!$K$3,IF($L5<1,((($T5*(1-$F5)+$S5*(1-$G5))/$L5)*((1+Inputs!$D$7)^BQ$2)),((INT(BQ$2/$L5)-INT((BQ$2-1)/$L5))*($T5*(1-$F5)+$S5*(1-$G5))*((1+Inputs!$D$7)^BQ$2))),((Inputs!$D$8^((1-_xlfn.WEIBULL.DIST(BQ$2,$M5,$L5,FALSE))/_xlfn.WEIBULL.DIST(BQ$2,$M5,$L5,FALSE))*($T5*(1-$F5)+$S5*(1-$G5))*((1+Inputs!$D$7)^BQ$2)))))))) -> 46.910977 | BR5: =MAX(AB5,($E5*IF(BR$2>Inputs!$D$5,0,IF(BR$2>VLOOKUP($H5,Lists!$P$3:$Q$7,2),IF($N5=Lists!$K$3,IF($L5<1,(($U5/$L5)*((1+Inputs!$D$7)^BR$2)),((INT(BR$2/$L5)-INT((BR$2-1)/$L5))*$U5*((1+Inputs!$D$7)^BR$2))),(Inputs!$D$8^((1-_xlfn.WEIBULL.DIST(BR$2,$M5,$L5,FALSE))/_xlfn.WEIBULL.DIST(BR$2,$M5,$L5,FALSE))*$U5*((1+Inputs!$D$7)^BR$2))),IF($N5=Lists!$K$3,IF($L5<1,((($T5*(1-$F5)+$S5*(1-$G5))/$L5)*((1+Inputs!$D$7)^BR$2)),((INT(BR$2/$L5)-INT((BR$2-1)/$L5))*($T5*(1-$F5)+$S5*(1-$G5))*((1+Inputs!$D$7)^BR$2))),((Inputs!$D$8^((1-_xlfn.WEIBULL.DIST(BR$2,$M5,$L5,FALSE))/_xlfn.WEIBULL.DIST(BR$2,$M5,$L5,FALSE))*($T5*(1-$F5)+$S5*(1-$G5))*((1+Inputs!$D$7)^BR$2)))))))) -> 47.849196 | BS5: =MAX(AC5,($E5*IF(BS$2>Inputs!$D$5,0,IF(BS$2>VLOOKUP($H5,Lists!$P$3:$Q$7,2),IF($N5=Lists!$K$3,IF($L5<1,(($U5/$L5)*((1+Inputs!$D$7)^BS$2)),((INT(BS$2/$L5)-INT((BS$2-1)/$L5))*$U5*((1+Inputs!$D$7)^BS$2))),(Inputs!$D$8^((1-_xlfn.WEIBULL.DIST(BS$2,$M5,$L5,FALSE))/_xlfn.WEIBULL.DIST(BS$2,$M5,$L5,FALSE))*$U5*((1+Inputs!$D$7)^BS$2))),IF($N5=Lists!$K$3,IF($L5<1,((($T5*(1-$F5)+$S5*(1-$G5))/$L5)*((1+Inputs!$D$7)^BS$2)),((INT(BS$2/$L5)-INT((BS$2-1)/$L5))*($T5*(1-$F5)+$S5*(1-$G5))*((1+Inputs!$D$7)^BS$2))),((Inputs!$D$8^((1-_xlfn.WEIBULL.DIST(BS$2,$M5,$L5,FALSE))/_xlfn.WEIBULL.DIST(BS$2,$M5,$L5,FALSE))*($T5*(1-$F5)+$S5*(1-$G5))*((1+Inputs!$D$7)^BS$2)))))))) -> 48.80618 | BT5: =MAX(AD5,($E5*IF(BT$2>Inputs!$D$5,0,IF(BT$2>VLOOKUP($H5,Lists!$P$3:$Q$7,2),IF($N5=Lists!$K$3,IF($L5<1,(($U5/$L5)*((1+Inputs!$D$7)^BT$2)),((INT(BT$2/$L5)-INT((BT$2-1)/$L5))*$U5*((1+Inputs!$D$7)^BT$2))),(Inputs!$D$8^((1-_xlfn.WEIBULL.DIST(BT$2,$M5,$L5,FALSE))/_xlfn.WEIBULL.DIST(BT$2,$M5,$L5,FALSE))*$U5*((1+Inputs!$D$7)^BT$2))),IF($N5=Lists!$K$3,IF($L5<1,((($T5*(1-$F5)+$S5*(1-$G5))/$L5)*((1+Inputs!$D$7)^BT$2)),((INT(BT$2/$L5)-INT((BT$2-1)/$L5))*($T5*(1-$F5)+$S5*(1-$G5))*((1+Inputs!$D$7)^BT$2))),((Inputs!$D$8^((1-_xlfn.WEIBULL.DIST(BT$2,$M5,$L5,FALSE))/_xlfn.WEIBULL.DIST(BT$2,$M5,$L5,FALSE))*($T5*(1-$F5)+$S5*(1-$G5))*((1+Inputs!$D$7)^BT$2)))))))) -> 49.782304 | BU5: =MAX(AE5,($E5*IF(BU$2>Inputs!$D$5,0,IF(BU$2>VLOOKUP($H5,Lists!$P$3:$Q$7,2),IF($N5=Lists!$K$3,IF($L5<1,(($U5/$L5)*((1+Inputs!$D$7)^BU$2)),((INT(BU$2/$L5)-INT((BU$2-1)/$L5))*$U5*((1+Inputs!$D$7)^BU$2))),(Inputs!$D$8^((1-_xlfn.WEIBULL.DIST(BU$2,$M5,$L5,FALSE))/_xlfn.WEIBULL.DIST(BU$2,$M5,$L5,FALSE))*$U5*((1+Inputs!$D$7)^BU$2))),IF($N5=Lists!$K$3,IF($L5<1,((($T5*(1-$F5)+$S5*(1-$G5))/$L5)*((1+Inputs!$D$7)^BU$2)),((INT(BU$2/$L5)-INT((BU$2-1)/$L5))*($T5*(1-$F5)+$S5*(1-$G5))*((1+Inputs!$D$7)^BU$2))),((Inputs!$D$8^((1-_xlfn.WEIBULL.DIST(BU$2,$M5,$L5,FALSE))/_xlfn.WEIBULL.DIST(BU$2,$M5,$L5,FALSE))*($T5*(1-$F5)+$S5*(1-$G5))*((1+Inputs!$D$7)^BU$2)))))))) -> 50.77795 | BV5: =MAX(AF5,($E5*IF(BV$2>Inputs!$D$5,0,IF(BV$2>VLOOKUP($H5,Lists!$P$3:$Q$7,2),IF($N5=Lists!$K$3,IF($L5<1,(($U5/$L5)*((1+Inputs!$D$7)^BV$2)),((INT(BV$2/$L5)-INT((BV$2-1)/$L5))*$U5*((1+Inputs!$D$7)^BV$2))),(Inputs!$D$8^((1-_xlfn.WEIBULL.DIST(BV$2,$M5,$L5,FALSE))/_xlfn.WEIBULL.DIST(BV$2,$M5,$L5,FALSE))*$U5*((1+Inputs!$D$7)^BV$2))),IF($N5=Lists!$K$3,IF($L5<1,((($T5*(1-$F5)+$S5*(1-$G5))/$L5)*((1+Inputs!$D$7)^BV$2)),((INT(BV$2/$L5)-INT((BV$2-1)/$L5))*($T5*(1-$F5)+$S5*(1-$G5))*((1+Inputs!$D$7)^BV$2))),((Inputs!$D$8^((1-_xlfn.WEIBULL.DIST(BV$2,$M5,$L5,FALSE))/_xlfn.WEIBULL.DIST(BV$2,$M5,$L5,FALSE))*($T5*(1-$F5)+$S5*(1-$G5))*((1+Inputs!$D$7)^BV$2)))))))) -> 51.793509 | BW5: =MAX(AG5,($E5*IF(BW$2>Inputs!$D$5,0,IF(BW$2>VLOOKUP($H5,Lists!$P$3:$Q$7,2),IF($N5=Lists!$K$3,IF($L5<1,(($U5/$L5)*((1+Inputs!$D$7)^BW$2)),((INT(BW$2/$L5)-INT((BW$2-1)/$L5))*$U5*((1+Inputs!$D$7)^BW$2))),(Inputs!$D$8^((1-_xlfn.WEIBULL.DIST(BW$2,$M5,$L5,FALSE))/_xlfn.WEIBULL.DIST(BW$2,$M5,$L5,FALSE))*$U5*((1+Inputs!$D$7)^BW$2))),IF($N5=Lists!$K$3,IF($L5<1,((($T5*(1-$F5)+$S5*(1-$G5))/$L5)*((1+Inputs!$D$7)^BW$2)),((INT(BW$2/$L5)-INT((BW$2-1)/$L5))*($T5*(1-$F5)+$S5*(1-$G5))*((1+Inputs!$D$7)^BW$2))),((Inputs!$D$8^((1-_xlfn.WEIBULL.DIST(BW$2,$M5,$L5,FALSE))/_xlfn.WEIBULL.DIST(BW$2,$M5,$L5,FALSE))*($T5*(1-$F5)+$S5*(1-$G5))*((1+Inputs!$D$7)^BW$2)))))))) -> 52.829379 | BX5: =MAX(AH5,($E5*IF(BX$2>Inputs!$D$5,0,IF(BX$2>VLOOKUP($H5,Lists!$P$3:$Q$7,2),IF($N5=Lists!$K$3,IF($L5<1,(($U5/$L5)*((1+Inputs!$D$7)^BX$2)),((INT(BX$2/$L5)-INT((BX$2-1)/$L5))*$U5*((1+Inputs!$D$7)^BX$2))),(Inputs!$D$8^((1-_xlfn.WEIBULL.DIST(BX$2,$M5,$L5,FALSE))/_xlfn.WEIBULL.DIST(BX$2,$M5,$L5,FALSE))*$U5*((1+Inputs!$D$7)^BX$2))),IF($N5=Lists!$K$3,IF($L5<1,((($T5*(1-$F5)+$S5*(1-$G5))/$L5)*((1+Inputs!$D$7)^BX$2)),((INT(BX$2/$L5)-INT((BX$2-1)/$L5))*($T5*(1-$F5)+$S5*(1-$G5))*((1+Inputs!$D$7)^BX$2))),((Inputs!$D$8^((1-_xlfn.WEIBULL.DIST(BX$2,$M5,$L5,FALSE))/_xlfn.WEIBULL.DIST(BX$2,$M5,$L5,FALSE))*($T5*(1-$F5)+$S5*(1-$G5))*((1+Inputs!$D$7)^BX$2)))))))) -> 53.885967 | ... DD5: =MAX(BN5,($E5*IF(DD$2>Inputs!$D$5,0,IF(DD$2>VLOOKUP($H5,Lists!$P$3:$Q$7,2),IF($N5=Lists!$K$3,IF($L5<1,(($U5/$L5)*((1+Inputs!$D$7)^DD$2)),((INT(DD$2/$L5)-INT((DD$2-1)/$L5))*$U5*((1+Inputs!$D$7)^DD$2))),(Inputs!$D$8^((1-_xlfn.WEIBULL.DIST(DD$2,$M5,$L5,FALSE))/_xlfn.WEIBULL.DIST(DD$2,$M5,$L5,FALSE))*$U5*((1+Inputs!$D$7)^DD$2))),IF($N5=Lists!$K$3,IF($L5<1,((($T5*(1-$F5)+$S5*(1-$G5))/$L5)*((1+Inputs!$D$7)^DD$2)),((INT(DD$2/$L5)-INT((DD$2-1)/$L5))*($T5*(1-$F5)+$S5*(1-$G5))*((1+Inputs!$D$7)^DD$2))),((Inputs!$D$8^((1-_xlfn.WEIBULL.DIST(DD$2,$M5,$L5,FALSE))/_xlfn.WEIBULL.DIST(DD$2,$M5,$L5,FALSE))*($T5*(1-$F5)+$S5*(1-$G5))*((1+Inputs!$D$7)^DD$2)))))))) -> 0
A6: Confirm availability and take any measures to secure operating instructions, warranties and performance guarantees, and other project documentation. | B6: Administration | C6: Management | D6: Documents | E6: 1 | F6: 0 | G6: 0 | H6: N/A | J6: Administrator | K6: =VLOOKUP(J6,'Labor Rates'!$A$1:$F$16,2) -> 22.995577 | L6: 1 | M6: 1 | N6: interval | O6: 1 | P6: =0.08+0.01*Inputs!D32*Inputs!D33 -> 100.08 | Q6: =O6*P6/L6 -> 100.08 | R6: 0 | S6: =P6*O6*K6 -> 2301.3973 | T6: =R6*O6 -> 0 | U6: =E6*(T6+S6) -> 2301.3973 | X6: =AVERAGE(AA6:AT6) -> 2851.813 | Y6: =NPV(Inputs!$D$6,AA6:BN6) -> 32756.897 | Z6: =Y6/SUM($Y$3:$Y$136) -> 0.015449752 | AA6: =$E6*IF(AA$2>Inputs!$D$5,0,IF(AA$2>VLOOKUP($H6,Lists!$P$3:$Q$7,2),IF($N6=Lists!$K$3,IF($L6<1,(($U6/$L6)*((1+Inputs!$D$7)^AA$2)),((INT(AA$2/$L6)-INT((AA$2-1)/$L6))*$U6*((1+Inputs!$D$7)^AA$2))),(_xlfn.WEIBULL.DIST(AA$2,$M6,$L6,FALSE)*$U6*((1+Inputs!$D$7)^AA$2))),IF($N6=Lists!$K$3,IF($L6<1,((($T6*(1-$F6)+$S6*(1-$G6))/$L6)*((1+Inputs!$D$7)^AA$2)),((INT(AA$2/$L6)-INT((AA$2-1)/$L6))*($T6*(1-$F6)+$S6*(1-$G6))*((1+Inputs!$D$7)^AA$2))),((_xlfn.WEIBULL.DIST(AA$2,$M6,$L6,FALSE)*($T6*(1-$F6)+$S6*(1-$G6))*((1+Inputs!$D$7)^AA$2)))))) -> 2347.4253 | AB6: =$E6*IF(AB$2>Inputs!$D$5,0,IF(AB$2>VLOOKUP($H6,Lists!$P$3:$Q$7,2),IF($N6=Lists!$K$3,IF($L6<1,(($U6/$L6)*((1+Inputs!$D$7)^AB$2)),((INT(AB$2/$L6)-INT((AB$2-1)/$L6))*$U6*((1+Inputs!$D$7)^AB$2))),(_xlfn.WEIBULL.DIST(AB$2,$M6,$L6,FALSE)*$U6*((1+Inputs!$D$7)^AB$2))),IF($N6=Lists!$K$3,IF($L6<1,((($T6*(1-$F6)+$S6*(1-$G6))/$L6)*((1+Inputs!$D$7)^AB$2)),((INT(AB$2/$L6)-INT((AB$2-1)/$L6))*($T6*(1-$F6)+$S6*(1-$G6))*((1+Inputs!$D$7)^AB$2))),((_xlfn.WEIBULL.DIST(AB$2,$M6,$L6,FALSE)*($T6*(1-$F6)+$S6*(1-$G6))*((1+Inputs!$D$7)^AB$2)))))) -> 2394.3738 | AC6: =$E6*IF(AC$2>Inputs!$D$5,0,IF(AC$2>VLOOKUP($H6,Lists!$P$3:$Q$7,2),IF($N6=Lists!$K$3,IF($L6<1,(($U6/$L6)*((1+Inputs!$D$7)^AC$2)),((INT(AC$2/$L6)-INT((AC$2-1)/$L6))*$U6*((1+Inputs!$D$7)^AC$2))),(_xlfn.WEIBULL.DIST(AC$2,$M6,$L6,FALSE)*$U6*((1+Inputs!$D$7)^AC$2))),IF($N6=Lists!$K$3,IF($L6<1,((($T6*(1-$F6)+$S6*(1-$G6))/$L6)*((1+Inputs!$D$7)^AC$2)),((INT(AC$2/$L6)-INT((AC$2-1)/$L6))*($T6*(1-$F6)+$S6*(1-$G6))*((1+Inputs!$D$7)^AC$2))),((_xlfn.WEIBULL.DIST(AC$2,$M6,$L6,FALSE)*($T6*(1-$F6)+$S6*(1-$G6))*((1+Inputs!$D$7)^AC$2)))))) -> 2442.2613 | AD6: =$E6*IF(AD$2>Inputs!$D$5,0,IF(AD$2>VLOOKUP($H6,Lists!$P$3:$Q$7,2),IF($N6=Lists!$K$3,IF($L6<1,(($U6/$L6)*((1+Inputs!$D$7)^AD$2)),((INT(AD$2/$L6)-INT((AD$2-1)/$L6))*$U6*((1+Inputs!$D$7)^AD$2))),(_xlfn.WEIBULL.DIST(AD$2,$M6,$L6,FALSE)*$U6*((1+Inputs!$D$7)^AD$2))),IF($N6=Lists!$K$3,IF($L6<1,((($T6*(1-$F6)+$S6*(1-$G6))/$L6)*((1+Inputs!$D$7)^AD$2)),((INT(AD$2/$L6)-INT((AD$2-1)/$L6))*($T6*(1-$F6)+$S6*(1-$G6))*((1+Inputs!$D$7)^AD$2))),((_xlfn.WEIBULL.DIST(AD$2,$M6,$L6,FALSE)*($T6*(1-$F6)+$S6*(1-$G6))*((1+Inputs!$D$7)^AD$2)))))) -> 2491.1065 | AE6: =$E6*IF(AE$2>Inputs!$D$5,0,IF(AE$2>VLOOKUP($H6,Lists!$P$3:$Q$7,2),IF($N6=Lists!$K$3,IF($L6<1,(($U6/$L6)*((1+Inputs!$D$7)^AE$2)),((INT(AE$2/$L6)-INT((AE$2-1)/$L6))*$U6*((1+Inputs!$D$7)^AE$2))),(_xlfn.WEIBULL.DIST(AE$2,$M6,$L6,FALSE)*$U6*((1+Inputs!$D$7)^AE$2))),IF($N6=Lists!$K$3,IF($L6<1,((($T6*(1-$F6)+$S6*(1-$G6))/$L6)*((1+Inputs!$D$7)^AE$2)),((INT(AE$2/$L6)-INT((AE$2-1)/$L6))*($T6*(1-$F6)+$S6*(1-$G6))*((1+Inputs!$D$7)^AE$2))),((_xlfn.WEIBULL.DIST(AE$2,$M6,$L6,FALSE)*($T6*(1-$F6)+$S6*(1-$G6))*((1+Inputs!$D$7)^AE$2)))))) -> 2540.9286 | AF6: =$E6*IF(AF$2>Inputs!$D$5,0,IF(AF$2>VLOOKUP($H6,Lists!$P$3:$Q$7,2),IF($N6=Lists!$K$3,IF($L6<1,(($U6/$L6)*((1+Inputs!$D$7)^AF$2)),((INT(AF$2/$L6)-INT((AF$2-1)/$L6))*$U6*((1+Inputs!$D$7)^AF$2))),(_xlfn.WEIBULL.DIST(AF$2,$M6,$L6,FALSE)*$U6*((1+Inputs!$D$7)^AF$2))),IF($N6=Lists!$K$3,IF($L6<1,((($T6*(1-$F6)+$S6*(1-$G6))/$L6)*((1+Inputs!$D$7)^AF$2)),((INT(AF$2/$L6)-INT((AF$2-1)/$L6))*($T6*(1-$F6)+$S6*(1-$G6))*((1+Inputs!$D$7)^AF$2))),((_xlfn.WEIBULL.DIST(AF$2,$M6,$L6,FALSE)*($T6*(1-$F6)+$S6*(1-$G6))*((1+Inputs!$D$7)^AF$2)))))) -> 2591.7472 | AG6: =$E6*IF(AG$2>Inputs!$D$5,0,IF(AG$2>VLOOKUP($H6,Lists!$P$3:$Q$7,2),IF($N6=Lists!$K$3,IF($L6<1,(($U6/$L6)*((1+Inputs!$D$7)^AG$2)),((INT(AG$2/$L6)-INT((AG$2-1)/$L6))*$U6*((1+Inputs!$D$7)^AG$2))),(_xlfn.WEIBULL.DIST(AG$2,$M6,$L6,FALSE)*$U6*((1+Inputs!$D$7)^AG$2))),IF($N6=Lists!$K$3,IF($L6<1,((($T6*(1-$F6)+$S6*(1-$G6))/$L6)*((1+Inputs!$D$7)^AG$2)),((INT(AG$2/$L6)-INT((AG$2-1)/$L6))*($T6*(1-$F6)+$S6*(1-$G6))*((1+Inputs!$D$7)^AG$2))),((_xlfn.WEIBULL.DIST(AG$2,$M6,$L6,FALSE)*($T6*(1-$F6)+$S6*(1-$G6))*((1+Inputs!$D$7)^AG$2)))))) -> 2643.5821 | AH6: =$E6*IF(AH$2>Inputs!$D$5,0,IF(AH$2>VLOOKUP($H6,Lists!$P$3:$Q$7,2),IF($N6=Lists!$K$3,IF($L6<1,(($U6/$L6)*((1+Inputs!$D$7)^AH$2)),((INT(AH$2/$L6)-INT((AH$2-1)/$L6))*$U6*((1+Inputs!$D$7)^AH$2))),(_xlfn.WEIBULL.DIST(AH$2,$M6,$L6,FALSE)*$U6*((1+Inputs!$D$7)^AH$2))),IF($N6=Lists!$K$3,IF($L6<1,((($T6*(1-$F6)+$S6*(1-$G6))/$L6)*((1+Inputs!$D$7)^AH$2)),((INT(AH$2/$L6)-INT((AH$2-1)/$L6))*($T6*(1-$F6)+$S6*(1-$G6))*((1+Inputs!$D$7)^AH$2))),((_xlfn.WEIBULL.DIST(AH$2,$M6,$L6,FALSE)*($T6*(1-$F6)+$S6*(1-$G6))*((1+Inputs!$D$7)^AH$2)))))) -> 2696.4538 | ... BN6: =$E6*IF(BN$2>Inputs!$D$5,0,IF(BN$2>VLOOKUP($H6,Lists!$P$3:$Q$7,2),IF($N6=Lists!$K$3,IF($L6<1,(($U6/$L6)*((1+Inputs!$D$7)^BN$2)),((INT(BN$2/$L6)-INT((BN$2-1)/$L6))*$U6*((1+Inputs!$D$7)^BN$2))),(_xlfn.WEIBULL.DIST(BN$2,$M6,$L6,FALSE)*$U6*((1+Inputs!$D$7)^BN$2))),IF($N6=Lists!$K$3,IF($L6<1,((($T6*(1-$F6)+$S6*(1-$G6))/$L6)*((1+Inputs!$D$7)^BN$2)),((INT(BN$2/$L6)-INT((BN$2-1)/$L6))*($T6*(1-$F6)+$S6*(1-$G6))*((1+Inputs!$D$7)^BN$2))),((_xlfn.WEIBULL.DIST(BN$2,$M6,$L6,FALSE)*($T6*(1-$F6)+$S6*(1-$G6))*((1+Inputs!$D$7)^BN$2)))))) -> 0 | BO6: =NPV(Inputs!$D$6,BQ6:DD6) -> 32756.897 | BP6: =BO6/SUM($Y$3:$Y$136) -> 0.015449752 | BQ6: =MAX(AA6,($E6*IF(BQ$2>Inputs!$D$5,0,IF(BQ$2>VLOOKUP($H6,Lists!$P$3:$Q$7,2),IF($N6=Lists!$K$3,IF($L6<1,(($U6/$L6)*((1+Inputs!$D$7)^BQ$2)),((INT(BQ$2/$L6)-INT((BQ$2-1)/$L6))*$U6*((1+Inputs!$D$7)^BQ$2))),(Inputs!$D$8^((1-_xlfn.WEIBULL.DIST(BQ$2,$M6,$L6,FALSE))/_xlfn.WEIBULL.DIST(BQ$2,$M6,$L6,FALSE))*$U6*((1+Inputs!$D$7)^BQ$2))),IF($N6=Lists!$K$3,IF($L6<1,((($T6*(1-$F6)+$S6*(1-$G6))/$L6)*((1+Inputs!$D$7)^BQ$2)),((INT(BQ$2/$L6)-INT((BQ$2-1)/$L6))*($T6*(1-$F6)+$S6*(1-$G6))*((1+Inputs!$D$7)^BQ$2))),((Inputs!$D$8^((1-_xlfn.WEIBULL.DIST(BQ$2,$M6,$L6,FALSE))/_xlfn.WEIBULL.DIST(BQ$2,$M6,$L6,FALSE))*($T6*(1-$F6)+$S6*(1-$G6))*((1+Inputs!$D$7)^BQ$2)))))))) -> 2347.4253 | BR6: =MAX(AB6,($E6*IF(BR$2>Inputs!$D$5,0,IF(BR$2>VLOOKUP($H6,Lists!$P$3:$Q$7,2),IF($N6=Lists!$K$3,IF($L6<1,(($U6/$L6)*((1+Inputs!$D$7)^BR$2)),((INT(BR$2/$L6)-INT((BR$2-1)/$L6))*$U6*((1+Inputs!$D$7)^BR$2))),(Inputs!$D$8^((1-_xlfn.WEIBULL.DIST(BR$2,$M6,$L6,FALSE))/_xlfn.WEIBULL.DIST(BR$2,$M6,$L6,FALSE))*$U6*((1+Inputs!$D$7)^BR$2))),IF($N6=Lists!$K$3,IF($L6<1,((($T6*(1-$F6)+$S6*(1-$G6))/$L6)*((1+Inputs!$D$7)^BR$2)),((INT(BR$2/$L6)-INT((BR$2-1)/$L6))*($T6*(1-$F6)+$S6*(1-$G6))*((1+Inputs!$D$7)^BR$2))),((Inputs!$D$8^((1-_xlfn.WEIBULL.DIST(BR$2,$M6,$L6,FALSE))/_xlfn.WEIBULL.DIST(BR$2,$M6,$L6,FALSE))*($T6*(1-$F6)+$S6*(1-$G6))*((1+Inputs!$D$7)^BR$2)))))))) -> 2394.3738 | BS6: =MAX(AC6,($E6*IF(BS$2>Inputs!$D$5,0,IF(BS$2>VLOOKUP($H6,Lists!$P$3:$Q$7,2),IF($N6=Lists!$K$3,IF($L6<1,(($U6/$L6)*((1+Inputs!$D$7)^BS$2)),((INT(BS$2/$L6)-INT((BS$2-1)/$L6))*$U6*((1+Inputs!$D$7)^BS$2))),(Inputs!$D$8^((1-_xlfn.WEIBULL.DIST(BS$2,$M6,$L6,FALSE))/_xlfn.WEIBULL.DIST(BS$2,$M6,$L6,FALSE))*$U6*((1+Inputs!$D$7)^BS$2))),IF($N6=Lists!$K$3,IF($L6<1,((($T6*(1-$F6)+$S6*(1-$G6))/$L6)*((1+Inputs!$D$7)^BS$2)),((INT(BS$2/$L6)-INT((BS$2-1)/$L6))*($T6*(1-$F6)+$S6*(1-$G6))*((1+Inputs!$D$7)^BS$2))),((Inputs!$D$8^((1-_xlfn.WEIBULL.DIST(BS$2,$M6,$L6,FALSE))/_xlfn.WEIBULL.DIST(BS$2,$M6,$L6,FALSE))*($T6*(1-$F6)+$S6*(1-$G6))*((1+Inputs!$D$7)^BS$2)))))))) -> 2442.2613 | BT6: =MAX(AD6,($E6*IF(BT$2>Inputs!$D$5,0,IF(BT$2>VLOOKUP($H6,Lists!$P$3:$Q$7,2),IF($N6=Lists!$K$3,IF($L6<1,(($U6/$L6)*((1+Inputs!$D$7)^BT$2)),((INT(BT$2/$L6)-INT((BT$2-1)/$L6))*$U6*((1+Inputs!$D$7)^BT$2))),(Inputs!$D$8^((1-_xlfn.WEIBULL.DIST(BT$2,$M6,$L6,FALSE))/_xlfn.WEIBULL.DIST(BT$2,$M6,$L6,FALSE))*$U6*((1+Inputs!$D$7)^BT$2))),IF($N6=Lists!$K$3,IF($L6<1,((($T6*(1-$F6)+$S6*(1-$G6))/$L6)*((1+Inputs!$D$7)^BT$2)),((INT(BT$2/$L6)-INT((BT$2-1)/$L6))*($T6*(1-$F6)+$S6*(1-$G6))*((1+Inputs!$D$7)^BT$2))),((Inputs!$D$8^((1-_xlfn.WEIBULL.DIST(BT$2,$M6,$L6,FALSE))/_xlfn.WEIBULL.DIST(BT$2,$M6,$L6,FALSE))*($T6*(1-$F6)+$S6*(1-$G6))*((1+Inputs!$D$7)^BT$2)))))))) -> 2491.1065 | BU6: =MAX(AE6,($E6*IF(BU$2>Inputs!$D$5,0,IF(BU$2>VLOOKUP($H6,Lists!$P$3:$Q$7,2),IF($N6=Lists!$K$3,IF($L6<1,(($U6/$L6)*((1+Inputs!$D$7)^BU$2)),((INT(BU$2/$L6)-INT((BU$2-1)/$L6))*$U6*((1+Inputs!$D$7)^BU$2))),(Inputs!$D$8^((1-_xlfn.WEIBULL.DIST(BU$2,$M6,$L6,FALSE))/_xlfn.WEIBULL.DIST(BU$2,$M6,$L6,FALSE))*$U6*((1+Inputs!$D$7)^BU$2))),IF($N6=Lists!$K$3,IF($L6<1,((($T6*(1-$F6)+$S6*(1-$G6))/$L6)*((1+Inputs!$D$7)^BU$2)),((INT(BU$2/$L6)-INT((BU$2-1)/$L6))*($T6*(1-$F6)+$S6*(1-$G6))*((1+Inputs!$D$7)^BU$2))),((Inputs!$D$8^((1-_xlfn.WEIBULL.DIST(BU$2,$M6,$L6,FALSE))/_xlfn.WEIBULL.DIST(BU$2,$M6,$L6,FALSE))*($T6*(1-$F6)+$S6*(1-$G6))*((1+Inputs!$D$7)^BU$2)))))))) -> 2540.9286 | BV6: =MAX(AF6,($E6*IF(BV$2>Inputs!$D$5,0,IF(BV$2>VLOOKUP($H6,Lists!$P$3:$Q$7,2),IF($N6=Lists!$K$3,IF($L6<1,(($U6/$L6)*((1+Inputs!$D$7)^BV$2)),((INT(BV$2/$L6)-INT((BV$2-1)/$L6))*$U6*((1+Inputs!$D$7)^BV$2))),(Inputs!$D$8^((1-_xlfn.WEIBULL.DIST(BV$2,$M6,$L6,FALSE))/_xlfn.WEIBULL.DIST(BV$2,$M6,$L6,FALSE))*$U6*((1+Inputs!$D$7)^BV$2))),IF($N6=Lists!$K$3,IF($L6<1,((($T6*(1-$F6)+$S6*(1-$G6))/$L6)*((1+Inputs!$D$7)^BV$2)),((INT(BV$2/$L6)-INT((BV$2-1)/$L6))*($T6*(1-$F6)+$S6*(1-$G6))*((1+Inputs!$D$7)^BV$2))),((Inputs!$D$8^((1-_xlfn.WEIBULL.DIST(BV$2,$M6,$L6,FALSE))/_xlfn.WEIBULL.DIST(BV$2,$M6,$L6,FALSE))*($T6*(1-$F6)+$S6*(1-$G6))*((1+Inputs!$D$7)^BV$2)))))))) -> 2591.7472 | BW6: =MAX(AG6,($E6*IF(BW$2>Inputs!$D$5,0,IF(BW$2>VLOOKUP($H6,Lists!$P$3:$Q$7,2),IF($N6=Lists!$K$3,IF($L6<1,(($U6/$L6)*((1+Inputs!$D$7)^BW$2)),((INT(BW$2/$L6)-INT((BW$2-1)/$L6))*$U6*((1+Inputs!$D$7)^BW$2))),(Inputs!$D$8^((1-_xlfn.WEIBULL.DIST(BW$2,$M6,$L6,FALSE))/_xlfn.WEIBULL.DIST(BW$2,$M6,$L6,FALSE))*$U6*((1+Inputs!$D$7)^BW$2))),IF($N6=Lists!$K$3,IF($L6<1,((($T6*(1-$F6)+$S6*(1-$G6))/$L6)*((1+Inputs!$D$7)^BW$2)),((INT(BW$2/$L6)-INT((BW$2-1)/$L6))*($T6*(1-$F6)+$S6*(1-$G6))*((1+Inputs!$D$7)^BW$2))),((Inputs!$D$8^((1-_xlfn.WEIBULL.DIST(BW$2,$M6,$L6,FALSE))/_xlfn.WEIBULL.DIST(BW$2,$M6,$L6,FALSE))*($T6*(1-$F6)+$S6*(1-$G6))*((1+Inputs!$D$7)^BW$2)))))))) -> 2643.5821 | BX6: =MAX(AH6,($E6*IF(BX$2>Inputs!$D$5,0,IF(BX$2>VLOOKUP($H6,Lists!$P$3:$Q$7,2),IF($N6=Lists!$K$3,IF($L6<1,(($U6/$L6)*((1+Inputs!$D$7)^BX$2)),((INT(BX$2/$L6)-INT((BX$2-1)/$L6))*$U6*((1+Inputs!$D$7)^BX$2))),(Inputs!$D$8^((1-_xlfn.WEIBULL.DIST(BX$2,$M6,$L6,FALSE))/_xlfn.WEIBULL.DIST(BX$2,$M6,$L6,FALSE))*$U6*((1+Inputs!$D$7)^BX$2))),IF($N6=Lists!$K$3,IF($L6<1,((($T6*(1-$F6)+$S6*(1-$G6))/$L6)*((1+Inputs!$D$7)^BX$2)),((INT(BX$2/$L6)-INT((BX$2-1)/$L6))*($T6*(1-$F6)+$S6*(1-$G6))*((1+Inputs!$D$7)^BX$2))),((Inputs!$D$8^((1-_xlfn.WEIBULL.DIST(BX$2,$M6,$L6,FALSE))/_xlfn.WEIBULL.DIST(BX$2,$M6,$L6,FALSE))*($T6*(1-$F6)+$S6*(1-$G6))*((1+Inputs!$D$7)^BX$2)))))))) -> 2696.4538 | ... DD6: =MAX(BN6,($E6*IF(DD$2>Inputs!$D$5,0,IF(DD$2>VLOOKUP($H6,Lists!$P$3:$Q$7,2),IF($N6=Lists!$K$3,IF($L6<1,(($U6/$L6)*((1+Inputs!$D$7)^DD$2)),((INT(DD$2/$L6)-INT((DD$2-1)/$L6))*$U6*((1+Inputs!$D$7)^DD$2))),(Inputs!$D$8^((1-_xlfn.WEIBULL.DIST(DD$2,$M6,$L6,FALSE))/_xlfn.WEIBULL.DIST(DD$2,$M6,$L6,FALSE))*$U6*((1+Inputs!$D$7)^DD$2))),IF($N6=Lists!$K$3,IF($L6<1,((($T6*(1-$F6)+$S6*(1-$G6))/$L6)*((1+Inputs!$D$7)^DD$2)),((INT(DD$2/$L6)-INT((DD$2-1)/$L6))*($T6*(1-$F6)+$S6*(1-$G6))*((1+Inputs!$D$7)^DD$2))),((Inputs!$D$8^((1-_xlfn.WEIBULL.DIST(DD$2,$M6,$L6,FALSE))/_xlfn.WEIBULL.DIST(DD$2,$M6,$L6,FALSE))*($T6*(1-$F6)+$S6*(1-$G6))*((1+Inputs!$D$7)^DD$2)))))))) -> 0
A7: Document all O&M activities in a workbook available to all service personnel. | B7: Administration | C7: Management | D7: Documents | E7: =IF(Inputs!$D$41=Lists!$I$4,0,1) -> 1 | F7: 0 | G7: 0 | H7: N/A | J7: Administrator | K7: =VLOOKUP(J7,'Labor Rates'!$A$1:$F$16,2) -> 22.995577 | L7: 0.08 | M7: 1 | N7: interval | O7: 1 | P7: 0.25 | Q7: =O7*P7/L7 -> 3.125 | R7: 0 | S7: =P7*O7*K7 -> 5.7488942 | T7: =R7*O7 -> 0 | U7: =E7*(T7+S7) -> 5.7488942 | X7: =AVERAGE(AA7:AT7) -> 89.047918 | Y7: =NPV(Inputs!$D$6,AA7:BN7) -> 1022.8348 | Z7: =Y7/SUM($Y$3:$Y$136) -> 0.00048241881 | AA7: =$E7*IF(AA$2>Inputs!$D$5,0,IF(AA$2>VLOOKUP($H7,Lists!$P$3:$Q$7,2),IF($N7=Lists!$K$3,IF($L7<1,(($U7/$L7)*((1+Inputs!$D$7)^AA$2)),((INT(AA$2/$L7)-INT((AA$2-1)/$L7))*$U7*((1+Inputs!$D$7)^AA$2))),(_xlfn.WEIBULL.DIST(AA$2,$M7,$L7,FALSE)*$U7*((1+Inputs!$D$7)^AA$2))),IF($N7=Lists!$K$3,IF($L7<1,((($T7*(1-$F7)+$S7*(1-$G7))/$L7)*((1+Inputs!$D$7)^AA$2)),((INT(AA$2/$L7)-INT((AA$2-1)/$L7))*($T7*(1-$F7)+$S7*(1-$G7))*((1+Inputs!$D$7)^AA$2))),((_xlfn.WEIBULL.DIST(AA$2,$M7,$L7,FALSE)*($T7*(1-$F7)+$S7*(1-$G7))*((1+Inputs!$D$7)^AA$2)))))) -> 73.298401 | AB7: =$E7*IF(AB$2>Inputs!$D$5,0,IF(AB$2>VLOOKUP($H7,Lists!$P$3:$Q$7,2),IF($N7=Lists!$K$3,IF($L7<1,(($U7/$L7)*((1+Inputs!$D$7)^AB$2)),((INT(AB$2/$L7)-INT((AB$2-1)/$L7))*$U7*((1+Inputs!$D$7)^AB$2))),(_xlfn.WEIBULL.DIST(AB$2,$M7,$L7,FALSE)*$U7*((1+Inputs!$D$7)^AB$2))),IF($N7=Lists!$K$3,IF($L7<1,((($T7*(1-$F7)+$S7*(1-$G7))/$L7)*((1+Inputs!$D$7)^AB$2)),((INT(AB$2/$L7)-INT((AB$2-1)/$L7))*($T7*(1-$F7)+$S7*(1-$G7))*((1+Inputs!$D$7)^AB$2))),((_xlfn.WEIBULL.DIST(AB$2,$M7,$L7,FALSE)*($T7*(1-$F7)+$S7*(1-$G7))*((1+Inputs!$D$7)^AB$2)))))) -> 74.764369 | AC7: =$E7*IF(AC$2>Inputs!$D$5,0,IF(AC$2>VLOOKUP($H7,Lists!$P$3:$Q$7,2),IF($N7=Lists!$K$3,IF($L7<1,(($U7/$L7)*((1+Inputs!$D$7)^AC$2)),((INT(AC$2/$L7)-INT((AC$2-1)/$L7))*$U7*((1+Inputs!$D$7)^AC$2))),(_xlfn.WEIBULL.DIST(AC$2,$M7,$L7,FALSE)*$U7*((1+Inputs!$D$7)^AC$2))),IF($N7=Lists!$K$3,IF($L7<1,((($T7*(1-$F7)+$S7*(1-$G7))/$L7)*((1+Inputs!$D$7)^AC$2)),((INT(AC$2/$L7)-INT((AC$2-1)/$L7))*($T7*(1-$F7)+$S7*(1-$G7))*((1+Inputs!$D$7)^AC$2))),((_xlfn.WEIBULL.DIST(AC$2,$M7,$L7,FALSE)*($T7*(1-$F7)+$S7*(1-$G7))*((1+Inputs!$D$7)^AC$2)))))) -> 76.259657 | AD7: =$E7*IF(AD$2>Inputs!$D$5,0,IF(AD$2>VLOOKUP($H7,Lists!$P$3:$Q$7,2),IF($N7=Lists!$K$3,IF($L7<1,(($U7/$L7)*((1+Inputs!$D$7)^AD$2)),((INT(AD$2/$L7)-INT((AD$2-1)/$L7))*$U7*((1+Inputs!$D$7)^AD$2))),(_xlfn.WEIBULL.DIST(AD$2,$M7,$L7,FALSE)*$U7*((1+Inputs!$D$7)^AD$2))),IF($N7=Lists!$K$3,IF($L7<1,((($T7*(1-$F7)+$S7*(1-$G7))/$L7)*((1+Inputs!$D$7)^AD$2)),((INT(AD$2/$L7)-INT((AD$2-1)/$L7))*($T7*(1-$F7)+$S7*(1-$G7))*((1+Inputs!$D$7)^AD$2))),((_xlfn.WEIBULL.DIST(AD$2,$M7,$L7,FALSE)*($T7*(1-$F7)+$S7*(1-$G7))*((1+Inputs!$D$7)^AD$2)))))) -> 77.78485 | AE7: =$E7*IF(AE$2>Inputs!$D$5,0,IF(AE$2>VLOOKUP($H7,Lists!$P$3:$Q$7,2),IF($N7=Lists!$K$3,IF($L7<1,(($U7/$L7)*((1+Inputs!$D$7)^AE$2)),((INT(AE$2/$L7)-INT((AE$2-1)/$L7))*$U7*((1+Inputs!$D$7)^AE$2))),(_xlfn.WEIBULL.DIST(AE$2,$M7,$L7,FALSE)*$U7*((1+Inputs!$D$7)^AE$2))),IF($N7=Lists!$K$3,IF($L7<1,((($T7*(1-$F7)+$S7*(1-$G7))/$L7)*((1+Inputs!$D$7)^AE$2)),((INT(AE$2/$L7)-INT((AE$2-1)/$L7))*($T7*(1-$F7)+$S7*(1-$G7))*((1+Inputs!$D$7)^AE$2))),((_xlfn.WEIBULL.DIST(AE$2,$M7,$L7,FALSE)*($T7*(1-$F7)+$S7*(1-$G7))*((1+Inputs!$D$7)^AE$2)))))) -> 79.340547 | AF7: =$E7*IF(AF$2>Inputs!$D$5,0,IF(AF$2>VLOOKUP($H7,Lists!$P$3:$Q$7,2),IF($N7=Lists!$K$3,IF($L7<1,(($U7/$L7)*((1+Inputs!$D$7)^AF$2)),((INT(AF$2/$L7)-INT((AF$2-1)/$L7))*$U7*((1+Inputs!$D$7)^AF$2))),(_xlfn.WEIBULL.DIST(AF$2,$M7,$L7,FALSE)*$U7*((1+Inputs!$D$7)^AF$2))),IF($N7=Lists!$K$3,IF($L7<1,((($T7*(1-$F7)+$S7*(1-$G7))/$L7)*((1+Inputs!$D$7)^AF$2)),((INT(AF$2/$L7)-INT((AF$2-1)/$L7))*($T7*(1-$F7)+$S7*(1-$G7))*((1+Inputs!$D$7)^AF$2))),((_xlfn.WEIBULL.DIST(AF$2,$M7,$L7,FALSE)*($T7*(1-$F7)+$S7*(1-$G7))*((1+Inputs!$D$7)^AF$2)))))) -> 80.927358 | AG7: =$E7*IF(AG$2>Inputs!$D$5,0,IF(AG$2>VLOOKUP($H7,Lists!$P$3:$Q$7,2),IF($N7=Lists!$K$3,IF($L7<1,(($U7/$L7)*((1+Inputs!$D$7)^AG$2)),((INT(AG$2/$L7)-INT((AG$2-1)/$L7))*$U7*((1+Inputs!$D$7)^AG$2))),(_xlfn.WEIBULL.DIST(AG$2,$M7,$L7,FALSE)*$U7*((1+Inputs!$D$7)^AG$2))),IF($N7=Lists!$K$3,IF($L7<1,((($T7*(1-$F7)+$S7*(1-$G7))/$L7)*((1+Inputs!$D$7)^AG$2)),((INT(AG$2/$L7)-INT((AG$2-1)/$L7))*($T7*(1-$F7)+$S7*(1-$G7))*((1+Inputs!$D$7)^AG$2))),((_xlfn.WEIBULL.DIST(AG$2,$M7,$L7,FALSE)*($T7*(1-$F7)+$S7*(1-$G7))*((1+Inputs!$D$7)^AG$2)))))) -> 82.545905 | AH7: =$E7*IF(AH$2>Inputs!$D$5,0,IF(AH$2>VLOOKUP($H7,Lists!$P$3:$Q$7,2),IF($N7=Lists!$K$3,IF($L7<1,(($U7/$L7)*((1+Inputs!$D$7)^AH$2)),((INT(AH$2/$L7)-INT((AH$2-1)/$L7))*$U7*((1+Inputs!$D$7)^AH$2))),(_xlfn.WEIBULL.DIST(AH$2,$M7,$L7,FALSE)*$U7*((1+Inputs!$D$7)^AH$2))),IF($N7=Lists!$K$3,IF($L7<1,((($T7*(1-$F7)+$S7*(1-$G7))/$L7)*((1+Inputs!$D$7)^AH$2)),((INT(AH$2/$L7)-INT((AH$2-1)/$L7))*($T7*(1-$F7)+$S7*(1-$G7))*((1+Inputs!$D$7)^AH$2))),((_xlfn.WEIBULL.DIST(AH$2,$M7,$L7,FALSE)*($T7*(1-$F7)+$S7*(1-$G7))*((1+Inputs!$D$7)^AH$2)))))) -> 84.196823 | ... BN7: =$E7*IF(BN$2>Inputs!$D$5,0,IF(BN$2>VLOOKUP($H7,Lists!$P$3:$Q$7,2),IF($N7=Lists!$K$3,IF($L7<1,(($U7/$L7)*((1+Inputs!$D$7)^BN$2)),((INT(BN$2/$L7)-INT((BN$2-1)/$L7))*$U7*((1+Inputs!$D$7)^BN$2))),(_xlfn.WEIBULL.DIST(BN$2,$M7,$L7,FALSE)*$U7*((1+Inputs!$D$7)^BN$2))),IF($N7=Lists!$K$3,IF($L7<1,((($T7*(1-$F7)+$S7*(1-$G7))/$L7)*((1+Inputs!$D$7)^BN$2)),((INT(BN$2/$L7)-INT((BN$2-1)/$L7))*($T7*(1-$F7)+$S7*(1-$G7))*((1+Inputs!$D$7)^BN$2))),((_xlfn.WEIBULL.DIST(BN$2,$M7,$L7,FALSE)*($T7*(1-$F7)+$S7*(1-$G7))*((1+Inputs!$D$7)^BN$2)))))) -> 0 | BO7: =NPV(Inputs!$D$6,BQ7:DD7) -> 1022.8348 | BP7: =BO7/SUM($Y$3:$Y$136) -> 0.00048241881 | BQ7: =MAX(AA7,($E7*IF(BQ$2>Inputs!$D$5,0,IF(BQ$2>VLOOKUP($H7,Lists!$P$3:$Q$7,2),IF($N7=Lists!$K$3,IF($L7<1,(($U7/$L7)*((1+Inputs!$D$7)^BQ$2)),((INT(BQ$2/$L7)-INT((BQ$2-1)/$L7))*$U7*((1+Inputs!$D$7)^BQ$2))),(Inputs!$D$8^((1-_xlfn.WEIBULL.DIST(BQ$2,$M7,$L7,FALSE))/_xlfn.WEIBULL.DIST(BQ$2,$M7,$L7,FALSE))*$U7*((1+Inputs!$D$7)^BQ$2))),IF($N7=Lists!$K$3,IF($L7<1,((($T7*(1-$F7)+$S7*(1-$G7))/$L7)*((1+Inputs!$D$7)^BQ$2)),((INT(BQ$2/$L7)-INT((BQ$2-1)/$L7))*($T7*(1-$F7)+$S7*(1-$G7))*((1+Inputs!$D$7)^BQ$2))),((Inputs!$D$8^((1-_xlfn.WEIBULL.DIST(BQ$2,$M7,$L7,FALSE))/_xlfn.WEIBULL.DIST(BQ$2,$M7,$L7,FALSE))*($T7*(1-$F7)+$S7*(1-$G7))*((1+Inputs!$D$7)^BQ$2)))))))) -> 73.298401 | BR7: =MAX(AB7,($E7*IF(BR$2>Inputs!$D$5,0,IF(BR$2>VLOOKUP($H7,Lists!$P$3:$Q$7,2),IF($N7=Lists!$K$3,IF($L7<1,(($U7/$L7)*((1+Inputs!$D$7)^BR$2)),((INT(BR$2/$L7)-INT((BR$2-1)/$L7))*$U7*((1+Inputs!$D$7)^BR$2))),(Inputs!$D$8^((1-_xlfn.WEIBULL.DIST(BR$2,$M7,$L7,FALSE))/_xlfn.WEIBULL.DIST(BR$2,$M7,$L7,FALSE))*$U7*((1+Inputs!$D$7)^BR$2))),IF($N7=Lists!$K$3,IF($L7<1,((($T7*(1-$F7)+$S7*(1-$G7))/$L7)*((1+Inputs!$D$7)^BR$2)),((INT(BR$2/$L7)-INT((BR$2-1)/$L7))*($T7*(1-$F7)+$S7*(1-$G7))*((1+Inputs!$D$7)^BR$2))),((Inputs!$D$8^((1-_xlfn.WEIBULL.DIST(BR$2,$M7,$L7,FALSE))/_xlfn.WEIBULL.DIST(BR$2,$M7,$L7,FALSE))*($T7*(1-$F7)+$S7*(1-$G7))*((1+Inputs!$D$7)^BR$2)))))))) -> 74.764369 | BS7: =MAX(AC7,($E7*IF(BS$2>Inputs!$D$5,0,IF(BS$2>VLOOKUP($H7,Lists!$P$3:$Q$7,2),IF($N7=Lists!$K$3,IF($L7<1,(($U7/$L7)*((1+Inputs!$D$7)^BS$2)),((INT(BS$2/$L7)-INT((BS$2-1)/$L7))*$U7*((1+Inputs!$D$7)^BS$2))),(Inputs!$D$8^((1-_xlfn.WEIBULL.DIST(BS$2,$M7,$L7,FALSE))/_xlfn.WEIBULL.DIST(BS$2,$M7,$L7,FALSE))*$U7*((1+Inputs!$D$7)^BS$2))),IF($N7=Lists!$K$3,IF($L7<1,((($T7*(1-$F7)+$S7*(1-$G7))/$L7)*((1+Inputs!$D$7)^BS$2)),((INT(BS$2/$L7)-INT((BS$2-1)/$L7))*($T7*(1-$F7)+$S7*(1-$G7))*((1+Inputs!$D$7)^BS$2))),((Inputs!$D$8^((1-_xlfn.WEIBULL.DIST(BS$2,$M7,$L7,FALSE))/_xlfn.WEIBULL.DIST(BS$2,$M7,$L7,FALSE))*($T7*(1-$F7)+$S7*(1-$G7))*((1+Inputs!$D$7)^BS$2)))))))) -> 76.259657 | BT7: =MAX(AD7,($E7*IF(BT$2>Inputs!$D$5,0,IF(BT$2>VLOOKUP($H7,Lists!$P$3:$Q$7,2),IF($N7=Lists!$K$3,IF($L7<1,(($U7/$L7)*((1+Inputs!$D$7)^BT$2)),((INT(BT$2/$L7)-INT((BT$2-1)/$L7))*$U7*((1+Inputs!$D$7)^BT$2))),(Inputs!$D$8^((1-_xlfn.WEIBULL.DIST(BT$2,$M7,$L7,FALSE))/_xlfn.WEIBULL.DIST(BT$2,$M7,$L7,FALSE))*$U7*((1+Inputs!$D$7)^BT$2))),IF($N7=Lists!$K$3,IF($L7<1,((($T7*(1-$F7)+$S7*(1-$G7))/$L7)*((1+Inputs!$D$7)^BT$2)),((INT(BT$2/$L7)-INT((BT$2-1)/$L7))*($T7*(1-$F7)+$S7*(1-$G7))*((1+Inputs!$D$7)^BT$2))),((Inputs!$D$8^((1-_xlfn.WEIBULL.DIST(BT$2,$M7,$L7,FALSE))/_xlfn.WEIBULL.DIST(BT$2,$M7,$L7,FALSE))*($T7*(1-$F7)+$S7*(1-$G7))*((1+Inputs!$D$7)^BT$2)))))))) -> 77.78485 | BU7: =MAX(AE7,($E7*IF(BU$2>Inputs!$D$5,0,IF(BU$2>VLOOKUP($H7,Lists!$P$3:$Q$7,2),IF($N7=Lists!$K$3,IF($L7<1,(($U7/$L7)*((1+Inputs!$D$7)^BU$2)),((INT(BU$2/$L7)-INT((BU$2-1)/$L7))*$U7*((1+Inputs!$D$7)^BU$2))),(Inputs!$D$8^((1-_xlfn.WEIBULL.DIST(BU$2,$M7,$L7,FALSE))/_xlfn.WEIBULL.DIST(BU$2,$M7,$L7,FALSE))*$U7*((1+Inputs!$D$7)^BU$2))),IF($N7=Lists!$K$3,IF($L7<1,((($T7*(1-$F7)+$S7*(1-$G7))/$L7)*((1+Inputs!$D$7)^BU$2)),((INT(BU$2/$L7)-INT((BU$2-1)/$L7))*($T7*(1-$F7)+$S7*(1-$G7))*((1+Inputs!$D$7)^BU$2))),((Inputs!$D$8^((1-_xlfn.WEIBULL.DIST(BU$2,$M7,$L7,FALSE))/_xlfn.WEIBULL.DIST(BU$2,$M7,$L7,FALSE))*($T7*(1-$F7)+$S7*(1-$G7))*((1+Inputs!$D$7)^BU$2)))))))) -> 79.340547 | BV7: =MAX(AF7,($E7*IF(BV$2>Inputs!$D$5,0,IF(BV$2>VLOOKUP($H7,Lists!$P$3:$Q$7,2),IF($N7=Lists!$K$3,IF($L7<1,(($U7/$L7)*((1+Inputs!$D$7)^BV$2)),((INT(BV$2/$L7)-INT((BV$2-1)/$L7))*$U7*((1+Inputs!$D$7)^BV$2))),(Inputs!$D$8^((1-_xlfn.WEIBULL.DIST(BV$2,$M7,$L7,FALSE))/_xlfn.WEIBULL.DIST(BV$2,$M7,$L7,FALSE))*$U7*((1+Inputs!$D$7)^BV$2))),IF($N7=Lists!$K$3,IF($L7<1,((($T7*(1-$F7)+$S7*(1-$G7))/$L7)*((1+Inputs!$D$7)^BV$2)),((INT(BV$2/$L7)-INT((BV$2-1)/$L7))*($T7*(1-$F7)+$S7*(1-$G7))*((1+Inputs!$D$7)^BV$2))),((Inputs!$D$8^((1-_xlfn.WEIBULL.DIST(BV$2,$M7,$L7,FALSE))/_xlfn.WEIBULL.DIST(BV$2,$M7,$L7,FALSE))*($T7*(1-$F7)+$S7*(1-$G7))*((1+Inputs!$D$7)^BV$2)))))))) -> 80.927358 | BW7: =MAX(AG7,($E7*IF(BW$2>Inputs!$D$5,0,IF(BW$2>VLOOKUP($H7,Lists!$P$3:$Q$7,2),IF($N7=Lists!$K$3,IF($L7<1,(($U7/$L7)*((1+Inputs!$D$7)^BW$2)),((INT(BW$2/$L7)-INT((BW$2-1)/$L7))*$U7*((1+Inputs!$D$7)^BW$2))),(Inputs!$D$8^((1-_xlfn.WEIBULL.DIST(BW$2,$M7,$L7,FALSE))/_xlfn.WEIBULL.DIST(BW$2,$M7,$L7,FALSE))*$U7*((1+Inputs!$D$7)^BW$2))),IF($N7=Lists!$K$3,IF($L7<1,((($T7*(1-$F7)+$S7*(1-$G7))/$L7)*((1+Inputs!$D$7)^BW$2)),((INT(BW$2/$L7)-INT((BW$2-1)/$L7))*($T7*(1-$F7)+$S7*(1-$G7))*((1+Inputs!$D$7)^BW$2))),((Inputs!$D$8^((1-_xlfn.WEIBULL.DIST(BW$2,$M7,$L7,FALSE))/_xlfn.WEIBULL.DIST(BW$2,$M7,$L7,FALSE))*($T7*(1-$F7)+$S7*(1-$G7))*((1+Inputs!$D$7)^BW$2)))))))) -> 82.545905 | BX7: =MAX(AH7,($E7*IF(BX$2>Inputs!$D$5,0,IF(BX$2>VLOOKUP($H7,Lists!$P$3:$Q$7,2),IF($N7=Lists!$K$3,IF($L7<1,(($U7/$L7)*((1+Inputs!$D$7)^BX$2)),((INT(BX$2/$L7)-INT((BX$2-1)/$L7))*$U7*((1+Inputs!$D$7)^BX$2))),(Inputs!$D$8^((1-_xlfn.WEIBULL.DIST(BX$2,$M7,$L7,FALSE))/_xlfn.WEIBULL.DIST(BX$2,$M7,$L7,FALSE))*$U7*((1+Inputs!$D$7)^BX$2))),IF($N7=Lists!$K$3,IF($L7<1,((($T7*(1-$F7)+$S7*(1-$G7))/$L7)*((1+Inputs!$D$7)^BX$2)),((INT(BX$2/$L7)-INT((BX$2-1)/$L7))*($T7*(1-$F7)+$S7*(1-$G7))*((1+Inputs!$D$7)^BX$2))),((Inputs!$D$8^((1-_xlfn.WEIBULL.DIST(BX$2,$M7,$L7,FALSE))/_xlfn.WEIBULL.DIST(BX$2,$M7,$L7,FALSE))*($T7*(1-$F7)+$S7*(1-$G7))*((1+Inputs!$D$7)^BX$2)))))))) -> 84.196823 | ... DD7: =MAX(BN7,($E7*IF(DD$2>Inputs!$D$5,0,IF(DD$2>VLOOKUP($H7,Lists!$P$3:$Q$7,2),IF($N7=Lists!$K$3,IF($L7<1,(($U7/$L7)*((1+Inputs!$D$7)^DD$2)),((INT(DD$2/$L7)-INT((DD$2-1)/$L7))*$U7*((1+Inputs!$D$7)^DD$2))),(Inputs!$D$8^((1-_xlfn.WEIBULL.DIST(DD$2,$M7,$L7,FALSE))/_xlfn.WEIBULL.DIST(DD$2,$M7,$L7,FALSE))*$U7*((1+Inputs!$D$7)^DD$2))),IF($N7=Lists!$K$3,IF($L7<1,((($T7*(1-$F7)+$S7*(1-$G7))/$L7)*((1+Inputs!$D$7)^DD$2)),((INT(DD$2/$L7)-INT((DD$2-1)/$L7))*($T7*(1-$F7)+$S7*(1-$G7))*((1+Inputs!$D$7)^DD$2))),((Inputs!$D$8^((1-_xlfn.WEIBULL.DIST(DD$2,$M7,$L7,FALSE))/_xlfn.WEIBULL.DIST(DD$2,$M7,$L7,FALSE))*($T7*(1-$F7)+$S7*(1-$G7))*((1+Inputs!$D$7)^DD$2)))))))) -> 0
A8: Review O&M agreements and ensure that services are actually provided | B8: Administration | C8: Management | D8: Documents | E8: =IF(Inputs!$D$41=Lists!$I$4,0,1) -> 1 | F8: 0 | G8: 0 | H8: N/A | J8: Administrator | K8: =VLOOKUP(J8,'Labor Rates'!$A$1:$F$16,2) -> 22.995577 | L8: 1 | M8: 1 | N8: interval | O8: 1 | P8: 1 | Q8: =O8*P8/L8 -> 1 | R8: 0 | S8: =P8*O8*K8 -> 22.995577 | T8: =R8*O8 -> 0 | U8: =E8*(T8+S8) -> 22.995577 | X8: =AVERAGE(AA8:AT8) -> 28.495334 | Y8: =NPV(Inputs!$D$6,AA8:BN8) -> 327.30713 | Z8: =Y8/SUM($Y$3:$Y$136) -> 0.00015437402 | AA8: =$E8*IF(AA$2>Inputs!$D$5,0,IF(AA$2>VLOOKUP($H8,Lists!$P$3:$Q$7,2),IF($N8=Lists!$K$3,IF($L8<1,(($U8/$L8)*((1+Inputs!$D$7)^AA$2)),((INT(AA$2/$L8)-INT((AA$2-1)/$L8))*$U8*((1+Inputs!$D$7)^AA$2))),(_xlfn.WEIBULL.DIST(AA$2,$M8,$L8,FALSE)*$U8*((1+Inputs!$D$7)^AA$2))),IF($N8=Lists!$K$3,IF($L8<1,((($T8*(1-$F8)+$S8*(1-$G8))/$L8)*((1+Inputs!$D$7)^AA$2)),((INT(AA$2/$L8)-INT((AA$2-1)/$L8))*($T8*(1-$F8)+$S8*(1-$G8))*((1+Inputs!$D$7)^AA$2))),((_xlfn.WEIBULL.DIST(AA$2,$M8,$L8,FALSE)*($T8*(1-$F8)+$S8*(1-$G8))*((1+Inputs!$D$7)^AA$2)))))) -> 23.455488 | AB8: =$E8*IF(AB$2>Inputs!$D$5,0,IF(AB$2>VLOOKUP($H8,Lists!$P$3:$Q$7,2),IF($N8=Lists!$K$3,IF($L8<1,(($U8/$L8)*((1+Inputs!$D$7)^AB$2)),((INT(AB$2/$L8)-INT((AB$2-1)/$L8))*$U8*((1+Inputs!$D$7)^AB$2))),(_xlfn.WEIBULL.DIST(AB$2,$M8,$L8,FALSE)*$U8*((1+Inputs!$D$7)^AB$2))),IF($N8=Lists!$K$3,IF($L8<1,((($T8*(1-$F8)+$S8*(1-$G8))/$L8)*((1+Inputs!$D$7)^AB$2)),((INT(AB$2/$L8)-INT((AB$2-1)/$L8))*($T8*(1-$F8)+$S8*(1-$G8))*((1+Inputs!$D$7)^AB$2))),((_xlfn.WEIBULL.DIST(AB$2,$M8,$L8,FALSE)*($T8*(1-$F8)+$S8*(1-$G8))*((1+Inputs!$D$7)^AB$2)))))) -> 23.924598 | AC8: =$E8*IF(AC$2>Inputs!$D$5,0,IF(AC$2>VLOOKUP($H8,Lists!$P$3:$Q$7,2),IF($N8=Lists!$K$3,IF($L8<1,(($U8/$L8)*((1+Inputs!$D$7)^AC$2)),((INT(AC$2/$L8)-INT((AC$2-1)/$L8))*$U8*((1+Inputs!$D$7)^AC$2))),(_xlfn.WEIBULL.DIST(AC$2,$M8,$L8,FALSE)*$U8*((1+Inputs!$D$7)^AC$2))),IF($N8=Lists!$K$3,IF($L8<1,((($T8*(1-$F8)+$S8*(1-$G8))/$L8)*((1+Inputs!$D$7)^AC$2)),((INT(AC$2/$L8)-INT((AC$2-1)/$L8))*($T8*(1-$F8)+$S8*(1-$G8))*((1+Inputs!$D$7)^AC$2))),((_xlfn.WEIBULL.DIST(AC$2,$M8,$L8,FALSE)*($T8*(1-$F8)+$S8*(1-$G8))*((1+Inputs!$D$7)^AC$2)))))) -> 24.40309 | AD8: =$E8*IF(AD$2>Inputs!$D$5,0,IF(AD$2>VLOOKUP($H8,Lists!$P$3:$Q$7,2),IF($N8=Lists!$K$3,IF($L8<1,(($U8/$L8)*((1+Inputs!$D$7)^AD$2)),((INT(AD$2/$L8)-INT((AD$2-1)/$L8))*$U8*((1+Inputs!$D$7)^AD$2))),(_xlfn.WEIBULL.DIST(AD$2,$M8,$L8,FALSE)*$U8*((1+Inputs!$D$7)^AD$2))),IF($N8=Lists!$K$3,IF($L8<1,((($T8*(1-$F8)+$S8*(1-$G8))/$L8)*((1+Inputs!$D$7)^AD$2)),((INT(AD$2/$L8)-INT((AD$2-1)/$L8))*($T8*(1-$F8)+$S8*(1-$G8))*((1+Inputs!$D$7)^AD$2))),((_xlfn.WEIBULL.DIST(AD$2,$M8,$L8,FALSE)*($T8*(1-$F8)+$S8*(1-$G8))*((1+Inputs!$D$7)^AD$2)))))) -> 24.891152 | AE8: =$E8*IF(AE$2>Inputs!$D$5,0,IF(AE$2>VLOOKUP($H8,Lists!$P$3:$Q$7,2),IF($N8=Lists!$K$3,IF($L8<1,(($U8/$L8)*((1+Inputs!$D$7)^AE$2)),((INT(AE$2/$L8)-INT((AE$2-1)/$L8))*$U8*((1+Inputs!$D$7)^AE$2))),(_xlfn.WEIBULL.DIST(AE$2,$M8,$L8,FALSE)*$U8*((1+Inputs!$D$7)^AE$2))),IF($N8=Lists!$K$3,IF($L8<1,((($T8*(1-$F8)+$S8*(1-$G8))/$L8)*((1+Inputs!$D$7)^AE$2)),((INT(AE$2/$L8)-INT((AE$2-1)/$L8))*($T8*(1-$F8)+$S8*(1-$G8))*((1+Inputs!$D$7)^AE$2))),((_xlfn.WEIBULL.DIST(AE$2,$M8,$L8,FALSE)*($T8*(1-$F8)+$S8*(1-$G8))*((1+Inputs!$D$7)^AE$2)))))) -> 25.388975 | AF8: =$E8*IF(AF$2>Inputs!$D$5,0,IF(AF$2>VLOOKUP($H8,Lists!$P$3:$Q$7,2),IF($N8=Lists!$K$3,IF($L8<1,(($U8/$L8)*((1+Inputs!$D$7)^AF$2)),((INT(AF$2/$L8)-INT((AF$2-1)/$L8))*$U8*((1+Inputs!$D$7)^AF$2))),(_xlfn.WEIBULL.DIST(AF$2,$M8,$L8,FALSE)*$U8*((1+Inputs!$D$7)^AF$2))),IF($N8=Lists!$K$3,IF($L8<1,((($T8*(1-$F8)+$S8*(1-$G8))/$L8)*((1+Inputs!$D$7)^AF$2)),((INT(AF$2/$L8)-INT((AF$2-1)/$L8))*($T8*(1-$F8)+$S8*(1-$G8))*((1+Inputs!$D$7)^AF$2))),((_xlfn.WEIBULL.DIST(AF$2,$M8,$L8,FALSE)*($T8*(1-$F8)+$S8*(1-$G8))*((1+Inputs!$D$7)^AF$2)))))) -> 25.896755 | AG8: =$E8*IF(AG$2>Inputs!$D$5,0,IF(AG$2>VLOOKUP($H8,Lists!$P$3:$Q$7,2),IF($N8=Lists!$K$3,IF($L8<1,(($U8/$L8)*((1+Inputs!$D$7)^AG$2)),((INT(AG$2/$L8)-INT((AG$2-1)/$L8))*$U8*((1+Inputs!$D$7)^AG$2))),(_xlfn.WEIBULL.DIST(AG$2,$M8,$L8,FALSE)*$U8*((1+Inputs!$D$7)^AG$2))),IF($N8=Lists!$K$3,IF($L8<1,((($T8*(1-$F8)+$S8*(1-$G8))/$L8)*((1+Inputs!$D$7)^AG$2)),((INT(AG$2/$L8)-INT((AG$2-1)/$L8))*($T8*(1-$F8)+$S8*(1-$G8))*((1+Inputs!$D$7)^AG$2))),((_xlfn.WEIBULL.DIST(AG$2,$M8,$L8,FALSE)*($T8*(1-$F8)+$S8*(1-$G8))*((1+Inputs!$D$7)^AG$2)))))) -> 26.41469 | AH8: =$E8*IF(AH$2>Inputs!$D$5,0,IF(AH$2>VLOOKUP($H8,Lists!$P$3:$Q$7,2),IF($N8=Lists!$K$3,IF($L8<1,(($U8/$L8)*((1+Inputs!$D$7)^AH$2)),((INT(AH$2/$L8)-INT((AH$2-1)/$L8))*$U8*((1+Inputs!$D$7)^AH$2))),(_xlfn.WEIBULL.DIST(AH$2,$M8,$L8,FALSE)*$U8*((1+Inputs!$D$7)^AH$2))),IF($N8=Lists!$K$3,IF($L8<1,((($T8*(1-$F8)+$S8*(1-$G8))/$L8)*((1+Inputs!$D$7)^AH$2)),((INT(AH$2/$L8)-INT((AH$2-1)/$L8))*($T8*(1-$F8)+$S8*(1-$G8))*((1+Inputs!$D$7)^AH$2))),((_xlfn.WEIBULL.DIST(AH$2,$M8,$L8,FALSE)*($T8*(1-$F8)+$S8*(1-$G8))*((1+Inputs!$D$7)^AH$2)))))) -> 26.942983 | ... BN8: =$E8*IF(BN$2>Inputs!$D$5,0,IF(BN$2>VLOOKUP($H8,Lists!$P$3:$Q$7,2),IF($N8=Lists!$K$3,IF($L8<1,(($U8/$L8)*((1+Inputs!$D$7)^BN$2)),((INT(BN$2/$L8)-INT((BN$2-1)/$L8))*$U8*((1+Inputs!$D$7)^BN$2))),(_xlfn.WEIBULL.DIST(BN$2,$M8,$L8,FALSE)*$U8*((1+Inputs!$D$7)^BN$2))),IF($N8=Lists!$K$3,IF($L8<1,((($T8*(1-$F8)+$S8*(1-$G8))/$L8)*((1+Inputs!$D$7)^BN$2)),((INT(BN$2/$L8)-INT((BN$2-1)/$L8))*($T8*(1-$F8)+$S8*(1-$G8))*((1+Inputs!$D$7)^BN$2))),((_xlfn.WEIBULL.DIST(BN$2,$M8,$L8,FALSE)*($T8*(1-$F8)+$S8*(1-$G8))*((1+Inputs!$D$7)^BN$2)))))) -> 0 | BO8: =NPV(Inputs!$D$6,BQ8:DD8) -> 327.30713 | BP8: =BO8/SUM($Y$3:$Y$136) -> 0.00015437402 | BQ8: =MAX(AA8,($E8*IF(BQ$2>Inputs!$D$5,0,IF(BQ$2>VLOOKUP($H8,Lists!$P$3:$Q$7,2),IF($N8=Lists!$K$3,IF($L8<1,(($U8/$L8)*((1+Inputs!$D$7)^BQ$2)),((INT(BQ$2/$L8)-INT((BQ$2-1)/$L8))*$U8*((1+Inputs!$D$7)^BQ$2))),(Inputs!$D$8^((1-_xlfn.WEIBULL.DIST(BQ$2,$M8,$L8,FALSE))/_xlfn.WEIBULL.DIST(BQ$2,$M8,$L8,FALSE))*$U8*((1+Inputs!$D$7)^BQ$2))),IF($N8=Lists!$K$3,IF($L8<1,((($T8*(1-$F8)+$S8*(1-$G8))/$L8)*((1+Inputs!$D$7)^BQ$2)),((INT(BQ$2/$L8)-INT((BQ$2-1)/$L8))*($T8*(1-$F8)+$S8*(1-$G8))*((1+Inputs!$D$7)^BQ$2))),((Inputs!$D$8^((1-_xlfn.WEIBULL.DIST(BQ$2,$M8,$L8,FALSE))/_xlfn.WEIBULL.DIST(BQ$2,$M8,$L8,FALSE))*($T8*(1-$F8)+$S8*(1-$G8))*((1+Inputs!$D$7)^BQ$2)))))))) -> 23.455488 | BR8: =MAX(AB8,($E8*IF(BR$2>Inputs!$D$5,0,IF(BR$2>VLOOKUP($H8,Lists!$P$3:$Q$7,2),IF($N8=Lists!$K$3,IF($L8<1,(($U8/$L8)*((1+Inputs!$D$7)^BR$2)),((INT(BR$2/$L8)-INT((BR$2-1)/$L8))*$U8*((1+Inputs!$D$7)^BR$2))),(Inputs!$D$8^((1-_xlfn.WEIBULL.DIST(BR$2,$M8,$L8,FALSE))/_xlfn.WEIBULL.DIST(BR$2,$M8,$L8,FALSE))*$U8*((1+Inputs!$D$7)^BR$2))),IF($N8=Lists!$K$3,IF($L8<1,((($T8*(1-$F8)+$S8*(1-$G8))/$L8)*((1+Inputs!$D$7)^BR$2)),((INT(BR$2/$L8)-INT((BR$2-1)/$L8))*($T8*(1-$F8)+$S8*(1-$G8))*((1+Inputs!$D$7)^BR$2))),((Inputs!$D$8^((1-_xlfn.WEIBULL.DIST(BR$2,$M8,$L8,FALSE))/_xlfn.WEIBULL.DIST(BR$2,$M8,$L8,FALSE))*($T8*(1-$F8)+$S8*(1-$G8))*((1+Inputs!$D$7)^BR$2)))))))) -> 23.924598 | BS8: =MAX(AC8,($E8*IF(BS$2>Inputs!$D$5,0,IF(BS$2>VLOOKUP($H8,Lists!$P$3:$Q$7,2),IF($N8=Lists!$K$3,IF($L8<1,(($U8/$L8)*((1+Inputs!$D$7)^BS$2)),((INT(BS$2/$L8)-INT((BS$2-1)/$L8))*$U8*((1+Inputs!$D$7)^BS$2))),(Inputs!$D$8^((1-_xlfn.WEIBULL.DIST(BS$2,$M8,$L8,FALSE))/_xlfn.WEIBULL.DIST(BS$2,$M8,$L8,FALSE))*$U8*((1+Inputs!$D$7)^BS$2))),IF($N8=Lists!$K$3,IF($L8<1,((($T8*(1-$F8)+$S8*(1-$G8))/$L8)*((1+Inputs!$D$7)^BS$2)),((INT(BS$2/$L8)-INT((BS$2-1)/$L8))*($T8*(1-$F8)+$S8*(1-$G8))*((1+Inputs!$D$7)^BS$2))),((Inputs!$D$8^((1-_xlfn.WEIBULL.DIST(BS$2,$M8,$L8,FALSE))/_xlfn.WEIBULL.DIST(BS$2,$M8,$L8,FALSE))*($T8*(1-$F8)+$S8*(1-$G8))*((1+Inputs!$D$7)^BS$2)))))))) -> 24.40309 | BT8: =MAX(AD8,($E8*IF(BT$2>Inputs!$D$5,0,IF(BT$2>VLOOKUP($H8,Lists!$P$3:$Q$7,2),IF($N8=Lists!$K$3,IF($L8<1,(($U8/$L8)*((1+Inputs!$D$7)^BT$2)),((INT(BT$2/$L8)-INT((BT$2-1)/$L8))*$U8*((1+Inputs!$D$7)^BT$2))),(Inputs!$D$8^((1-_xlfn.WEIBULL.DIST(BT$2,$M8,$L8,FALSE))/_xlfn.WEIBULL.DIST(BT$2,$M8,$L8,FALSE))*$U8*((1+Inputs!$D$7)^BT$2))),IF($N8=Lists!$K$3,IF($L8<1,((($T8*(1-$F8)+$S8*(1-$G8))/$L8)*((1+Inputs!$D$7)^BT$2)),((INT(BT$2/$L8)-INT((BT$2-1)/$L8))*($T8*(1-$F8)+$S8*(1-$G8))*((1+Inputs!$D$7)^BT$2))),((Inputs!$D$8^((1-_xlfn.WEIBULL.DIST(BT$2,$M8,$L8,FALSE))/_xlfn.WEIBULL.DIST(BT$2,$M8,$L8,FALSE))*($T8*(1-$F8)+$S8*(1-$G8))*((1+Inputs!$D$7)^BT$2)))))))) -> 24.891152 | BU8: =MAX(AE8,($E8*IF(BU$2>Inputs!$D$5,0,IF(BU$2>VLOOKUP($H8,Lists!$P$3:$Q$7,2),IF($N8=Lists!$K$3,IF($L8<1,(($U8/$L8)*((1+Inputs!$D$7)^BU$2)),((INT(BU$2/$L8)-INT((BU$2-1)/$L8))*$U8*((1+Inputs!$D$7)^BU$2))),(Inputs!$D$8^((1-_xlfn.WEIBULL.DIST(BU$2,$M8,$L8,FALSE))/_xlfn.WEIBULL.DIST(BU$2,$M8,$L8,FALSE))*$U8*((1+Inputs!$D$7)^BU$2))),IF($N8=Lists!$K$3,IF($L8<1,((($T8*(1-$F8)+$S8*(1-$G8))/$L8)*((1+Inputs!$D$7)^BU$2)),((INT(BU$2/$L8)-INT((BU$2-1)/$L8))*($T8*(1-$F8)+$S8*(1-$G8))*((1+Inputs!$D$7)^BU$2))),((Inputs!$D$8^((1-_xlfn.WEIBULL.DIST(BU$2,$M8,$L8,FALSE))/_xlfn.WEIBULL.DIST(BU$2,$M8,$L8,FALSE))*($T8*(1-$F8)+$S8*(1-$G8))*((1+Inputs!$D$7)^BU$2)))))))) -> 25.388975 | BV8: =MAX(AF8,($E8*IF(BV$2>Inputs!$D$5,0,IF(BV$2>VLOOKUP($H8,Lists!$P$3:$Q$7,2),IF($N8=Lists!$K$3,IF($L8<1,(($U8/$L8)*((1+Inputs!$D$7)^BV$2)),((INT(BV$2/$L8)-INT((BV$2-1)/$L8))*$U8*((1+Inputs!$D$7)^BV$2))),(Inputs!$D$8^((1-_xlfn.WEIBULL.DIST(BV$2,$M8,$L8,FALSE))/_xlfn.WEIBULL.DIST(BV$2,$M8,$L8,FALSE))*$U8*((1+Inputs!$D$7)^BV$2))),IF($N8=Lists!$K$3,IF($L8<1,((($T8*(1-$F8)+$S8*(1-$G8))/$L8)*((1+Inputs!$D$7)^BV$2)),((INT(BV$2/$L8)-INT((BV$2-1)/$L8))*($T8*(1-$F8)+$S8*(1-$G8))*((1+Inputs!$D$7)^BV$2))),((Inputs!$D$8^((1-_xlfn.WEIBULL.DIST(BV$2,$M8,$L8,FALSE))/_xlfn.WEIBULL.DIST(BV$2,$M8,$L8,FALSE))*($T8*(1-$F8)+$S8*(1-$G8))*((1+Inputs!$D$7)^BV$2)))))))) -> 25.896755 | BW8: =MAX(AG8,($E8*IF(BW$2>Inputs!$D$5,0,IF(BW$2>VLOOKUP($H8,Lists!$P$3:$Q$7,2),IF($N8=Lists!$K$3,IF($L8<1,(($U8/$L8)*((1+Inputs!$D$7)^BW$2)),((INT(BW$2/$L8)-INT((BW$2-1)/$L8))*$U8*((1+Inputs!$D$7)^BW$2))),(Inputs!$D$8^((1-_xlfn.WEIBULL.DIST(BW$2,$M8,$L8,FALSE))/_xlfn.WEIBULL.DIST(BW$2,$M8,$L8,FALSE))*$U8*((1+Inputs!$D$7)^BW$2))),IF($N8=Lists!$K$3,IF($L8<1,((($T8*(1-$F8)+$S8*(1-$G8))/$L8)*((1+Inputs!$D$7)^BW$2)),((INT(BW$2/$L8)-INT((BW$2-1)/$L8))*($T8*(1-$F8)+$S8*(1-$G8))*((1+Inputs!$D$7)^BW$2))),((Inputs!$D$8^((1-_xlfn.WEIBULL.DIST(BW$2,$M8,$L8,FALSE))/_xlfn.WEIBULL.DIST(BW$2,$M8,$L8,FALSE))*($T8*(1-$F8)+$S8*(1-$G8))*((1+Inputs!$D$7)^BW$2)))))))) -> 26.41469 | BX8: =MAX(AH8,($E8*IF(BX$2>Inputs!$D$5,0,IF(BX$2>VLOOKUP($H8,Lists!$P$3:$Q$7,2),IF($N8=Lists!$K$3,IF($L8<1,(($U8/$L8)*((1+Inputs!$D$7)^BX$2)),((INT(BX$2/$L8)-INT((BX$2-1)/$L8))*$U8*((1+Inputs!$D$7)^BX$2))),(Inputs!$D$8^((1-_xlfn.WEIBULL.DIST(BX$2,$M8,$L8,FALSE))/_xlfn.WEIBULL.DIST(BX$2,$M8,$L8,FALSE))*$U8*((1+Inputs!$D$7)^BX$2))),IF($N8=Lists!$K$3,IF($L8<1,((($T8*(1-$F8)+$S8*(1-$G8))/$L8)*((1+Inputs!$D$7)^BX$2)),((INT(BX$2/$L8)-INT((BX$2-1)/$L8))*($T8*(1-$F8)+$S8*(1-$G8))*((1+Inputs!$D$7)^BX$2))),((Inputs!$D$8^((1-_xlfn.WEIBULL.DIST(BX$2,$M8,$L8,FALSE))/_xlfn.WEIBULL.DIST(BX$2,$M8,$L8,FALSE))*($T8*(1-$F8)+$S8*(1-$G8))*((1+Inputs!$D$7)^BX$2)))))))) -> 26.942983 | ... DD8: =MAX(BN8,($E8*IF(DD$2>Inputs!$D$5,0,IF(DD$2>VLOOKUP($H8,Lists!$P$3:$Q$7,2),IF($N8=Lists!$K$3,IF($L8<1,(($U8/$L8)*((1+Inputs!$D$7)^DD$2)),((INT(DD$2/$L8)-INT((DD$2-1)/$L8))*$U8*((1+Inputs!$D$7)^DD$2))),(Inputs!$D$8^((1-_xlfn.WEIBULL.DIST(DD$2,$M8,$L8,FALSE))/_xlfn.WEIBULL.DIST(DD$2,$M8,$L8,FALSE))*$U8*((1+Inputs!$D$7)^DD$2))),IF($N8=Lists!$K$3,IF($L8<1,((($T8*(1-$F8)+$S8*(1-$G8))/$L8)*((1+Inputs!$D$7)^DD$2)),((INT(DD$2/$L8)-INT((DD$2-1)/$L8))*($T8*(1-$F8)+$S8*(1-$G8))*((1+Inputs!$D$7)^DD$2))),((Inputs!$D$8^((1-_xlfn.WEIBULL.DIST(DD$2,$M8,$L8,FALSE))/_xlfn.WEIBULL.DIST(DD$2,$M8,$L8,FALSE))*($T8*(1-$F8)+$S8*(1-$G8))*((1+Inputs!$D$7)^DD$2)))))))) -> 0
A9: Update record with preventative maintenance activities and track any problems or warranty issues and secure the record on-site. | B9: Administration | C9: Management | D9: Documents | E9: =IF(Inputs!$D$41=Lists!$I$4,0,1) -> 1 | F9: 0 | G9: 0 | H9: N/A | J9: Administrator | K9: =VLOOKUP(J9,'Labor Rates'!$A$1:$F$16,2) -> 22.995577 | L9: 0.08 | M9: 1 | N9: interval | O9: 1 | P9: 0.25 | Q9: =O9*P9/L9 -> 3.125 | R9: 0 | S9: =P9*O9*K9 -> 5.7488942 | T9: =R9*O9 -> 0 | U9: =E9*(T9+S9) -> 5.7488942 | X9: =AVERAGE(AA9:AT9) -> 89.047918 | Y9: =NPV(Inputs!$D$6,AA9:BN9) -> 1022.8348 | Z9: =Y9/SUM($Y$3:$Y$136) -> 0.00048241881 | AA9: =$E9*IF(AA$2>Inputs!$D$5,0,IF(AA$2>VLOOKUP($H9,Lists!$P$3:$Q$7,2),IF($N9=Lists!$K$3,IF($L9<1,(($U9/$L9)*((1+Inputs!$D$7)^AA$2)),((INT(AA$2/$L9)-INT((AA$2-1)/$L9))*$U9*((1+Inputs!$D$7)^AA$2))),(_xlfn.WEIBULL.DIST(AA$2,$M9,$L9,FALSE)*$U9*((1+Inputs!$D$7)^AA$2))),IF($N9=Lists!$K$3,IF($L9<1,((($T9*(1-$F9)+$S9*(1-$G9))/$L9)*((1+Inputs!$D$7)^AA$2)),((INT(AA$2/$L9)-INT((AA$2-1)/$L9))*($T9*(1-$F9)+$S9*(1-$G9))*((1+Inputs!$D$7)^AA$2))),((_xlfn.WEIBULL.DIST(AA$2,$M9,$L9,FALSE)*($T9*(1-$F9)+$S9*(1-$G9))*((1+Inputs!$D$7)^AA$2)))))) -> 73.298401 | AB9: =$E9*IF(AB$2>Inputs!$D$5,0,IF(AB$2>VLOOKUP($H9,Lists!$P$3:$Q$7,2),IF($N9=Lists!$K$3,IF($L9<1,(($U9/$L9)*((1+Inputs!$D$7)^AB$2)),((INT(AB$2/$L9)-INT((AB$2-1)/$L9))*$U9*((1+Inputs!$D$7)^AB$2))),(_xlfn.WEIBULL.DIST(AB$2,$M9,$L9,FALSE)*$U9*((1+Inputs!$D$7)^AB$2))),IF($N9=Lists!$K$3,IF($L9<1,((($T9*(1-$F9)+$S9*(1-$G9))/$L9)*((1+Inputs!$D$7)^AB$2)),((INT(AB$2/$L9)-INT((AB$2-1)/$L9))*($T9*(1-$F9)+$S9*(1-$G9))*((1+Inputs!$D$7)^AB$2))),((_xlfn.WEIBULL.DIST(AB$2,$M9,$L9,FALSE)*($T9*(1-$F9)+$S9*(1-$G9))*((1+Inputs!$D$7)^AB$2)))))) -> 74.764369 | AC9: =$E9*IF(AC$2>Inputs!$D$5,0,IF(AC$2>VLOOKUP($H9,Lists!$P$3:$Q$7,2),IF($N9=Lists!$K$3,IF($L9<1,(($U9/$L9)*((1+Inputs!$D$7)^AC$2)),((INT(AC$2/$L9)-INT((AC$2-1)/$L9))*$U9*((1+Inputs!$D$7)^AC$2))),(_xlfn.WEIBULL.DIST(AC$2,$M9,$L9,FALSE)*$U9*((1+Inputs!$D$7)^AC$2))),IF($N9=Lists!$K$3,IF($L9<1,((($T9*(1-$F9)+$S9*(1-$G9))/$L9)*((1+Inputs!$D$7)^AC$2)),((INT(AC$2/$L9)-INT((AC$2-1)/$L9))*($T9*(1-$F9)+$S9*(1-$G9))*((1+Inputs!$D$7)^AC$2))),((_xlfn.WEIBULL.DIST(AC$2,$M9,$L9,FALSE)*($T9*(1-$F9)+$S9*(1-$G9))*((1+Inputs!$D$7)^AC$2)))))) -> 76.259657 | AD9: =$E9*IF(AD$2>Inputs!$D$5,0,IF(AD$2>VLOOKUP($H9,Lists!$P$3:$Q$7,2),IF($N9=Lists!$K$3,IF($L9<1,(($U9/$L9)*((1+Inputs!$D$7)^AD$2)),((INT(AD$2/$L9)-INT((AD$2-1)/$L9))*$U9*((1+Inputs!$D$7)^AD$2))),(_xlfn.WEIBULL.DIST(AD$2,$M9,$L9,FALSE)*$U9*((1+Inputs!$D$7)^AD$2))),IF($N9=Lists!$K$3,IF($L9<1,((($T9*(1-$F9)+$S9*(1-$G9))/$L9)*((1+Inputs!$D$7)^AD$2)),((INT(AD$2/$L9)-INT((AD$2-1)/$L9))*($T9*(1-$F9)+$S9*(1-$G9))*((1+Inputs!$D$7)^AD$2))),((_xlfn.WEIBULL.DIST(AD$2,$M9,$L9,FALSE)*($T9*(1-$F9)+$S9*(1-$G9))*((1+Inputs!$D$7)^AD$2)))))) -> 77.78485 | AE9: =$E9*IF(AE$2>Inputs!$D$5,0,IF(AE$2>VLOOKUP($H9,Lists!$P$3:$Q$7,2),IF($N9=Lists!$K$3,IF($L9<1,(($U9/$L9)*((1+Inputs!$D$7)^AE$2)),((INT(AE$2/$L9)-INT((AE$2-1)/$L9))*$U9*((1+Inputs!$D$7)^AE$2))),(_xlfn.WEIBULL.DIST(AE$2,$M9,$L9,FALSE)*$U9*((1+Inputs!$D$7)^AE$2))),IF($N9=Lists!$K$3,IF($L9<1,((($T9*(1-$F9)+$S9*(1-$G9))/$L9)*((1+Inputs!$D$7)^AE$2)),((INT(AE$2/$L9)-INT((AE$2-1)/$L9))*($T9*(1-$F9)+$S9*(1-$G9))*((1+Inputs!$D$7)^AE$2))),((_xlfn.WEIBULL.DIST(AE$2,$M9,$L9,FALSE)*($T9*(1-$F9)+$S9*(1-$G9))*((1+Inputs!$D$7)^AE$2)))))) -> 79.340547 | AF9: =$E9*IF(AF$2>Inputs!$D$5,0,IF(AF$2>VLOOKUP($H9,Lists!$P$3:$Q$7,2),IF($N9=Lists!$K$3,IF($L9<1,(($U9/$L9)*((1+Inputs!$D$7)^AF$2)),((INT(AF$2/$L9)-INT((AF$2-1)/$L9))*$U9*((1+Inputs!$D$7)^AF$2))),(_xlfn.WEIBULL.DIST(AF$2,$M9,$L9,FALSE)*$U9*((1+Inputs!$D$7)^AF$2))),IF($N9=Lists!$K$3,IF($L9<1,((($T9*(1-$F9)+$S9*(1-$G9))/$L9)*((1+Inputs!$D$7)^AF$2)),((INT(AF$2/$L9)-INT((AF$2-1)/$L9))*($T9*(1-$F9)+$S9*(1-$G9))*((1+Inputs!$D$7)^AF$2))),((_xlfn.WEIBULL.DIST(AF$2,$M9,$L9,FALSE)*($T9*(1-$F9)+$S9*(1-$G9))*((1+Inputs!$D$7)^AF$2)))))) -> 80.927358 | AG9: =$E9*IF(AG$2>Inputs!$D$5,0,IF(AG$2>VLOOKUP($H9,Lists!$P$3:$Q$7,2),IF($N9=Lists!$K$3,IF($L9<1,(($U9/$L9)*((1+Inputs!$D$7)^AG$2)),((INT(AG$2/$L9)-INT((AG$2-1)/$L9))*$U9*((1+Inputs!$D$7)^AG$2))),(_xlfn.WEIBULL.DIST(AG$2,$M9,$L9,FALSE)*$U9*((1+Inputs!$D$7)^AG$2))),IF($N9=Lists!$K$3,IF($L9<1,((($T9*(1-$F9)+$S9*(1-$G9))/$L9)*((1+Inputs!$D$7)^AG$2)),((INT(AG$2/$L9)-INT((AG$2-1)/$L9))*($T9*(1-$F9)+$S9*(1-$G9))*((1+Inputs!$D$7)^AG$2))),((_xlfn.WEIBULL.DIST(AG$2,$M9,$L9,FALSE)*($T9*(1-$F9)+$S9*(1-$G9))*((1+Inputs!$D$7)^AG$2)))))) -> 82.545905 | AH9: =$E9*IF(AH$2>Inputs!$D$5,0,IF(AH$2>VLOOKUP($H9,Lists!$P$3:$Q$7,2),IF($N9=Lists!$K$3,IF($L9<1,(($U9/$L9)*((1+Inputs!$D$7)^AH$2)),((INT(AH$2/$L9)-INT((AH$2-1)/$L9))*$U9*((1+Inputs!$D$7)^AH$2))),(_xlfn.WEIBULL.DIST(AH$2,$M9,$L9,FALSE)*$U9*((1+Inputs!$D$7)^AH$2))),IF($N9=Lists!$K$3,IF($L9<1,((($T9*(1-$F9)+$S9*(1-$G9))/$L9)*((1+Inputs!$D$7)^AH$2)),((INT(AH$2/$L9)-INT((AH$2-1)/$L9))*($T9*(1-$F9)+$S9*(1-$G9))*((1+Inputs!$D$7)^AH$2))),((_xlfn.WEIBULL.DIST(AH$2,$M9,$L9,FALSE)*($T9*(1-$F9)+$S9*(1-$G9))*((1+Inputs!$D$7)^AH$2)))))) -> 84.196823 | ... BN9: =$E9*IF(BN$2>Inputs!$D$5,0,IF(BN$2>VLOOKUP($H9,Lists!$P$3:$Q$7,2),IF($N9=Lists!$K$3,IF($L9<1,(($U9/$L9)*((1+Inputs!$D$7)^BN$2)),((INT(BN$2/$L9)-INT((BN$2-1)/$L9))*$U9*((1+Inputs!$D$7)^BN$2))),(_xlfn.WEIBULL.DIST(BN$2,$M9,$L9,FALSE)*$U9*((1+Inputs!$D$7)^BN$2))),IF($N9=Lists!$K$3,IF($L9<1,((($T9*(1-$F9)+$S9*(1-$G9))/$L9)*((1+Inputs!$D$7)^BN$2)),((INT(BN$2/$L9)-INT((BN$2-1)/$L9))*($T9*(1-$F9)+$S9*(1-$G9))*((1+Inputs!$D$7)^BN$2))),((_xlfn.WEIBULL.DIST(BN$2,$M9,$L9,FALSE)*($T9*(1-$F9)+$S9*(1-$G9))*((1+Inputs!$D$7)^BN$2)))))) -> 0 | BO9: =NPV(Inputs!$D$6,BQ9:DD9) -> 1022.8348 | BP9: =BO9/SUM($Y$3:$Y$136) -> 0.00048241881 | BQ9: =MAX(AA9,($E9*IF(BQ$2>Inputs!$D$5,0,IF(BQ$2>VLOOKUP($H9,Lists!$P$3:$Q$7,2),IF($N9=Lists!$K$3,IF($L9<1,(($U9/$L9)*((1+Inputs!$D$7)^BQ$2)),((INT(BQ$2/$L9)-INT((BQ$2-1)/$L9))*$U9*((1+Inputs!$D$7)^BQ$2))),(Inputs!$D$8^((1-_xlfn.WEIBULL.DIST(BQ$2,$M9,$L9,FALSE))/_xlfn.WEIBULL.DIST(BQ$2,$M9,$L9,FALSE))*$U9*((1+Inputs!$D$7)^BQ$2))),IF($N9=Lists!$K$3,IF($L9<1,((($T9*(1-$F9)+$S9*(1-$G9))/$L9)*((1+Inputs!$D$7)^BQ$2)),((INT(BQ$2/$L9)-INT((BQ$2-1)/$L9))*($T9*(1-$F9)+$S9*(1-$G9))*((1+Inputs!$D$7)^BQ$2))),((Inputs!$D$8^((1-_xlfn.WEIBULL.DIST(BQ$2,$M9,$L9,FALSE))/_xlfn.WEIBULL.DIST(BQ$2,$M9,$L9,FALSE))*($T9*(1-$F9)+$S9*(1-$G9))*((1+Inputs!$D$7)^BQ$2)))))))) -> 73.298401 | BR9: =MAX(AB9,($E9*IF(BR$2>Inputs!$D$5,0,IF(BR$2>VLOOKUP($H9,Lists!$P$3:$Q$7,2),IF($N9=Lists!$K$3,IF($L9<1,(($U9/$L9)*((1+Inputs!$D$7)^BR$2)),((INT(BR$2/$L9)-INT((BR$2-1)/$L9))*$U9*((1+Inputs!$D$7)^BR$2))),(Inputs!$D$8^((1-_xlfn.WEIBULL.DIST(BR$2,$M9,$L9,FALSE))/_xlfn.WEIBULL.DIST(BR$2,$M9,$L9,FALSE))*$U9*((1+Inputs!$D$7)^BR$2))),IF($N9=Lists!$K$3,IF($L9<1,((($T9*(1-$F9)+$S9*(1-$G9))/$L9)*((1+Inputs!$D$7)^BR$2)),((INT(BR$2/$L9)-INT((BR$2-1)/$L9))*($T9*(1-$F9)+$S9*(1-$G9))*((1+Inputs!$D$7)^BR$2))),((Inputs!$D$8^((1-_xlfn.WEIBULL.DIST(BR$2,$M9,$L9,FALSE))/_xlfn.WEIBULL.DIST(BR$2,$M9,$L9,FALSE))*($T9*(1-$F9)+$S9*(1-$G9))*((1+Inputs!$D$7)^BR$2)))))))) -> 74.764369 | BS9: =MAX(AC9,($E9*IF(BS$2>Inputs!$D$5,0,IF(BS$2>VLOOKUP($H9,Lists!$P$3:$Q$7,2),IF($N9=Lists!$K$3,IF($L9<1,(($U9/$L9)*((1+Inputs!$D$7)^BS$2)),((INT(BS$2/$L9)-INT((BS$2-1)/$L9))*$U9*((1+Inputs!$D$7)^BS$2))),(Inputs!$D$8^((1-_xlfn.WEIBULL.DIST(BS$2,$M9,$L9,FALSE))/_xlfn.WEIBULL.DIST(BS$2,$M9,$L9,FALSE))*$U9*((1+Inputs!$D$7)^BS$2))),IF($N9=Lists!$K$3,IF($L9<1,((($T9*(1-$F9)+$S9*(1-$G9))/$L9)*((1+Inputs!$D$7)^BS$2)),((INT(BS$2/$L9)-INT((BS$2-1)/$L9))*($T9*(1-$F9)+$S9*(1-$G9))*((1+Inputs!$D$7)^BS$2))),((Inputs!$D$8^((1-_xlfn.WEIBULL.DIST(BS$2,$M9,$L9,FALSE))/_xlfn.WEIBULL.DIST(BS$2,$M9,$L9,FALSE))*($T9*(1-$F9)+$S9*(1-$G9))*((1+Inputs!$D$7)^BS$2)))))))) -> 76.259657 | BT9: =MAX(AD9,($E9*IF(BT$2>Inputs!$D$5,0,IF(BT$2>VLOOKUP($H9,Lists!$P$3:$Q$7,2),IF($N9=Lists!$K$3,IF($L9<1,(($U9/$L9)*((1+Inputs!$D$7)^BT$2)),((INT(BT$2/$L9)-INT((BT$2-1)/$L9))*$U9*((1+Inputs!$D$7)^BT$2))),(Inputs!$D$8^((1-_xlfn.WEIBULL.DIST(BT$2,$M9,$L9,FALSE))/_xlfn.WEIBULL.DIST(BT$2,$M9,$L9,FALSE))*$U9*((1+Inputs!$D$7)^BT$2))),IF($N9=Lists!$K$3,IF($L9<1,((($T9*(1-$F9)+$S9*(1-$G9))/$L9)*((1+Inputs!$D$7)^BT$2)),((INT(BT$2/$L9)-INT((BT$2-1)/$L9))*($T9*(1-$F9)+$S9*(1-$G9))*((1+Inputs!$D$7)^BT$2))),((Inputs!$D$8^((1-_xlfn.WEIBULL.DIST(BT$2,$M9,$L9,FALSE))/_xlfn.WEIBULL.DIST(BT$2,$M9,$L9,FALSE))*($T9*(1-$F9)+$S9*(1-$G9))*((1+Inputs!$D$7)^BT$2)))))))) -> 77.78485 | BU9: =MAX(AE9,($E9*IF(BU$2>Inputs!$D$5,0,IF(BU$2>VLOOKUP($H9,Lists!$P$3:$Q$7,2),IF($N9=Lists!$K$3,IF($L9<1,(($U9/$L9)*((1+Inputs!$D$7)^BU$2)),((INT(BU$2/$L9)-INT((BU$2-1)/$L9))*$U9*((1+Inputs!$D$7)^BU$2))),(Inputs!$D$8^((1-_xlfn.WEIBULL.DIST(BU$2,$M9,$L9,FALSE))/_xlfn.WEIBULL.DIST(BU$2,$M9,$L9,FALSE))*$U9*((1+Inputs!$D$7)^BU$2))),IF($N9=Lists!$K$3,IF($L9<1,((($T9*(1-$F9)+$S9*(1-$G9))/$L9)*((1+Inputs!$D$7)^BU$2)),((INT(BU$2/$L9)-INT((BU$2-1)/$L9))*($T9*(1-$F9)+$S9*(1-$G9))*((1+Inputs!$D$7)^BU$2))),((Inputs!$D$8^((1-_xlfn.WEIBULL.DIST(BU$2,$M9,$L9,FALSE))/_xlfn.WEIBULL.DIST(BU$2,$M9,$L9,FALSE))*($T9*(1-$F9)+$S9*(1-$G9))*((1+Inputs!$D$7)^BU$2)))))))) -> 79.340547 | BV9: =MAX(AF9,($E9*IF(BV$2>Inputs!$D$5,0,IF(BV$2>VLOOKUP($H9,Lists!$P$3:$Q$7,2),IF($N9=Lists!$K$3,IF($L9<1,(($U9/$L9)*((1+Inputs!$D$7)^BV$2)),((INT(BV$2/$L9)-INT((BV$2-1)/$L9))*$U9*((1+Inputs!$D$7)^BV$2))),(Inputs!$D$8^((1-_xlfn.WEIBULL.DIST(BV$2,$M9,$L9,FALSE))/_xlfn.WEIBULL.DIST(BV$2,$M9,$L9,FALSE))*$U9*((1+Inputs!$D$7)^BV$2))),IF($N9=Lists!$K$3,IF($L9<1,((($T9*(1-$F9)+$S9*(1-$G9))/$L9)*((1+Inputs!$D$7)^BV$2)),((INT(BV$2/$L9)-INT((BV$2-1)/$L9))*($T9*(1-$F9)+$S9*(1-$G9))*((1+Inputs!$D$7)^BV$2))),((Inputs!$D$8^((1-_xlfn.WEIBULL.DIST(BV$2,$M9,$L9,FALSE))/_xlfn.WEIBULL.DIST(BV$2,$M9,$L9,FALSE))*($T9*(1-$F9)+$S9*(1-$G9))*((1+Inputs!$D$7)^BV$2)))))))) -> 80.927358 | BW9: =MAX(AG9,($E9*IF(BW$2>Inputs!$D$5,0,IF(BW$2>VLOOKUP($H9,Lists!$P$3:$Q$7,2),IF($N9=Lists!$K$3,IF($L9<1,(($U9/$L9)*((1+Inputs!$D$7)^BW$2)),((INT(BW$2/$L9)-INT((BW$2-1)/$L9))*$U9*((1+Inputs!$D$7)^BW$2))),(Inputs!$D$8^((1-_xlfn.WEIBULL.DIST(BW$2,$M9,$L9,FALSE))/_xlfn.WEIBULL.DIST(BW$2,$M9,$L9,FALSE))*$U9*((1+Inputs!$D$7)^BW$2))),IF($N9=Lists!$K$3,IF($L9<1,((($T9*(1-$F9)+$S9*(1-$G9))/$L9)*((1+Inputs!$D$7)^BW$2)),((INT(BW$2/$L9)-INT((BW$2-1)/$L9))*($T9*(1-$F9)+$S9*(1-$G9))*((1+Inputs!$D$7)^BW$2))),((Inputs!$D$8^((1-_xlfn.WEIBULL.DIST(BW$2,$M9,$L9,FALSE))/_xlfn.WEIBULL.DIST(BW$2,$M9,$L9,FALSE))*($T9*(1-$F9)+$S9*(1-$G9))*((1+Inputs!$D$7)^BW$2)))))))) -> 82.545905 | BX9: =MAX(AH9,($E9*IF(BX$2>Inputs!$D$5,0,IF(BX$2>VLOOKUP($H9,Lists!$P$3:$Q$7,2),IF($N9=Lists!$K$3,IF($L9<1,(($U9/$L9)*((1+Inputs!$D$7)^BX$2)),((INT(BX$2/$L9)-INT((BX$2-1)/$L9))*$U9*((1+Inputs!$D$7)^BX$2))),(Inputs!$D$8^((1-_xlfn.WEIBULL.DIST(BX$2,$M9,$L9,FALSE))/_xlfn.WEIBULL.DIST(BX$2,$M9,$L9,FALSE))*$U9*((1+Inputs!$D$7)^BX$2))),IF($N9=Lists!$K$3,IF($L9<1,((($T9*(1-$F9)+$S9*(1-$G9))/$L9)*((1+Inputs!$D$7)^BX$2)),((INT(BX$2/$L9)-INT((BX$2-1)/$L9))*($T9*(1-$F9)+$S9*(1-$G9))*((1+Inputs!$D$7)^BX$2))),((Inputs!$D$8^((1-_xlfn.WEIBULL.DIST(BX$2,$M9,$L9,FALSE))/_xlfn.WEIBULL.DIST(BX$2,$M9,$L9,FALSE))*($T9*(1-$F9)+$S9*(1-$G9))*((1+Inputs!$D$7)^BX$2)))))))) -> 84.196823 | ... DD9: =MAX(BN9,($E9*IF(DD$2>Inputs!$D$5,0,IF(DD$2>VLOOKUP($H9,Lists!$P$3:$Q$7,2),IF($N9=Lists!$K$3,IF($L9<1,(($U9/$L9)*((1+Inputs!$D$7)^DD$2)),((INT(DD$2/$L9)-INT((DD$2-1)/$L9))*$U9*((1+Inputs!$D$7)^DD$2))),(Inputs!$D$8^((1-_xlfn.WEIBULL.DIST(DD$2,$M9,$L9,FALSE))/_xlfn.WEIBULL.DIST(DD$2,$M9,$L9,FALSE))*$U9*((1+Inputs!$D$7)^DD$2))),IF($N9=Lists!$K$3,IF($L9<1,((($T9*(1-$F9)+$S9*(1-$G9))/$L9)*((1+Inputs!$D$7)^DD$2)),((INT(DD$2/$L9)-INT((DD$2-1)/$L9))*($T9*(1-$F9)+$S9*(1-$G9))*((1+Inputs!$D$7)^DD$2))),((Inputs!$D$8^((1-_xlfn.WEIBULL.DIST(DD$2,$M9,$L9,FALSE))/_xlfn.WEIBULL.DIST(DD$2,$M9,$L9,FALSE))*($T9*(1-$F9)+$S9*(1-$G9))*((1+Inputs!$D$7)^DD$2)))))))) -> 0
A10: Maintain a log of cumulative power delivery (kWh to date) and chart this value against date. Chart the value even for uneven or infrequent intervals. Explain variation by season or weather. | B10: Administration | C10: Management | D10: Meter | E10: =IF(Inputs!D41=Lists!I4,0,1) -> 1 | F10: 0 | G10: 0 | H10: N/A | J10: Administrator | K10: =VLOOKUP(J10,'Labor Rates'!$A$1:$F$16,2) -> 22.995577 | L10: 0.08 | M10: 1 | N10: interval | O10: 1 | P10: 0.05 | Q10: =O10*P10/L10 -> 0.625 | R10: 0 | S10: =P10*O10*K10 -> 1.1497788 | T10: =R10*O10 -> 0 | U10: =E10*(T10+S10) -> 1.1497788 | X10: =AVERAGE(AA10:AT10) -> 17.809584 | Y10: =NPV(Inputs!$D$6,AA10:BN10) -> 204.56695 | Z10: =Y10/SUM($Y$3:$Y$136) -> 9.6483762e-05 | AA10: =$E10*IF(AA$2>Inputs!$D$5,0,IF(AA$2>VLOOKUP($H10,Lists!$P$3:$Q$7,2),IF($N10=Lists!$K$3,IF($L10<1,(($U10/$L10)*((1+Inputs!$D$7)^AA$2)),((INT(AA$2/$L10)-INT((AA$2-1)/$L10))*$U10*((1+Inputs!$D$7)^AA$2))),(_xlfn.WEIBULL.DIST(AA$2,$M10,$L10,FALSE)*$U10*((1+Inputs!$D$7)^AA$2))),IF($N10=Lists!$K$3,IF($L10<1,((($T10*(1-$F10)+$S10*(1-$G10))/$L10)*((1+Inputs!$D$7)^AA$2)),((INT(AA$2/$L10)-INT((AA$2-1)/$L10))*($T10*(1-$F10)+$S10*(1-$G10))*((1+Inputs!$D$7)^AA$2))),((_xlfn.WEIBULL.DIST(AA$2,$M10,$L10,FALSE)*($T10*(1-$F10)+$S10*(1-$G10))*((1+Inputs!$D$7)^AA$2)))))) -> 14.65968 | AB10: =$E10*IF(AB$2>Inputs!$D$5,0,IF(AB$2>VLOOKUP($H10,Lists!$P$3:$Q$7,2),IF($N10=Lists!$K$3,IF($L10<1,(($U10/$L10)*((1+Inputs!$D$7)^AB$2)),((INT(AB$2/$L10)-INT((AB$2-1)/$L10))*$U10*((1+Inputs!$D$7)^AB$2))),(_xlfn.WEIBULL.DIST(AB$2,$M10,$L10,FALSE)*$U10*((1+Inputs!$D$7)^AB$2))),IF($N10=Lists!$K$3,IF($L10<1,((($T10*(1-$F10)+$S10*(1-$G10))/$L10)*((1+Inputs!$D$7)^AB$2)),((INT(AB$2/$L10)-INT((AB$2-1)/$L10))*($T10*(1-$F10)+$S10*(1-$G10))*((1+Inputs!$D$7)^AB$2))),((_xlfn.WEIBULL.DIST(AB$2,$M10,$L10,FALSE)*($T10*(1-$F10)+$S10*(1-$G10))*((1+Inputs!$D$7)^AB$2)))))) -> 14.952874 | AC10: =$E10*IF(AC$2>Inputs!$D$5,0,IF(AC$2>VLOOKUP($H10,Lists!$P$3:$Q$7,2),IF($N10=Lists!$K$3,IF($L10<1,(($U10/$L10)*((1+Inputs!$D$7)^AC$2)),((INT(AC$2/$L10)-INT((AC$2-1)/$L10))*$U10*((1+Inputs!$D$7)^AC$2))),(_xlfn.WEIBULL.DIST(AC$2,$M10,$L10,FALSE)*$U10*((1+Inputs!$D$7)^AC$2))),IF($N10=Lists!$K$3,IF($L10<1,((($T10*(1-$F10)+$S10*(1-$G10))/$L10)*((1+Inputs!$D$7)^AC$2)),((INT(AC$2/$L10)-INT((AC$2-1)/$L10))*($T10*(1-$F10)+$S10*(1-$G10))*((1+Inputs!$D$7)^AC$2))),((_xlfn.WEIBULL.DIST(AC$2,$M10,$L10,FALSE)*($T10*(1-$F10)+$S10*(1-$G10))*((1+Inputs!$D$7)^AC$2)))))) -> 15.251931 | AD10: =$E10*IF(AD$2>Inputs!$D$5,0,IF(AD$2>VLOOKUP($H10,Lists!$P$3:$Q$7,2),IF($N10=Lists!$K$3,IF($L10<1,(($U10/$L10)*((1+Inputs!$D$7)^AD$2)),((INT(AD$2/$L10)-INT((AD$2-1)/$L10))*$U10*((1+Inputs!$D$7)^AD$2))),(_xlfn.WEIBULL.DIST(AD$2,$M10,$L10,FALSE)*$U10*((1+Inputs!$D$7)^AD$2))),IF($N10=Lists!$K$3,IF($L10<1,((($T10*(1-$F10)+$S10*(1-$G10))/$L10)*((1+Inputs!$D$7)^AD$2)),((INT(AD$2/$L10)-INT((AD$2-1)/$L10))*($T10*(1-$F10)+$S10*(1-$G10))*((1+Inputs!$D$7)^AD$2))),((_xlfn.WEIBULL.DIST(AD$2,$M10,$L10,FALSE)*($T10*(1-$F10)+$S10*(1-$G10))*((1+Inputs!$D$7)^AD$2)))))) -> 15.55697 | AE10: =$E10*IF(AE$2>Inputs!$D$5,0,IF(AE$2>VLOOKUP($H10,Lists!$P$3:$Q$7,2),IF($N10=Lists!$K$3,IF($L10<1,(($U10/$L10)*((1+Inputs!$D$7)^AE$2)),((INT(AE$2/$L10)-INT((AE$2-1)/$L10))*$U10*((1+Inputs!$D$7)^AE$2))),(_xlfn.WEIBULL.DIST(AE$2,$M10,$L10,FALSE)*$U10*((1+Inputs!$D$7)^AE$2))),IF($N10=Lists!$K$3,IF($L10<1,((($T10*(1-$F10)+$S10*(1-$G10))/$L10)*((1+Inputs!$D$7)^AE$2)),((INT(AE$2/$L10)-INT((AE$2-1)/$L10))*($T10*(1-$F10)+$S10*(1-$G10))*((1+Inputs!$D$7)^AE$2))),((_xlfn.WEIBULL.DIST(AE$2,$M10,$L10,FALSE)*($T10*(1-$F10)+$S10*(1-$G10))*((1+Inputs!$D$7)^AE$2)))))) -> 15.868109 | AF10: =$E10*IF(AF$2>Inputs!$D$5,0,IF(AF$2>VLOOKUP($H10,Lists!$P$3:$Q$7,2),IF($N10=Lists!$K$3,IF($L10<1,(($U10/$L10)*((1+Inputs!$D$7)^AF$2)),((INT(AF$2/$L10)-INT((AF$2-1)/$L10))*$U10*((1+Inputs!$D$7)^AF$2))),(_xlfn.WEIBULL.DIST(AF$2,$M10,$L10,FALSE)*$U10*((1+Inputs!$D$7)^AF$2))),IF($N10=Lists!$K$3,IF($L10<1,((($T10*(1-$F10)+$S10*(1-$G10))/$L10)*((1+Inputs!$D$7)^AF$2)),((INT(AF$2/$L10)-INT((AF$2-1)/$L10))*($T10*(1-$F10)+$S10*(1-$G10))*((1+Inputs!$D$7)^AF$2))),((_xlfn.WEIBULL.DIST(AF$2,$M10,$L10,FALSE)*($T10*(1-$F10)+$S10*(1-$G10))*((1+Inputs!$D$7)^AF$2)))))) -> 16.185472 | AG10: =$E10*IF(AG$2>Inputs!$D$5,0,IF(AG$2>VLOOKUP($H10,Lists!$P$3:$Q$7,2),IF($N10=Lists!$K$3,IF($L10<1,(($U10/$L10)*((1+Inputs!$D$7)^AG$2)),((INT(AG$2/$L10)-INT((AG$2-1)/$L10))*$U10*((1+Inputs!$D$7)^AG$2))),(_xlfn.WEIBULL.DIST(AG$2,$M10,$L10,FALSE)*$U10*((1+Inputs!$D$7)^AG$2))),IF($N10=Lists!$K$3,IF($L10<1,((($T10*(1-$F10)+$S10*(1-$G10))/$L10)*((1+Inputs!$D$7)^AG$2)),((INT(AG$2/$L10)-INT((AG$2-1)/$L10))*($T10*(1-$F10)+$S10*(1-$G10))*((1+Inputs!$D$7)^AG$2))),((_xlfn.WEIBULL.DIST(AG$2,$M10,$L10,FALSE)*($T10*(1-$F10)+$S10*(1-$G10))*((1+Inputs!$D$7)^AG$2)))))) -> 16.509181 | AH10: =$E10*IF(AH$2>Inputs!$D$5,0,IF(AH$2>VLOOKUP($H10,Lists!$P$3:$Q$7,2),IF($N10=Lists!$K$3,IF($L10<1,(($U10/$L10)*((1+Inputs!$D$7)^AH$2)),((INT(AH$2/$L10)-INT((AH$2-1)/$L10))*$U10*((1+Inputs!$D$7)^AH$2))),(_xlfn.WEIBULL.DIST(AH$2,$M10,$L10,FALSE)*$U10*((1+Inputs!$D$7)^AH$2))),IF($N10=Lists!$K$3,IF($L10<1,((($T10*(1-$F10)+$S10*(1-$G10))/$L10)*((1+Inputs!$D$7)^AH$2)),((INT(AH$2/$L10)-INT((AH$2-1)/$L10))*($T10*(1-$F10)+$S10*(1-$G10))*((1+Inputs!$D$7)^AH$2))),((_xlfn.WEIBULL.DIST(AH$2,$M10,$L10,FALSE)*($T10*(1-$F10)+$S10*(1-$G10))*((1+Inputs!$D$7)^AH$2)))))) -> 16.839365 | ... BN10: =$E10*IF(BN$2>Inputs!$D$5,0,IF(BN$2>VLOOKUP($H10,Lists!$P$3:$Q$7,2),IF($N10=Lists!$K$3,IF($L10<1,(($U10/$L10)*((1+Inputs!$D$7)^BN$2)),((INT(BN$2/$L10)-INT((BN$2-1)/$L10))*$U10*((1+Inputs!$D$7)^BN$2))),(_xlfn.WEIBULL.DIST(BN$2,$M10,$L10,FALSE)*$U10*((1+Inputs!$D$7)^BN$2))),IF($N10=Lists!$K$3,IF($L10<1,((($T10*(1-$F10)+$S10*(1-$G10))/$L10)*((1+Inputs!$D$7)^BN$2)),((INT(BN$2/$L10)-INT((BN$2-1)/$L10))*($T10*(1-$F10)+$S10*(1-$G10))*((1+Inputs!$D$7)^BN$2))),((_xlfn.WEIBULL.DIST(BN$2,$M10,$L10,FALSE)*($T10*(1-$F10)+$S10*(1-$G10))*((1+Inputs!$D$7)^BN$2)))))) -> 0 | BO10: =NPV(Inputs!$D$6,BQ10:DD10) -> 204.56695 | BP10: =BO10/SUM($Y$3:$Y$136) -> 9.6483762e-05 | BQ10: =MAX(AA10,($E10*IF(BQ$2>Inputs!$D$5,0,IF(BQ$2>VLOOKUP($H10,Lists!$P$3:$Q$7,2),IF($N10=Lists!$K$3,IF($L10<1,(($U10/$L10)*((1+Inputs!$D$7)^BQ$2)),((INT(BQ$2/$L10)-INT((BQ$2-1)/$L10))*$U10*((1+Inputs!$D$7)^BQ$2))),(Inputs!$D$8^((1-_xlfn.WEIBULL.DIST(BQ$2,$M10,$L10,FALSE))/_xlfn.WEIBULL.DIST(BQ$2,$M10,$L10,FALSE))*$U10*((1+Inputs!$D$7)^BQ$2))),IF($N10=Lists!$K$3,IF($L10<1,((($T10*(1-$F10)+$S10*(1-$G10))/$L10)*((1+Inputs!$D$7)^BQ$2)),((INT(BQ$2/$L10)-INT((BQ$2-1)/$L10))*($T10*(1-$F10)+$S10*(1-$G10))*((1+Inputs!$D$7)^BQ$2))),((Inputs!$D$8^((1-_xlfn.WEIBULL.DIST(BQ$2,$M10,$L10,FALSE))/_xlfn.WEIBULL.DIST(BQ$2,$M10,$L10,FALSE))*($T10*(1-$F10)+$S10*(1-$G10))*((1+Inputs!$D$7)^BQ$2)))))))) -> 14.65968 | BR10: =MAX(AB10,($E10*IF(BR$2>Inputs!$D$5,0,IF(BR$2>VLOOKUP($H10,Lists!$P$3:$Q$7,2),IF($N10=Lists!$K$3,IF($L10<1,(($U10/$L10)*((1+Inputs!$D$7)^BR$2)),((INT(BR$2/$L10)-INT((BR$2-1)/$L10))*$U10*((1+Inputs!$D$7)^BR$2))),(Inputs!$D$8^((1-_xlfn.WEIBULL.DIST(BR$2,$M10,$L10,FALSE))/_xlfn.WEIBULL.DIST(BR$2,$M10,$L10,FALSE))*$U10*((1+Inputs!$D$7)^BR$2))),IF($N10=Lists!$K$3,IF($L10<1,((($T10*(1-$F10)+$S10*(1-$G10))/$L10)*((1+Inputs!$D$7)^BR$2)),((INT(BR$2/$L10)-INT((BR$2-1)/$L10))*($T10*(1-$F10)+$S10*(1-$G10))*((1+Inputs!$D$7)^BR$2))),((Inputs!$D$8^((1-_xlfn.WEIBULL.DIST(BR$2,$M10,$L10,FALSE))/_xlfn.WEIBULL.DIST(BR$2,$M10,$L10,FALSE))*($T10*(1-$F10)+$S10*(1-$G10))*((1+Inputs!$D$7)^BR$2)))))))) -> 14.952874 | BS10: =MAX(AC10,($E10*IF(BS$2>Inputs!$D$5,0,IF(BS$2>VLOOKUP($H10,Lists!$P$3:$Q$7,2),IF($N10=Lists!$K$3,IF($L10<1,(($U10/$L10)*((1+Inputs!$D$7)^BS$2)),((INT(BS$2/$L10)-INT((BS$2-1)/$L10))*$U10*((1+Inputs!$D$7)^BS$2))),(Inputs!$D$8^((1-_xlfn.WEIBULL.DIST(BS$2,$M10,$L10,FALSE))/_xlfn.WEIBULL.DIST(BS$2,$M10,$L10,FALSE))*$U10*((1+Inputs!$D$7)^BS$2))),IF($N10=Lists!$K$3,IF($L10<1,((($T10*(1-$F10)+$S10*(1-$G10))/$L10)*((1+Inputs!$D$7)^BS$2)),((INT(BS$2/$L10)-INT((BS$2-1)/$L10))*($T10*(1-$F10)+$S10*(1-$G10))*((1+Inputs!$D$7)^BS$2))),((Inputs!$D$8^((1-_xlfn.WEIBULL.DIST(BS$2,$M10,$L10,FALSE))/_xlfn.WEIBULL.DIST(BS$2,$M10,$L10,FALSE))*($T10*(1-$F10)+$S10*(1-$G10))*((1+Inputs!$D$7)^BS$2)))))))) -> 15.251931 | BT10: =MAX(AD10,($E10*IF(BT$2>Inputs!$D$5,0,IF(BT$2>VLOOKUP($H10,Lists!$P$3:$Q$7,2),IF($N10=Lists!$K$3,IF($L10<1,(($U10/$L10)*((1+Inputs!$D$7)^BT$2)),((INT(BT$2/$L10)-INT((BT$2-1)/$L10))*$U10*((1+Inputs!$D$7)^BT$2))),(Inputs!$D$8^((1-_xlfn.WEIBULL.DIST(BT$2,$M10,$L10,FALSE))/_xlfn.WEIBULL.DIST(BT$2,$M10,$L10,FALSE))*$U10*((1+Inputs!$D$7)^BT$2))),IF($N10=Lists!$K$3,IF($L10<1,((($T10*(1-$F10)+$S10*(1-$G10))/$L10)*((1+Inputs!$D$7)^BT$2)),((INT(BT$2/$L10)-INT((BT$2-1)/$L10))*($T10*(1-$F10)+$S10*(1-$G10))*((1+Inputs!$D$7)^BT$2))),((Inputs!$D$8^((1-_xlfn.WEIBULL.DIST(BT$2,$M10,$L10,FALSE))/_xlfn.WEIBULL.DIST(BT$2,$M10,$L10,FALSE))*($T10*(1-$F10)+$S10*(1-$G10))*((1+Inputs!$D$7)^BT$2)))))))) -> 15.55697 | BU10: =MAX(AE10,($E10*IF(BU$2>Inputs!$D$5,0,IF(BU$2>VLOOKUP($H10,Lists!$P$3:$Q$7,2),IF($N10=Lists!$K$3,IF($L10<1,(($U10/$L10)*((1+Inputs!$D$7)^BU$2)),((INT(BU$2/$L10)-INT((BU$2-1)/$L10))*$U10*((1+Inputs!$D$7)^BU$2))),(Inputs!$D$8^((1-_xlfn.WEIBULL.DIST(BU$2,$M10,$L10,FALSE))/_xlfn.WEIBULL.DIST(BU$2,$M10,$L10,FALSE))*$U10*((1+Inputs!$D$7)^BU$2))),IF($N10=Lists!$K$3,IF($L10<1,((($T10*(1-$F10)+$S10*(1-$G10))/$L10)*((1+Inputs!$D$7)^BU$2)),((INT(BU$2/$L10)-INT((BU$2-1)/$L10))*($T10*(1-$F10)+$S10*(1-$G10))*((1+Inputs!$D$7)^BU$2))),((Inputs!$D$8^((1-_xlfn.WEIBULL.DIST(BU$2,$M10,$L10,FALSE))/_xlfn.WEIBULL.DIST(BU$2,$M10,$L10,FALSE))*($T10*(1-$F10)+$S10*(1-$G10))*((1+Inputs!$D$7)^BU$2)))))))) -> 15.868109 | BV10: =MAX(AF10,($E10*IF(BV$2>Inputs!$D$5,0,IF(BV$2>VLOOKUP($H10,Lists!$P$3:$Q$7,2),IF($N10=Lists!$K$3,IF($L10<1,(($U10/$L10)*((1+Inputs!$D$7)^BV$2)),((INT(BV$2/$L10)-INT((BV$2-1)/$L10))*$U10*((1+Inputs!$D$7)^BV$2))),(Inputs!$D$8^((1-_xlfn.WEIBULL.DIST(BV$2,$M10,$L10,FALSE))/_xlfn.WEIBULL.DIST(BV$2,$M10,$L10,FALSE))*$U10*((1+Inputs!$D$7)^BV$2))),IF($N10=Lists!$K$3,IF($L10<1,((($T10*(1-$F10)+$S10*(1-$G10))/$L10)*((1+Inputs!$D$7)^BV$2)),((INT(BV$2/$L10)-INT((BV$2-1)/$L10))*($T10*(1-$F10)+$S10*(1-$G10))*((1+Inputs!$D$7)^BV$2))),((Inputs!$D$8^((1-_xlfn.WEIBULL.DIST(BV$2,$M10,$L10,FALSE))/_xlfn.WEIBULL.DIST(BV$2,$M10,$L10,FALSE))*($T10*(1-$F10)+$S10*(1-$G10))*((1+Inputs!$D$7)^BV$2)))))))) -> 16.185472 | BW10: =MAX(AG10,($E10*IF(BW$2>Inputs!$D$5,0,IF(BW$2>VLOOKUP($H10,Lists!$P$3:$Q$7,2),IF($N10=Lists!$K$3,IF($L10<1,(($U10/$L10)*((1+Inputs!$D$7)^BW$2)),((INT(BW$2/$L10)-INT((BW$2-1)/$L10))*$U10*((1+Inputs!$D$7)^BW$2))),(Inputs!$D$8^((1-_xlfn.WEIBULL.DIST(BW$2,$M10,$L10,FALSE))/_xlfn.WEIBULL.DIST(BW$2,$M10,$L10,FALSE))*$U10*((1+Inputs!$D$7)^BW$2))),IF($N10=Lists!$K$3,IF($L10<1,((($T10*(1-$F10)+$S10*(1-$G10))/$L10)*((1+Inputs!$D$7)^BW$2)),((INT(BW$2/$L10)-INT((BW$2-1)/$L10))*($T10*(1-$F10)+$S10*(1-$G10))*((1+Inputs!$D$7)^BW$2))),((Inputs!$D$8^((1-_xlfn.WEIBULL.DIST(BW$2,$M10,$L10,FALSE))/_xlfn.WEIBULL.DIST(BW$2,$M10,$L10,FALSE))*($T10*(1-$F10)+$S10*(1-$G10))*((1+Inputs!$D$7)^BW$2)))))))) -> 16.509181 | BX10: =MAX(AH10,($E10*IF(BX$2>Inputs!$D$5,0,IF(BX$2>VLOOKUP($H10,Lists!$P$3:$Q$7,2),IF($N10=Lists!$K$3,IF($L10<1,(($U10/$L10)*((1+Inputs!$D$7)^BX$2)),((INT(BX$2/$L10)-INT((BX$2-1)/$L10))*$U10*((1+Inputs!$D$7)^BX$2))),(Inputs!$D$8^((1-_xlfn.WEIBULL.DIST(BX$2,$M10,$L10,FALSE))/_xlfn.WEIBULL.DIST(BX$2,$M10,$L10,FALSE))*$U10*((1+Inputs!$D$7)^BX$2))),IF($N10=Lists!$K$3,IF($L10<1,((($T10*(1-$F10)+$S10*(1-$G10))/$L10)*((1+Inputs!$D$7)^BX$2)),((INT(BX$2/$L10)-INT((BX$2-1)/$L10))*($T10*(1-$F10)+$S10*(1-$G10))*((1+Inputs!$D$7)^BX$2))),((Inputs!$D$8^((1-_xlfn.WEIBULL.DIST(BX$2,$M10,$L10,FALSE))/_xlfn.WEIBULL.DIST(BX$2,$M10,$L10,FALSE))*($T10*(1-$F10)+$S10*(1-$G10))*((1+Inputs!$D$7)^BX$2)))))))) -> 16.839365 | ... DD10: =MAX(BN10,($E10*IF(DD$2>Inputs!$D$5,0,IF(DD$2>VLOOKUP($H10,Lists!$P$3:$Q$7,2),IF($N10=Lists!$K$3,IF($L10<1,(($U10/$L10)*((1+Inputs!$D$7)^DD$2)),((INT(DD$2/$L10)-INT((DD$2-1)/$L10))*$U10*((1+Inputs!$D$7)^DD$2))),(Inputs!$D$8^((1-_xlfn.WEIBULL.DIST(DD$2,$M10,$L10,FALSE))/_xlfn.WEIBULL.DIST(DD$2,$M10,$L10,FALSE))*$U10*((1+Inputs!$D$7)^DD$2))),IF($N10=Lists!$K$3,IF($L10<1,((($T10*(1-$F10)+$S10*(1-$G10))/$L10)*((1+Inputs!$D$7)^DD$2)),((INT(DD$2/$L10)-INT((DD$2-1)/$L10))*($T10*(1-$F10)+$S10*(1-$G10))*((1+Inputs!$D$7)^DD$2))),((Inputs!$D$8^((1-_xlfn.WEIBULL.DIST(DD$2,$M10,$L10,FALSE))/_xlfn.WEIBULL.DIST(DD$2,$M10,$L10,FALSE))*($T10*(1-$F10)+$S10*(1-$G10))*((1+Inputs!$D$7)^DD$2)))))))) -> 0
A11: Replace protective devices (breakers) in building panel | B11: Corrective | C11: Repair | D11: AC wiring | E11: 1 | F11: 1 | G11: 1 | H11: N/A | J11: Master electrician | K11: =VLOOKUP(J11,'Labor Rates'!$A$1:$F$16,2) -> 32.012019 | L11: 25 | M11: 3 | N11: Weibull | O11: 3 | P11: 0.25 | Q11: =O11*P11/L11 -> 0.03 | R11: 10 | S11: =P11*O11*K11 -> 24.009014 | T11: =R11*O11 -> 30 | U11: =E11*(T11+S11) -> 54.009014 | X11: =AVERAGE(AA11:AT11) -> 1.5378367 | Y11: =NPV(Inputs!$D$6,AA11:BN11) -> 15.676871 | Z11: =Y11/SUM($Y$3:$Y$136) -> 7.3939777e-06 | AA11: =$E11*IF(AA$2>Inputs!$D$5,0,IF(AA$2>VLOOKUP($H11,Lists!$P$3:$Q$7,2),IF($N11=Lists!$K$3,IF($L11<1,(($U11/$L11)*((1+Inputs!$D$7)^AA$2)),((INT(AA$2/$L11)-INT((AA$2-1)/$L11))*$U11*((1+Inputs!$D$7)^AA$2))),(_xlfn.WEIBULL.DIST(AA$2,$M11,$L11,FALSE)*$U11*((1+Inputs!$D$7)^AA$2))),IF($N11=Lists!$K$3,IF($L11<1,((($T11*(1-$F11)+$S11*(1-$G11))/$L11)*((1+Inputs!$D$7)^AA$2)),((INT(AA$2/$L11)-INT((AA$2-1)/$L11))*($T11*(1-$F11)+$S11*(1-$G11))*((1+Inputs!$D$7)^AA$2))),((_xlfn.WEIBULL.DIST(AA$2,$M11,$L11,FALSE)*($T11*(1-$F11)+$S11*(1-$G11))*((1+Inputs!$D$7)^AA$2)))))) -> 0.010576448 | AB11: =$E11*IF(AB$2>Inputs!$D$5,0,IF(AB$2>VLOOKUP($H11,Lists!$P$3:$Q$7,2),IF($N11=Lists!$K$3,IF($L11<1,(($U11/$L11)*((1+Inputs!$D$7)^AB$2)),((INT(AB$2/$L11)-INT((AB$2-1)/$L11))*$U11*((1+Inputs!$D$7)^AB$2))),(_xlfn.WEIBULL.DIST(AB$2,$M11,$L11,FALSE)*$U11*((1+Inputs!$D$7)^AB$2))),IF($N11=Lists!$K$3,IF($L11<1,((($T11*(1-$F11)+$S11*(1-$G11))/$L11)*((1+Inputs!$D$7)^AB$2)),((INT(AB$2/$L11)-INT((AB$2-1)/$L11))*($T11*(1-$F11)+$S11*(1-$G11))*((1+Inputs!$D$7)^AB$2))),((_xlfn.WEIBULL.DIST(AB$2,$M11,$L11,FALSE)*($T11*(1-$F11)+$S11*(1-$G11))*((1+Inputs!$D$7)^AB$2)))))) -> 0.043132582 | AC11: =$E11*IF(AC$2>Inputs!$D$5,0,IF(AC$2>VLOOKUP($H11,Lists!$P$3:$Q$7,2),IF($N11=Lists!$K$3,IF($L11<1,(($U11/$L11)*((1+Inputs!$D$7)^AC$2)),((INT(AC$2/$L11)-INT((AC$2-1)/$L11))*$U11*((1+Inputs!$D$7)^AC$2))),(_xlfn.WEIBULL.DIST(AC$2,$M11,$L11,FALSE)*$U11*((1+Inputs!$D$7)^AC$2))),IF($N11=Lists!$K$3,IF($L11<1,((($T11*(1-$F11)+$S11*(1-$G11))/$L11)*((1+Inputs!$D$7)^AC$2)),((INT(AC$2/$L11)-INT((AC$2-1)/$L11))*($T11*(1-$F11)+$S11*(1-$G11))*((1+Inputs!$D$7)^AC$2))),((_xlfn.WEIBULL.DIST(AC$2,$M11,$L11,FALSE)*($T11*(1-$F11)+$S11*(1-$G11))*((1+Inputs!$D$7)^AC$2)))))) -> 0.098868978 | AD11: =$E11*IF(AD$2>Inputs!$D$5,0,IF(AD$2>VLOOKUP($H11,Lists!$P$3:$Q$7,2),IF($N11=Lists!$K$3,IF($L11<1,(($U11/$L11)*((1+Inputs!$D$7)^AD$2)),((INT(AD$2/$L11)-INT((AD$2-1)/$L11))*$U11*((1+Inputs!$D$7)^AD$2))),(_xlfn.WEIBULL.DIST(AD$2,$M11,$L11,FALSE)*$U11*((1+Inputs!$D$7)^AD$2))),IF($N11=Lists!$K$3,IF($L11<1,((($T11*(1-$F11)+$S11*(1-$G11))/$L11)*((1+Inputs!$D$7)^AD$2)),((INT(AD$2/$L11)-INT((AD$2-1)/$L11))*($T11*(1-$F11)+$S11*(1-$G11))*((1+Inputs!$D$7)^AD$2))),((_xlfn.WEIBULL.DIST(AD$2,$M11,$L11,FALSE)*($T11*(1-$F11)+$S11*(1-$G11))*((1+Inputs!$D$7)^AD$2)))))) -> 0.17885837 | AE11: =$E11*IF(AE$2>Inputs!$D$5,0,IF(AE$2>VLOOKUP($H11,Lists!$P$3:$Q$7,2),IF($N11=Lists!$K$3,IF($L11<1,(($U11/$L11)*((1+Inputs!$D$7)^AE$2)),((INT(AE$2/$L11)-INT((AE$2-1)/$L11))*$U11*((1+Inputs!$D$7)^AE$2))),(_xlfn.WEIBULL.DIST(AE$2,$M11,$L11,FALSE)*$U11*((1+Inputs!$D$7)^AE$2))),IF($N11=Lists!$K$3,IF($L11<1,((($T11*(1-$F11)+$S11*(1-$G11))/$L11)*((1+Inputs!$D$7)^AE$2)),((INT(AE$2/$L11)-INT((AE$2-1)/$L11))*($T11*(1-$F11)+$S11*(1-$G11))*((1+Inputs!$D$7)^AE$2))),((_xlfn.WEIBULL.DIST(AE$2,$M11,$L11,FALSE)*($T11*(1-$F11)+$S11*(1-$G11))*((1+Inputs!$D$7)^AE$2)))))) -> 0.28394485 | AF11: =$E11*IF(AF$2>Inputs!$D$5,0,IF(AF$2>VLOOKUP($H11,Lists!$P$3:$Q$7,2),IF($N11=Lists!$K$3,IF($L11<1,(($U11/$L11)*((1+Inputs!$D$7)^AF$2)),((INT(AF$2/$L11)-INT((AF$2-1)/$L11))*$U11*((1+Inputs!$D$7)^AF$2))),(_xlfn.WEIBULL.DIST(AF$2,$M11,$L11,FALSE)*$U11*((1+Inputs!$D$7)^AF$2))),IF($N11=Lists!$K$3,IF($L11<1,((($T11*(1-$F11)+$S11*(1-$G11))/$L11)*((1+Inputs!$D$7)^AF$2)),((INT(AF$2/$L11)-INT((AF$2-1)/$L11))*($T11*(1-$F11)+$S11*(1-$G11))*((1+Inputs!$D$7)^AF$2))),((_xlfn.WEIBULL.DIST(AF$2,$M11,$L11,FALSE)*($T11*(1-$F11)+$S11*(1-$G11))*((1+Inputs!$D$7)^AF$2)))))) -> 0.4146363 | AG11: =$E11*IF(AG$2>Inputs!$D$5,0,IF(AG$2>VLOOKUP($H11,Lists!$P$3:$Q$7,2),IF($N11=Lists!$K$3,IF($L11<1,(($U11/$L11)*((1+Inputs!$D$7)^AG$2)),((INT(AG$2/$L11)-INT((AG$2-1)/$L11))*$U11*((1+Inputs!$D$7)^AG$2))),(_xlfn.WEIBULL.DIST(AG$2,$M11,$L11,FALSE)*$U11*((1+Inputs!$D$7)^AG$2))),IF($N11=Lists!$K$3,IF($L11<1,((($T11*(1-$F11)+$S11*(1-$G11))/$L11)*((1+Inputs!$D$7)^AG$2)),((INT(AG$2/$L11)-INT((AG$2-1)/$L11))*($T11*(1-$F11)+$S11*(1-$G11))*((1+Inputs!$D$7)^AG$2))),((_xlfn.WEIBULL.DIST(AG$2,$M11,$L11,FALSE)*($T11*(1-$F11)+$S11*(1-$G11))*((1+Inputs!$D$7)^AG$2)))))) -> 0.57099346 | AH11: =$E11*IF(AH$2>Inputs!$D$5,0,IF(AH$2>VLOOKUP($H11,Lists!$P$3:$Q$7,2),IF($N11=Lists!$K$3,IF($L11<1,(($U11/$L11)*((1+Inputs!$D$7)^AH$2)),((INT(AH$2/$L11)-INT((AH$2-1)/$L11))*$U11*((1+Inputs!$D$7)^AH$2))),(_xlfn.WEIBULL.DIST(AH$2,$M11,$L11,FALSE)*$U11*((1+Inputs!$D$7)^AH$2))),IF($N11=Lists!$K$3,IF($L11<1,((($T11*(1-$F11)+$S11*(1-$G11))/$L11)*((1+Inputs!$D$7)^AH$2)),((INT(AH$2/$L11)-INT((AH$2-1)/$L11))*($T11*(1-$F11)+$S11*(1-$G11))*((1+Inputs!$D$7)^AH$2))),((_xlfn.WEIBULL.DIST(AH$2,$M11,$L11,FALSE)*($T11*(1-$F11)+$S11*(1-$G11))*((1+Inputs!$D$7)^AH$2)))))) -> 0.75251969 | ... BN11: =$E11*IF(BN$2>Inputs!$D$5,0,IF(BN$2>VLOOKUP($H11,Lists!$P$3:$Q$7,2),IF($N11=Lists!$K$3,IF($L11<1,(($U11/$L11)*((1+Inputs!$D$7)^BN$2)),((INT(BN$2/$L11)-INT((BN$2-1)/$L11))*$U11*((1+Inputs!$D$7)^BN$2))),(_xlfn.WEIBULL.DIST(BN$2,$M11,$L11,FALSE)*$U11*((1+Inputs!$D$7)^BN$2))),IF($N11=Lists!$K$3,IF($L11<1,((($T11*(1-$F11)+$S11*(1-$G11))/$L11)*((1+Inputs!$D$7)^BN$2)),((INT(BN$2/$L11)-INT((BN$2-1)/$L11))*($T11*(1-$F11)+$S11*(1-$G11))*((1+Inputs!$D$7)^BN$2))),((_xlfn.WEIBULL.DIST(BN$2,$M11,$L11,FALSE)*($T11*(1-$F11)+$S11*(1-$G11))*((1+Inputs!$D$7)^BN$2)))))) -> 0 | BO11: =NPV(Inputs!$D$6,BQ11:DD11) -> 44.142542 | BP11: =BO11/SUM($Y$3:$Y$136) -> 2.0819778e-05 | BQ11: =MAX(AA11,($E11*IF(BQ$2>Inputs!$D$5,0,IF(BQ$2>VLOOKUP($H11,Lists!$P$3:$Q$7,2),IF($N11=Lists!$K$3,IF($L11<1,(($U11/$L11)*((1+Inputs!$D$7)^BQ$2)),((INT(BQ$2/$L11)-INT((BQ$2-1)/$L11))*$U11*((1+Inputs!$D$7)^BQ$2))),(Inputs!$D$8^((1-_xlfn.WEIBULL.DIST(BQ$2,$M11,$L11,FALSE))/_xlfn.WEIBULL.DIST(BQ$2,$M11,$L11,FALSE))*$U11*((1+Inputs!$D$7)^BQ$2))),IF($N11=Lists!$K$3,IF($L11<1,((($T11*(1-$F11)+$S11*(1-$G11))/$L11)*((1+Inputs!$D$7)^BQ$2)),((INT(BQ$2/$L11)-INT((BQ$2-1)/$L11))*($T11*(1-$F11)+$S11*(1-$G11))*((1+Inputs!$D$7)^BQ$2))),((Inputs!$D$8^((1-_xlfn.WEIBULL.DIST(BQ$2,$M11,$L11,FALSE))/_xlfn.WEIBULL.DIST(BQ$2,$M11,$L11,FALSE))*($T11*(1-$F11)+$S11*(1-$G11))*((1+Inputs!$D$7)^BQ$2)))))))) -> 0.010576448 | BR11: =MAX(AB11,($E11*IF(BR$2>Inputs!$D$5,0,IF(BR$2>VLOOKUP($H11,Lists!$P$3:$Q$7,2),IF($N11=Lists!$K$3,IF($L11<1,(($U11/$L11)*((1+Inputs!$D$7)^BR$2)),((INT(BR$2/$L11)-INT((BR$2-1)/$L11))*$U11*((1+Inputs!$D$7)^BR$2))),(Inputs!$D$8^((1-_xlfn.WEIBULL.DIST(BR$2,$M11,$L11,FALSE))/_xlfn.WEIBULL.DIST(BR$2,$M11,$L11,FALSE))*$U11*((1+Inputs!$D$7)^BR$2))),IF($N11=Lists!$K$3,IF($L11<1,((($T11*(1-$F11)+$S11*(1-$G11))/$L11)*((1+Inputs!$D$7)^BR$2)),((INT(BR$2/$L11)-INT((BR$2-1)/$L11))*($T11*(1-$F11)+$S11*(1-$G11))*((1+Inputs!$D$7)^BR$2))),((Inputs!$D$8^((1-_xlfn.WEIBULL.DIST(BR$2,$M11,$L11,FALSE))/_xlfn.WEIBULL.DIST(BR$2,$M11,$L11,FALSE))*($T11*(1-$F11)+$S11*(1-$G11))*((1+Inputs!$D$7)^BR$2)))))))) -> 0.043132582 | BS11: =MAX(AC11,($E11*IF(BS$2>Inputs!$D$5,0,IF(BS$2>VLOOKUP($H11,Lists!$P$3:$Q$7,2),IF($N11=Lists!$K$3,IF($L11<1,(($U11/$L11)*((1+Inputs!$D$7)^BS$2)),((INT(BS$2/$L11)-INT((BS$2-1)/$L11))*$U11*((1+Inputs!$D$7)^BS$2))),(Inputs!$D$8^((1-_xlfn.WEIBULL.DIST(BS$2,$M11,$L11,FALSE))/_xlfn.WEIBULL.DIST(BS$2,$M11,$L11,FALSE))*$U11*((1+Inputs!$D$7)^BS$2))),IF($N11=Lists!$K$3,IF($L11<1,((($T11*(1-$F11)+$S11*(1-$G11))/$L11)*((1+Inputs!$D$7)^BS$2)),((INT(BS$2/$L11)-INT((BS$2-1)/$L11))*($T11*(1-$F11)+$S11*(1-$G11))*((1+Inputs!$D$7)^BS$2))),((Inputs!$D$8^((1-_xlfn.WEIBULL.DIST(BS$2,$M11,$L11,FALSE))/_xlfn.WEIBULL.DIST(BS$2,$M11,$L11,FALSE))*($T11*(1-$F11)+$S11*(1-$G11))*((1+Inputs!$D$7)^BS$2)))))))) -> 0.098868978 | BT11: =MAX(AD11,($E11*IF(BT$2>Inputs!$D$5,0,IF(BT$2>VLOOKUP($H11,Lists!$P$3:$Q$7,2),IF($N11=Lists!$K$3,IF($L11<1,(($U11/$L11)*((1+Inputs!$D$7)^BT$2)),((INT(BT$2/$L11)-INT((BT$2-1)/$L11))*$U11*((1+Inputs!$D$7)^BT$2))),(Inputs!$D$8^((1-_xlfn.WEIBULL.DIST(BT$2,$M11,$L11,FALSE))/_xlfn.WEIBULL.DIST(BT$2,$M11,$L11,FALSE))*$U11*((1+Inputs!$D$7)^BT$2))),IF($N11=Lists!$K$3,IF($L11<1,((($T11*(1-$F11)+$S11*(1-$G11))/$L11)*((1+Inputs!$D$7)^BT$2)),((INT(BT$2/$L11)-INT((BT$2-1)/$L11))*($T11*(1-$F11)+$S11*(1-$G11))*((1+Inputs!$D$7)^BT$2))),((Inputs!$D$8^((1-_xlfn.WEIBULL.DIST(BT$2,$M11,$L11,FALSE))/_xlfn.WEIBULL.DIST(BT$2,$M11,$L11,FALSE))*($T11*(1-$F11)+$S11*(1-$G11))*((1+Inputs!$D$7)^BT$2)))))))) -> 0.17885837 | BU11: =MAX(AE11,($E11*IF(BU$2>Inputs!$D$5,0,IF(BU$2>VLOOKUP($H11,Lists!$P$3:$Q$7,2),IF($N11=Lists!$K$3,IF($L11<1,(($U11/$L11)*((1+Inputs!$D$7)^BU$2)),((INT(BU$2/$L11)-INT((BU$2-1)/$L11))*$U11*((1+Inputs!$D$7)^BU$2))),(Inputs!$D$8^((1-_xlfn.WEIBULL.DIST(BU$2,$M11,$L11,FALSE))/_xlfn.WEIBULL.DIST(BU$2,$M11,$L11,FALSE))*$U11*((1+Inputs!$D$7)^BU$2))),IF($N11=Lists!$K$3,IF($L11<1,((($T11*(1-$F11)+$S11*(1-$G11))/$L11)*((1+Inputs!$D$7)^BU$2)),((INT(BU$2/$L11)-INT((BU$2-1)/$L11))*($T11*(1-$F11)+$S11*(1-$G11))*((1+Inputs!$D$7)^BU$2))),((Inputs!$D$8^((1-_xlfn.WEIBULL.DIST(BU$2,$M11,$L11,FALSE))/_xlfn.WEIBULL.DIST(BU$2,$M11,$L11,FALSE))*($T11*(1-$F11)+$S11*(1-$G11))*((1+Inputs!$D$7)^BU$2)))))))) -> 0.28394485 | BV11: =MAX(AF11,($E11*IF(BV$2>Inputs!$D$5,0,IF(BV$2>VLOOKUP($H11,Lists!$P$3:$Q$7,2),IF($N11=Lists!$K$3,IF($L11<1,(($U11/$L11)*((1+Inputs!$D$7)^BV$2)),((INT(BV$2/$L11)-INT((BV$2-1)/$L11))*$U11*((1+Inputs!$D$7)^BV$2))),(Inputs!$D$8^((1-_xlfn.WEIBULL.DIST(BV$2,$M11,$L11,FALSE))/_xlfn.WEIBULL.DIST(BV$2,$M11,$L11,FALSE))*$U11*((1+Inputs!$D$7)^BV$2))),IF($N11=Lists!$K$3,IF($L11<1,((($T11*(1-$F11)+$S11*(1-$G11))/$L11)*((1+Inputs!$D$7)^BV$2)),((INT(BV$2/$L11)-INT((BV$2-1)/$L11))*($T11*(1-$F11)+$S11*(1-$G11))*((1+Inputs!$D$7)^BV$2))),((Inputs!$D$8^((1-_xlfn.WEIBULL.DIST(BV$2,$M11,$L11,FALSE))/_xlfn.WEIBULL.DIST(BV$2,$M11,$L11,FALSE))*($T11*(1-$F11)+$S11*(1-$G11))*((1+Inputs!$D$7)^BV$2)))))))) -> 0.4146363 | BW11: =MAX(AG11,($E11*IF(BW$2>Inputs!$D$5,0,IF(BW$2>VLOOKUP($H11,Lists!$P$3:$Q$7,2),IF($N11=Lists!$K$3,IF($L11<1,(($U11/$L11)*((1+Inputs!$D$7)^BW$2)),((INT(BW$2/$L11)-INT((BW$2-1)/$L11))*$U11*((1+Inputs!$D$7)^BW$2))),(Inputs!$D$8^((1-_xlfn.WEIBULL.DIST(BW$2,$M11,$L11,FALSE))/_xlfn.WEIBULL.DIST(BW$2,$M11,$L11,FALSE))*$U11*((1+Inputs!$D$7)^BW$2))),IF($N11=Lists!$K$3,IF($L11<1,((($T11*(1-$F11)+$S11*(1-$G11))/$L11)*((1+Inputs!$D$7)^BW$2)),((INT(BW$2/$L11)-INT((BW$2-1)/$L11))*($T11*(1-$F11)+$S11*(1-$G11))*((1+Inputs!$D$7)^BW$2))),((Inputs!$D$8^((1-_xlfn.WEIBULL.DIST(BW$2,$M11,$L11,FALSE))/_xlfn.WEIBULL.DIST(BW$2,$M11,$L11,FALSE))*($T11*(1-$F11)+$S11*(1-$G11))*((1+Inputs!$D$7)^BW$2)))))))) -> 0.57099346 | BX11: =MAX(AH11,($E11*IF(BX$2>Inputs!$D$5,0,IF(BX$2>VLOOKUP($H11,Lists!$P$3:$Q$7,2),IF($N11=Lists!$K$3,IF($L11<1,(($U11/$L11)*((1+Inputs!$D$7)^BX$2)),((INT(BX$2/$L11)-INT((BX$2-1)/$L11))*$U11*((1+Inputs!$D$7)^BX$2))),(Inputs!$D$8^((1-_xlfn.WEIBULL.DIST(BX$2,$M11,$L11,FALSE))/_xlfn.WEIBULL.DIST(BX$2,$M11,$L11,FALSE))*$U11*((1+Inputs!$D$7)^BX$2))),IF($N11=Lists!$K$3,IF($L11<1,((($T11*(1-$F11)+$S11*(1-$G11))/$L11)*((1+Inputs!$D$7)^BX$2)),((INT(BX$2/$L11)-INT((BX$2-1)/$L11))*($T11*(1-$F11)+$S11*(1-$G11))*((1+Inputs!$D$7)^BX$2))),((Inputs!$D$8^((1-_xlfn.WEIBULL.DIST(BX$2,$M11,$L11,FALSE))/_xlfn.WEIBULL.DIST(BX$2,$M11,$L11,FALSE))*($T11*(1-$F11)+$S11*(1-$G11))*((1+Inputs!$D$7)^BX$2)))))))) -> 0.75251969 | ... DD11: =MAX(BN11,($E11*IF(DD$2>Inputs!$D$5,0,IF(DD$2>VLOOKUP($H11,Lists!$P$3:$Q$7,2),IF($N11=Lists!$K$3,IF($L11<1,(($U11/$L11)*((1+Inputs!$D$7)^DD$2)),((INT(DD$2/$L11)-INT((DD$2-1)/$L11))*$U11*((1+Inputs!$D$7)^DD$2))),(Inputs!$D$8^((1-_xlfn.WEIBULL.DIST(DD$2,$M11,$L11,FALSE))/_xlfn.WEIBULL.DIST(DD$2,$M11,$L11,FALSE))*$U11*((1+Inputs!$D$7)^DD$2))),IF($N11=Lists!$K$3,IF($L11<1,((($T11*(1-$F11)+$S11*(1-$G11))/$L11)*((1+Inputs!$D$7)^DD$2)),((INT(DD$2/$L11)-INT((DD$2-1)/$L11))*($T11*(1-$F11)+$S11*(1-$G11))*((1+Inputs!$D$7)^DD$2))),((Inputs!$D$8^((1-_xlfn.WEIBULL.DIST(DD$2,$M11,$L11,FALSE))/_xlfn.WEIBULL.DIST(DD$2,$M11,$L11,FALSE))*($T11*(1-$F11)+$S11*(1-$G11))*((1+Inputs!$D$7)^DD$2)))))))) -> 0
A12: Replace inverter AC fuse(s) | B12: Corrective | C12: Repair | D12: AC wiring | E12: =IF(Inputs!D30=Lists!M5,0,1) -> 1 | F12: 1 | G12: 1 | H12: EPC | J12: Journeyman electrician | K12: =VLOOKUP(J12,'Labor Rates'!$A$1:$F$16,2) -> 19.903846 | L12: 25 | M12: 1 | N12: Weibull | O12: =Inputs!$D$34*3 -> 30 | P12: 0.15 | Q12: =O12*P12/L12 -> 0.18 | R12: 10 | S12: =P12*O12*K12 -> 89.567308 | T12: =R12*O12 -> 300 | U12: =E12*(T12+S12) -> 389.56731 | X12: =AVERAGE(AA12:AT12) -> 11.927038 | Y12: =NPV(Inputs!$D$6,AA12:BN12) -> 136.54702 | Z12: =Y12/SUM($Y$3:$Y$136) -> 6.4402241e-05 | AA12: =$E12*IF(AA$2>Inputs!$D$5,0,IF(AA$2>VLOOKUP($H12,Lists!$P$3:$Q$7,2),IF($N12=Lists!$K$3,IF($L12<1,(($U12/$L12)*((1+Inputs!$D$7)^AA$2)),((INT(AA$2/$L12)-INT((AA$2-1)/$L12))*$U12*((1+Inputs!$D$7)^AA$2))),(_xlfn.WEIBULL.DIST(AA$2,$M12,$L12,FALSE)*$U12*((1+Inputs!$D$7)^AA$2))),IF($N12=Lists!$K$3,IF($L12<1,((($T12*(1-$F12)+$S12*(1-$G12))/$L12)*((1+Inputs!$D$7)^AA$2)),((INT(AA$2/$L12)-INT((AA$2-1)/$L12))*($T12*(1-$F12)+$S12*(1-$G12))*((1+Inputs!$D$7)^AA$2))),((_xlfn.WEIBULL.DIST(AA$2,$M12,$L12,FALSE)*($T12*(1-$F12)+$S12*(1-$G12))*((1+Inputs!$D$7)^AA$2)))))) -> 0 | AB12: =$E12*IF(AB$2>Inputs!$D$5,0,IF(AB$2>VLOOKUP($H12,Lists!$P$3:$Q$7,2),IF($N12=Lists!$K$3,IF($L12<1,(($U12/$L12)*((1+Inputs!$D$7)^AB$2)),((INT(AB$2/$L12)-INT((AB$2-1)/$L12))*$U12*((1+Inputs!$D$7)^AB$2))),(_xlfn.WEIBULL.DIST(AB$2,$M12,$L12,FALSE)*$U12*((1+Inputs!$D$7)^AB$2))),IF($N12=Lists!$K$3,IF($L12<1,((($T12*(1-$F12)+$S12*(1-$G12))/$L12)*((1+Inputs!$D$7)^AB$2)),((INT(AB$2/$L12)-INT((AB$2-1)/$L12))*($T12*(1-$F12)+$S12*(1-$G12))*((1+Inputs!$D$7)^AB$2))),((_xlfn.WEIBULL.DIST(AB$2,$M12,$L12,FALSE)*($T12*(1-$F12)+$S12*(1-$G12))*((1+Inputs!$D$7)^AB$2)))))) -> 14.965777 | AC12: =$E12*IF(AC$2>Inputs!$D$5,0,IF(AC$2>VLOOKUP($H12,Lists!$P$3:$Q$7,2),IF($N12=Lists!$K$3,IF($L12<1,(($U12/$L12)*((1+Inputs!$D$7)^AC$2)),((INT(AC$2/$L12)-INT((AC$2-1)/$L12))*$U12*((1+Inputs!$D$7)^AC$2))),(_xlfn.WEIBULL.DIST(AC$2,$M12,$L12,FALSE)*$U12*((1+Inputs!$D$7)^AC$2))),IF($N12=Lists!$K$3,IF($L12<1,((($T12*(1-$F12)+$S12*(1-$G12))/$L12)*((1+Inputs!$D$7)^AC$2)),((INT(AC$2/$L12)-INT((AC$2-1)/$L12))*($T12*(1-$F12)+$S12*(1-$G12))*((1+Inputs!$D$7)^AC$2))),((_xlfn.WEIBULL.DIST(AC$2,$M12,$L12,FALSE)*($T12*(1-$F12)+$S12*(1-$G12))*((1+Inputs!$D$7)^AC$2)))))) -> 14.66654 | AD12: =$E12*IF(AD$2>Inputs!$D$5,0,IF(AD$2>VLOOKUP($H12,Lists!$P$3:$Q$7,2),IF($N12=Lists!$K$3,IF($L12<1,(($U12/$L12)*((1+Inputs!$D$7)^AD$2)),((INT(AD$2/$L12)-INT((AD$2-1)/$L12))*$U12*((1+Inputs!$D$7)^AD$2))),(_xlfn.WEIBULL.DIST(AD$2,$M12,$L12,FALSE)*$U12*((1+Inputs!$D$7)^AD$2))),IF($N12=Lists!$K$3,IF($L12<1,((($T12*(1-$F12)+$S12*(1-$G12))/$L12)*((1+Inputs!$D$7)^AD$2)),((INT(AD$2/$L12)-INT((AD$2-1)/$L12))*($T12*(1-$F12)+$S12*(1-$G12))*((1+Inputs!$D$7)^AD$2))),((_xlfn.WEIBULL.DIST(AD$2,$M12,$L12,FALSE)*($T12*(1-$F12)+$S12*(1-$G12))*((1+Inputs!$D$7)^AD$2)))))) -> 14.373286 | AE12: =$E12*IF(AE$2>Inputs!$D$5,0,IF(AE$2>VLOOKUP($H12,Lists!$P$3:$Q$7,2),IF($N12=Lists!$K$3,IF($L12<1,(($U12/$L12)*((1+Inputs!$D$7)^AE$2)),((INT(AE$2/$L12)-INT((AE$2-1)/$L12))*$U12*((1+Inputs!$D$7)^AE$2))),(_xlfn.WEIBULL.DIST(AE$2,$M12,$L12,FALSE)*$U12*((1+Inputs!$D$7)^AE$2))),IF($N12=Lists!$K$3,IF($L12<1,((($T12*(1-$F12)+$S12*(1-$G12))/$L12)*((1+Inputs!$D$7)^AE$2)),((INT(AE$2/$L12)-INT((AE$2-1)/$L12))*($T12*(1-$F12)+$S12*(1-$G12))*((1+Inputs!$D$7)^AE$2))),((_xlfn.WEIBULL.DIST(AE$2,$M12,$L12,FALSE)*($T12*(1-$F12)+$S12*(1-$G12))*((1+Inputs!$D$7)^AE$2)))))) -> 14.085895 | AF12: =$E12*IF(AF$2>Inputs!$D$5,0,IF(AF$2>VLOOKUP($H12,Lists!$P$3:$Q$7,2),IF($N12=Lists!$K$3,IF($L12<1,(($U12/$L12)*((1+Inputs!$D$7)^AF$2)),((INT(AF$2/$L12)-INT((AF$2-1)/$L12))*$U12*((1+Inputs!$D$7)^AF$2))),(_xlfn.WEIBULL.DIST(AF$2,$M12,$L12,FALSE)*$U12*((1+Inputs!$D$7)^AF$2))),IF($N12=Lists!$K$3,IF($L12<1,((($T12*(1-$F12)+$S12*(1-$G12))/$L12)*((1+Inputs!$D$7)^AF$2)),((INT(AF$2/$L12)-INT((AF$2-1)/$L12))*($T12*(1-$F12)+$S12*(1-$G12))*((1+Inputs!$D$7)^AF$2))),((_xlfn.WEIBULL.DIST(AF$2,$M12,$L12,FALSE)*($T12*(1-$F12)+$S12*(1-$G12))*((1+Inputs!$D$7)^AF$2)))))) -> 13.804251 | AG12: =$E12*IF(AG$2>Inputs!$D$5,0,IF(AG$2>VLOOKUP($H12,Lists!$P$3:$Q$7,2),IF($N12=Lists!$K$3,IF($L12<1,(($U12/$L12)*((1+Inputs!$D$7)^AG$2)),((INT(AG$2/$L12)-INT((AG$2-1)/$L12))*$U12*((1+Inputs!$D$7)^AG$2))),(_xlfn.WEIBULL.DIST(AG$2,$M12,$L12,FALSE)*$U12*((1+Inputs!$D$7)^AG$2))),IF($N12=Lists!$K$3,IF($L12<1,((($T12*(1-$F12)+$S12*(1-$G12))/$L12)*((1+Inputs!$D$7)^AG$2)),((INT(AG$2/$L12)-INT((AG$2-1)/$L12))*($T12*(1-$F12)+$S12*(1-$G12))*((1+Inputs!$D$7)^AG$2))),((_xlfn.WEIBULL.DIST(AG$2,$M12,$L12,FALSE)*($T12*(1-$F12)+$S12*(1-$G12))*((1+Inputs!$D$7)^AG$2)))))) -> 13.528238 | AH12: =$E12*IF(AH$2>Inputs!$D$5,0,IF(AH$2>VLOOKUP($H12,Lists!$P$3:$Q$7,2),IF($N12=Lists!$K$3,IF($L12<1,(($U12/$L12)*((1+Inputs!$D$7)^AH$2)),((INT(AH$2/$L12)-INT((AH$2-1)/$L12))*$U12*((1+Inputs!$D$7)^AH$2))),(_xlfn.WEIBULL.DIST(AH$2,$M12,$L12,FALSE)*$U12*((1+Inputs!$D$7)^AH$2))),IF($N12=Lists!$K$3,IF($L12<1,((($T12*(1-$F12)+$S12*(1-$G12))/$L12)*((1+Inputs!$D$7)^AH$2)),((INT(AH$2/$L12)-INT((AH$2-1)/$L12))*($T12*(1-$F12)+$S12*(1-$G12))*((1+Inputs!$D$7)^AH$2))),((_xlfn.WEIBULL.DIST(AH$2,$M12,$L12,FALSE)*($T12*(1-$F12)+$S12*(1-$G12))*((1+Inputs!$D$7)^AH$2)))))) -> 13.257744 | ... BN12: =$E12*IF(BN$2>Inputs!$D$5,0,IF(BN$2>VLOOKUP($H12,Lists!$P$3:$Q$7,2),IF($N12=Lists!$K$3,IF($L12<1,(($U12/$L12)*((1+Inputs!$D$7)^BN$2)),((INT(BN$2/$L12)-INT((BN$2-1)/$L12))*$U12*((1+Inputs!$D$7)^BN$2))),(_xlfn.WEIBULL.DIST(BN$2,$M12,$L12,FALSE)*$U12*((1+Inputs!$D$7)^BN$2))),IF($N12=Lists!$K$3,IF($L12<1,((($T12*(1-$F12)+$S12*(1-$G12))/$L12)*((1+Inputs!$D$7)^BN$2)),((INT(BN$2/$L12)-INT((BN$2-1)/$L12))*($T12*(1-$F12)+$S12*(1-$G12))*((1+Inputs!$D$7)^BN$2))),((_xlfn.WEIBULL.DIST(BN$2,$M12,$L12,FALSE)*($T12*(1-$F12)+$S12*(1-$G12))*((1+Inputs!$D$7)^BN$2)))))) -> 0 | BO12: =NPV(Inputs!$D$6,BQ12:DD12) -> 276.89682 | BP12: =BO12/SUM($Y$3:$Y$136) -> 0.00013059806 | BQ12: =MAX(AA12,($E12*IF(BQ$2>Inputs!$D$5,0,IF(BQ$2>VLOOKUP($H12,Lists!$P$3:$Q$7,2),IF($N12=Lists!$K$3,IF($L12<1,(($U12/$L12)*((1+Inputs!$D$7)^BQ$2)),((INT(BQ$2/$L12)-INT((BQ$2-1)/$L12))*$U12*((1+Inputs!$D$7)^BQ$2))),(Inputs!$D$8^((1-_xlfn.WEIBULL.DIST(BQ$2,$M12,$L12,FALSE))/_xlfn.WEIBULL.DIST(BQ$2,$M12,$L12,FALSE))*$U12*((1+Inputs!$D$7)^BQ$2))),IF($N12=Lists!$K$3,IF($L12<1,((($T12*(1-$F12)+$S12*(1-$G12))/$L12)*((1+Inputs!$D$7)^BQ$2)),((INT(BQ$2/$L12)-INT((BQ$2-1)/$L12))*($T12*(1-$F12)+$S12*(1-$G12))*((1+Inputs!$D$7)^BQ$2))),((Inputs!$D$8^((1-_xlfn.WEIBULL.DIST(BQ$2,$M12,$L12,FALSE))/_xlfn.WEIBULL.DIST(BQ$2,$M12,$L12,FALSE))*($T12*(1-$F12)+$S12*(1-$G12))*((1+Inputs!$D$7)^BQ$2)))))))) -> 0 | BR12: =MAX(AB12,($E12*IF(BR$2>Inputs!$D$5,0,IF(BR$2>VLOOKUP($H12,Lists!$P$3:$Q$7,2),IF($N12=Lists!$K$3,IF($L12<1,(($U12/$L12)*((1+Inputs!$D$7)^BR$2)),((INT(BR$2/$L12)-INT((BR$2-1)/$L12))*$U12*((1+Inputs!$D$7)^BR$2))),(Inputs!$D$8^((1-_xlfn.WEIBULL.DIST(BR$2,$M12,$L12,FALSE))/_xlfn.WEIBULL.DIST(BR$2,$M12,$L12,FALSE))*$U12*((1+Inputs!$D$7)^BR$2))),IF($N12=Lists!$K$3,IF($L12<1,((($T12*(1-$F12)+$S12*(1-$G12))/$L12)*((1+Inputs!$D$7)^BR$2)),((INT(BR$2/$L12)-INT((BR$2-1)/$L12))*($T12*(1-$F12)+$S12*(1-$G12))*((1+Inputs!$D$7)^BR$2))),((Inputs!$D$8^((1-_xlfn.WEIBULL.DIST(BR$2,$M12,$L12,FALSE))/_xlfn.WEIBULL.DIST(BR$2,$M12,$L12,FALSE))*($T12*(1-$F12)+$S12*(1-$G12))*((1+Inputs!$D$7)^BR$2)))))))) -> 46.056461 | BS12: =MAX(AC12,($E12*IF(BS$2>Inputs!$D$5,0,IF(BS$2>VLOOKUP($H12,Lists!$P$3:$Q$7,2),IF($N12=Lists!$K$3,IF($L12<1,(($U12/$L12)*((1+Inputs!$D$7)^BS$2)),((INT(BS$2/$L12)-INT((BS$2-1)/$L12))*$U12*((1+Inputs!$D$7)^BS$2))),(Inputs!$D$8^((1-_xlfn.WEIBULL.DIST(BS$2,$M12,$L12,FALSE))/_xlfn.WEIBULL.DIST(BS$2,$M12,$L12,FALSE))*$U12*((1+Inputs!$D$7)^BS$2))),IF($N12=Lists!$K$3,IF($L12<1,((($T12*(1-$F12)+$S12*(1-$G12))/$L12)*((1+Inputs!$D$7)^BS$2)),((INT(BS$2/$L12)-INT((BS$2-1)/$L12))*($T12*(1-$F12)+$S12*(1-$G12))*((1+Inputs!$D$7)^BS$2))),((Inputs!$D$8^((1-_xlfn.WEIBULL.DIST(BS$2,$M12,$L12,FALSE))/_xlfn.WEIBULL.DIST(BS$2,$M12,$L12,FALSE))*($T12*(1-$F12)+$S12*(1-$G12))*((1+Inputs!$D$7)^BS$2)))))))) -> 42.841772 | BT12: =MAX(AD12,($E12*IF(BT$2>Inputs!$D$5,0,IF(BT$2>VLOOKUP($H12,Lists!$P$3:$Q$7,2),IF($N12=Lists!$K$3,IF($L12<1,(($U12/$L12)*((1+Inputs!$D$7)^BT$2)),((INT(BT$2/$L12)-INT((BT$2-1)/$L12))*$U12*((1+Inputs!$D$7)^BT$2))),(Inputs!$D$8^((1-_xlfn.WEIBULL.DIST(BT$2,$M12,$L12,FALSE))/_xlfn.WEIBULL.DIST(BT$2,$M12,$L12,FALSE))*$U12*((1+Inputs!$D$7)^BT$2))),IF($N12=Lists!$K$3,IF($L12<1,((($T12*(1-$F12)+$S12*(1-$G12))/$L12)*((1+Inputs!$D$7)^BT$2)),((INT(BT$2/$L12)-INT((BT$2-1)/$L12))*($T12*(1-$F12)+$S12*(1-$G12))*((1+Inputs!$D$7)^BT$2))),((Inputs!$D$8^((1-_xlfn.WEIBULL.DIST(BT$2,$M12,$L12,FALSE))/_xlfn.WEIBULL.DIST(BT$2,$M12,$L12,FALSE))*($T12*(1-$F12)+$S12*(1-$G12))*((1+Inputs!$D$7)^BT$2)))))))) -> 39.701865 | BU12: =MAX(AE12,($E12*IF(BU$2>Inputs!$D$5,0,IF(BU$2>VLOOKUP($H12,Lists!$P$3:$Q$7,2),IF($N12=Lists!$K$3,IF($L12<1,(($U12/$L12)*((1+Inputs!$D$7)^BU$2)),((INT(BU$2/$L12)-INT((BU$2-1)/$L12))*$U12*((1+Inputs!$D$7)^BU$2))),(Inputs!$D$8^((1-_xlfn.WEIBULL.DIST(BU$2,$M12,$L12,FALSE))/_xlfn.WEIBULL.DIST(BU$2,$M12,$L12,FALSE))*$U12*((1+Inputs!$D$7)^BU$2))),IF($N12=Lists!$K$3,IF($L12<1,((($T12*(1-$F12)+$S12*(1-$G12))/$L12)*((1+Inputs!$D$7)^BU$2)),((INT(BU$2/$L12)-INT((BU$2-1)/$L12))*($T12*(1-$F12)+$S12*(1-$G12))*((1+Inputs!$D$7)^BU$2))),((Inputs!$D$8^((1-_xlfn.WEIBULL.DIST(BU$2,$M12,$L12,FALSE))/_xlfn.WEIBULL.DIST(BU$2,$M12,$L12,FALSE))*($T12*(1-$F12)+$S12*(1-$G12))*((1+Inputs!$D$7)^BU$2)))))))) -> 36.648343 | BV12: =MAX(AF12,($E12*IF(BV$2>Inputs!$D$5,0,IF(BV$2>VLOOKUP($H12,Lists!$P$3:$Q$7,2),IF($N12=Lists!$K$3,IF($L12<1,(($U12/$L12)*((1+Inputs!$D$7)^BV$2)),((INT(BV$2/$L12)-INT((BV$2-1)/$L12))*$U12*((1+Inputs!$D$7)^BV$2))),(Inputs!$D$8^((1-_xlfn.WEIBULL.DIST(BV$2,$M12,$L12,FALSE))/_xlfn.WEIBULL.DIST(BV$2,$M12,$L12,FALSE))*$U12*((1+Inputs!$D$7)^BV$2))),IF($N12=Lists!$K$3,IF($L12<1,((($T12*(1-$F12)+$S12*(1-$G12))/$L12)*((1+Inputs!$D$7)^BV$2)),((INT(BV$2/$L12)-INT((BV$2-1)/$L12))*($T12*(1-$F12)+$S12*(1-$G12))*((1+Inputs!$D$7)^BV$2))),((Inputs!$D$8^((1-_xlfn.WEIBULL.DIST(BV$2,$M12,$L12,FALSE))/_xlfn.WEIBULL.DIST(BV$2,$M12,$L12,FALSE))*($T12*(1-$F12)+$S12*(1-$G12))*((1+Inputs!$D$7)^BV$2)))))))) -> 33.692122 | BW12: =MAX(AG12,($E12*IF(BW$2>Inputs!$D$5,0,IF(BW$2>VLOOKUP($H12,Lists!$P$3:$Q$7,2),IF($N12=Lists!$K$3,IF($L12<1,(($U12/$L12)*((1+Inputs!$D$7)^BW$2)),((INT(BW$2/$L12)-INT((BW$2-1)/$L12))*$U12*((1+Inputs!$D$7)^BW$2))),(Inputs!$D$8^((1-_xlfn.WEIBULL.DIST(BW$2,$M12,$L12,FALSE))/_xlfn.WEIBULL.DIST(BW$2,$M12,$L12,FALSE))*$U12*((1+Inputs!$D$7)^BW$2))),IF($N12=Lists!$K$3,IF($L12<1,((($T12*(1-$F12)+$S12*(1-$G12))/$L12)*((1+Inputs!$D$7)^BW$2)),((INT(BW$2/$L12)-INT((BW$2-1)/$L12))*($T12*(1-$F12)+$S12*(1-$G12))*((1+Inputs!$D$7)^BW$2))),((Inputs!$D$8^((1-_xlfn.WEIBULL.DIST(BW$2,$M12,$L12,FALSE))/_xlfn.WEIBULL.DIST(BW$2,$M12,$L12,FALSE))*($T12*(1-$F12)+$S12*(1-$G12))*((1+Inputs!$D$7)^BW$2)))))))) -> 30.843294 | BX12: =MAX(AH12,($E12*IF(BX$2>Inputs!$D$5,0,IF(BX$2>VLOOKUP($H12,Lists!$P$3:$Q$7,2),IF($N12=Lists!$K$3,IF($L12<1,(($U12/$L12)*((1+Inputs!$D$7)^BX$2)),((INT(BX$2/$L12)-INT((BX$2-1)/$L12))*$U12*((1+Inputs!$D$7)^BX$2))),(Inputs!$D$8^((1-_xlfn.WEIBULL.DIST(BX$2,$M12,$L12,FALSE))/_xlfn.WEIBULL.DIST(BX$2,$M12,$L12,FALSE))*$U12*((1+Inputs!$D$7)^BX$2))),IF($N12=Lists!$K$3,IF($L12<1,((($T12*(1-$F12)+$S12*(1-$G12))/$L12)*((1+Inputs!$D$7)^BX$2)),((INT(BX$2/$L12)-INT((BX$2-1)/$L12))*($T12*(1-$F12)+$S12*(1-$G12))*((1+Inputs!$D$7)^BX$2))),((Inputs!$D$8^((1-_xlfn.WEIBULL.DIST(BX$2,$M12,$L12,FALSE))/_xlfn.WEIBULL.DIST(BX$2,$M12,$L12,FALSE))*($T12*(1-$F12)+$S12*(1-$G12))*((1+Inputs!$D$7)^BX$2)))))))) -> 28.111003 | ... DD12: =MAX(BN12,($E12*IF(DD$2>Inputs!$D$5,0,IF(DD$2>VLOOKUP($H12,Lists!$P$3:$Q$7,2),IF($N12=Lists!$K$3,IF($L12<1,(($U12/$L12)*((1+Inputs!$D$7)^DD$2)),((INT(DD$2/$L12)-INT((DD$2-1)/$L12))*$U12*((1+Inputs!$D$7)^DD$2))),(Inputs!$D$8^((1-_xlfn.WEIBULL.DIST(DD$2,$M12,$L12,FALSE))/_xlfn.WEIBULL.DIST(DD$2,$M12,$L12,FALSE))*$U12*((1+Inputs!$D$7)^DD$2))),IF($N12=Lists!$K$3,IF($L12<1,((($T12*(1-$F12)+$S12*(1-$G12))/$L12)*((1+Inputs!$D$7)^DD$2)),((INT(DD$2/$L12)-INT((DD$2-1)/$L12))*($T12*(1-$F12)+$S12*(1-$G12))*((1+Inputs!$D$7)^DD$2))),((Inputs!$D$8^((1-_xlfn.WEIBULL.DIST(DD$2,$M12,$L12,FALSE))/_xlfn.WEIBULL.DIST(DD$2,$M12,$L12,FALSE))*($T12*(1-$F12)+$S12*(1-$G12))*((1+Inputs!$D$7)^DD$2)))))))) -> 0
A13: Locate line-to-line fault | B13: Corrective | C13: Repair | D13: AC Wiring | E13: 1 | F13: 1 | G13: 1 | H13: EPC | J13: Master electrician | K13: =VLOOKUP(J13,'Labor Rates'!$A$1:$F$16,2) -> 32.012019 | L13: 25 | M13: 3 | N13: Weibull | O13: 1 | P13: 1 | Q13: =O13*P13/L13 -> 0.04 | R13: 0 | S13: =P13*O13*K13 -> 32.012019 | T13: =R13*O13 -> 0 | U13: =E13*(T13+S13) -> 32.012019 | X13: =AVERAGE(AA13:AT13) -> 0.91118731 | Y13: =NPV(Inputs!$D$6,AA13:BN13) -> 9.2860771 | Z13: =Y13/SUM($Y$3:$Y$136) -> 4.3797673e-06 | AA13: =$E13*IF(AA$2>Inputs!$D$5,0,IF(AA$2>VLOOKUP($H13,Lists!$P$3:$Q$7,2),IF($N13=Lists!$K$3,IF($L13<1,(($U13/$L13)*((1+Inputs!$D$7)^AA$2)),((INT(AA$2/$L13)-INT((AA$2-1)/$L13))*$U13*((1+Inputs!$D$7)^AA$2))),(_xlfn.WEIBULL.DIST(AA$2,$M13,$L13,FALSE)*$U13*((1+Inputs!$D$7)^AA$2))),IF($N13=Lists!$K$3,IF($L13<1,((($T13*(1-$F13)+$S13*(1-$G13))/$L13)*((1+Inputs!$D$7)^AA$2)),((INT(AA$2/$L13)-INT((AA$2-1)/$L13))*($T13*(1-$F13)+$S13*(1-$G13))*((1+Inputs!$D$7)^AA$2))),((_xlfn.WEIBULL.DIST(AA$2,$M13,$L13,FALSE)*($T13*(1-$F13)+$S13*(1-$G13))*((1+Inputs!$D$7)^AA$2)))))) -> 0 | AB13: =$E13*IF(AB$2>Inputs!$D$5,0,IF(AB$2>VLOOKUP($H13,Lists!$P$3:$Q$7,2),IF($N13=Lists!$K$3,IF($L13<1,(($U13/$L13)*((1+Inputs!$D$7)^AB$2)),((INT(AB$2/$L13)-INT((AB$2-1)/$L13))*$U13*((1+Inputs!$D$7)^AB$2))),(_xlfn.WEIBULL.DIST(AB$2,$M13,$L13,FALSE)*$U13*((1+Inputs!$D$7)^AB$2))),IF($N13=Lists!$K$3,IF($L13<1,((($T13*(1-$F13)+$S13*(1-$G13))/$L13)*((1+Inputs!$D$7)^AB$2)),((INT(AB$2/$L13)-INT((AB$2-1)/$L13))*($T13*(1-$F13)+$S13*(1-$G13))*((1+Inputs!$D$7)^AB$2))),((_xlfn.WEIBULL.DIST(AB$2,$M13,$L13,FALSE)*($T13*(1-$F13)+$S13*(1-$G13))*((1+Inputs!$D$7)^AB$2)))))) -> 0.025565381 | AC13: =$E13*IF(AC$2>Inputs!$D$5,0,IF(AC$2>VLOOKUP($H13,Lists!$P$3:$Q$7,2),IF($N13=Lists!$K$3,IF($L13<1,(($U13/$L13)*((1+Inputs!$D$7)^AC$2)),((INT(AC$2/$L13)-INT((AC$2-1)/$L13))*$U13*((1+Inputs!$D$7)^AC$2))),(_xlfn.WEIBULL.DIST(AC$2,$M13,$L13,FALSE)*$U13*((1+Inputs!$D$7)^AC$2))),IF($N13=Lists!$K$3,IF($L13<1,((($T13*(1-$F13)+$S13*(1-$G13))/$L13)*((1+Inputs!$D$7)^AC$2)),((INT(AC$2/$L13)-INT((AC$2-1)/$L13))*($T13*(1-$F13)+$S13*(1-$G13))*((1+Inputs!$D$7)^AC$2))),((_xlfn.WEIBULL.DIST(AC$2,$M13,$L13,FALSE)*($T13*(1-$F13)+$S13*(1-$G13))*((1+Inputs!$D$7)^AC$2)))))) -> 0.058601248 | AD13: =$E13*IF(AD$2>Inputs!$D$5,0,IF(AD$2>VLOOKUP($H13,Lists!$P$3:$Q$7,2),IF($N13=Lists!$K$3,IF($L13<1,(($U13/$L13)*((1+Inputs!$D$7)^AD$2)),((INT(AD$2/$L13)-INT((AD$2-1)/$L13))*$U13*((1+Inputs!$D$7)^AD$2))),(_xlfn.WEIBULL.DIST(AD$2,$M13,$L13,FALSE)*$U13*((1+Inputs!$D$7)^AD$2))),IF($N13=Lists!$K$3,IF($L13<1,((($T13*(1-$F13)+$S13*(1-$G13))/$L13)*((1+Inputs!$D$7)^AD$2)),((INT(AD$2/$L13)-INT((AD$2-1)/$L13))*($T13*(1-$F13)+$S13*(1-$G13))*((1+Inputs!$D$7)^AD$2))),((_xlfn.WEIBULL.DIST(AD$2,$M13,$L13,FALSE)*($T13*(1-$F13)+$S13*(1-$G13))*((1+Inputs!$D$7)^AD$2)))))) -> 0.10601226 | AE13: =$E13*IF(AE$2>Inputs!$D$5,0,IF(AE$2>VLOOKUP($H13,Lists!$P$3:$Q$7,2),IF($N13=Lists!$K$3,IF($L13<1,(($U13/$L13)*((1+Inputs!$D$7)^AE$2)),((INT(AE$2/$L13)-INT((AE$2-1)/$L13))*$U13*((1+Inputs!$D$7)^AE$2))),(_xlfn.WEIBULL.DIST(AE$2,$M13,$L13,FALSE)*$U13*((1+Inputs!$D$7)^AE$2))),IF($N13=Lists!$K$3,IF($L13<1,((($T13*(1-$F13)+$S13*(1-$G13))/$L13)*((1+Inputs!$D$7)^AE$2)),((INT(AE$2/$L13)-INT((AE$2-1)/$L13))*($T13*(1-$F13)+$S13*(1-$G13))*((1+Inputs!$D$7)^AE$2))),((_xlfn.WEIBULL.DIST(AE$2,$M13,$L13,FALSE)*($T13*(1-$F13)+$S13*(1-$G13))*((1+Inputs!$D$7)^AE$2)))))) -> 0.16829872 | AF13: =$E13*IF(AF$2>Inputs!$D$5,0,IF(AF$2>VLOOKUP($H13,Lists!$P$3:$Q$7,2),IF($N13=Lists!$K$3,IF($L13<1,(($U13/$L13)*((1+Inputs!$D$7)^AF$2)),((INT(AF$2/$L13)-INT((AF$2-1)/$L13))*$U13*((1+Inputs!$D$7)^AF$2))),(_xlfn.WEIBULL.DIST(AF$2,$M13,$L13,FALSE)*$U13*((1+Inputs!$D$7)^AF$2))),IF($N13=Lists!$K$3,IF($L13<1,((($T13*(1-$F13)+$S13*(1-$G13))/$L13)*((1+Inputs!$D$7)^AF$2)),((INT(AF$2/$L13)-INT((AF$2-1)/$L13))*($T13*(1-$F13)+$S13*(1-$G13))*((1+Inputs!$D$7)^AF$2))),((_xlfn.WEIBULL.DIST(AF$2,$M13,$L13,FALSE)*($T13*(1-$F13)+$S13*(1-$G13))*((1+Inputs!$D$7)^AF$2)))))) -> 0.24576167 | AG13: =$E13*IF(AG$2>Inputs!$D$5,0,IF(AG$2>VLOOKUP($H13,Lists!$P$3:$Q$7,2),IF($N13=Lists!$K$3,IF($L13<1,(($U13/$L13)*((1+Inputs!$D$7)^AG$2)),((INT(AG$2/$L13)-INT((AG$2-1)/$L13))*$U13*((1+Inputs!$D$7)^AG$2))),(_xlfn.WEIBULL.DIST(AG$2,$M13,$L13,FALSE)*$U13*((1+Inputs!$D$7)^AG$2))),IF($N13=Lists!$K$3,IF($L13<1,((($T13*(1-$F13)+$S13*(1-$G13))/$L13)*((1+Inputs!$D$7)^AG$2)),((INT(AG$2/$L13)-INT((AG$2-1)/$L13))*($T13*(1-$F13)+$S13*(1-$G13))*((1+Inputs!$D$7)^AG$2))),((_xlfn.WEIBULL.DIST(AG$2,$M13,$L13,FALSE)*($T13*(1-$F13)+$S13*(1-$G13))*((1+Inputs!$D$7)^AG$2)))))) -> 0.33843709 | AH13: =$E13*IF(AH$2>Inputs!$D$5,0,IF(AH$2>VLOOKUP($H13,Lists!$P$3:$Q$7,2),IF($N13=Lists!$K$3,IF($L13<1,(($U13/$L13)*((1+Inputs!$D$7)^AH$2)),((INT(AH$2/$L13)-INT((AH$2-1)/$L13))*$U13*((1+Inputs!$D$7)^AH$2))),(_xlfn.WEIBULL.DIST(AH$2,$M13,$L13,FALSE)*$U13*((1+Inputs!$D$7)^AH$2))),IF($N13=Lists!$K$3,IF($L13<1,((($T13*(1-$F13)+$S13*(1-$G13))/$L13)*((1+Inputs!$D$7)^AH$2)),((INT(AH$2/$L13)-INT((AH$2-1)/$L13))*($T13*(1-$F13)+$S13*(1-$G13))*((1+Inputs!$D$7)^AH$2))),((_xlfn.WEIBULL.DIST(AH$2,$M13,$L13,FALSE)*($T13*(1-$F13)+$S13*(1-$G13))*((1+Inputs!$D$7)^AH$2)))))) -> 0.44603063 | ... BN13: =$E13*IF(BN$2>Inputs!$D$5,0,IF(BN$2>VLOOKUP($H13,Lists!$P$3:$Q$7,2),IF($N13=Lists!$K$3,IF($L13<1,(($U13/$L13)*((1+Inputs!$D$7)^BN$2)),((INT(BN$2/$L13)-INT((BN$2-1)/$L13))*$U13*((1+Inputs!$D$7)^BN$2))),(_xlfn.WEIBULL.DIST(BN$2,$M13,$L13,FALSE)*$U13*((1+Inputs!$D$7)^BN$2))),IF($N13=Lists!$K$3,IF($L13<1,((($T13*(1-$F13)+$S13*(1-$G13))/$L13)*((1+Inputs!$D$7)^BN$2)),((INT(BN$2/$L13)-INT((BN$2-1)/$L13))*($T13*(1-$F13)+$S13*(1-$G13))*((1+Inputs!$D$7)^BN$2))),((_xlfn.WEIBULL.DIST(BN$2,$M13,$L13,FALSE)*($T13*(1-$F13)+$S13*(1-$G13))*((1+Inputs!$D$7)^BN$2)))))) -> 0 | BO13: =NPV(Inputs!$D$6,BQ13:DD13) -> 26.158142 | BP13: =BO13/SUM($Y$3:$Y$136) -> 1.2337457e-05 | BQ13: =MAX(AA13,($E13*IF(BQ$2>Inputs!$D$5,0,IF(BQ$2>VLOOKUP($H13,Lists!$P$3:$Q$7,2),IF($N13=Lists!$K$3,IF($L13<1,(($U13/$L13)*((1+Inputs!$D$7)^BQ$2)),((INT(BQ$2/$L13)-INT((BQ$2-1)/$L13))*$U13*((1+Inputs!$D$7)^BQ$2))),(Inputs!$D$8^((1-_xlfn.WEIBULL.DIST(BQ$2,$M13,$L13,FALSE))/_xlfn.WEIBULL.DIST(BQ$2,$M13,$L13,FALSE))*$U13*((1+Inputs!$D$7)^BQ$2))),IF($N13=Lists!$K$3,IF($L13<1,((($T13*(1-$F13)+$S13*(1-$G13))/$L13)*((1+Inputs!$D$7)^BQ$2)),((INT(BQ$2/$L13)-INT((BQ$2-1)/$L13))*($T13*(1-$F13)+$S13*(1-$G13))*((1+Inputs!$D$7)^BQ$2))),((Inputs!$D$8^((1-_xlfn.WEIBULL.DIST(BQ$2,$M13,$L13,FALSE))/_xlfn.WEIBULL.DIST(BQ$2,$M13,$L13,FALSE))*($T13*(1-$F13)+$S13*(1-$G13))*((1+Inputs!$D$7)^BQ$2)))))))) -> 0 | BR13: =MAX(AB13,($E13*IF(BR$2>Inputs!$D$5,0,IF(BR$2>VLOOKUP($H13,Lists!$P$3:$Q$7,2),IF($N13=Lists!$K$3,IF($L13<1,(($U13/$L13)*((1+Inputs!$D$7)^BR$2)),((INT(BR$2/$L13)-INT((BR$2-1)/$L13))*$U13*((1+Inputs!$D$7)^BR$2))),(Inputs!$D$8^((1-_xlfn.WEIBULL.DIST(BR$2,$M13,$L13,FALSE))/_xlfn.WEIBULL.DIST(BR$2,$M13,$L13,FALSE))*$U13*((1+Inputs!$D$7)^BR$2))),IF($N13=Lists!$K$3,IF($L13<1,((($T13*(1-$F13)+$S13*(1-$G13))/$L13)*((1+Inputs!$D$7)^BR$2)),((INT(BR$2/$L13)-INT((BR$2-1)/$L13))*($T13*(1-$F13)+$S13*(1-$G13))*((1+Inputs!$D$7)^BR$2))),((Inputs!$D$8^((1-_xlfn.WEIBULL.DIST(BR$2,$M13,$L13,FALSE))/_xlfn.WEIBULL.DIST(BR$2,$M13,$L13,FALSE))*($T13*(1-$F13)+$S13*(1-$G13))*((1+Inputs!$D$7)^BR$2)))))))) -> 0.025565381 | BS13: =MAX(AC13,($E13*IF(BS$2>Inputs!$D$5,0,IF(BS$2>VLOOKUP($H13,Lists!$P$3:$Q$7,2),IF($N13=Lists!$K$3,IF($L13<1,(($U13/$L13)*((1+Inputs!$D$7)^BS$2)),((INT(BS$2/$L13)-INT((BS$2-1)/$L13))*$U13*((1+Inputs!$D$7)^BS$2))),(Inputs!$D$8^((1-_xlfn.WEIBULL.DIST(BS$2,$M13,$L13,FALSE))/_xlfn.WEIBULL.DIST(BS$2,$M13,$L13,FALSE))*$U13*((1+Inputs!$D$7)^BS$2))),IF($N13=Lists!$K$3,IF($L13<1,((($T13*(1-$F13)+$S13*(1-$G13))/$L13)*((1+Inputs!$D$7)^BS$2)),((INT(BS$2/$L13)-INT((BS$2-1)/$L13))*($T13*(1-$F13)+$S13*(1-$G13))*((1+Inputs!$D$7)^BS$2))),((Inputs!$D$8^((1-_xlfn.WEIBULL.DIST(BS$2,$M13,$L13,FALSE))/_xlfn.WEIBULL.DIST(BS$2,$M13,$L13,FALSE))*($T13*(1-$F13)+$S13*(1-$G13))*((1+Inputs!$D$7)^BS$2)))))))) -> 0.058601248 | BT13: =MAX(AD13,($E13*IF(BT$2>Inputs!$D$5,0,IF(BT$2>VLOOKUP($H13,Lists!$P$3:$Q$7,2),IF($N13=Lists!$K$3,IF($L13<1,(($U13/$L13)*((1+Inputs!$D$7)^BT$2)),((INT(BT$2/$L13)-INT((BT$2-1)/$L13))*$U13*((1+Inputs!$D$7)^BT$2))),(Inputs!$D$8^((1-_xlfn.WEIBULL.DIST(BT$2,$M13,$L13,FALSE))/_xlfn.WEIBULL.DIST(BT$2,$M13,$L13,FALSE))*$U13*((1+Inputs!$D$7)^BT$2))),IF($N13=Lists!$K$3,IF($L13<1,((($T13*(1-$F13)+$S13*(1-$G13))/$L13)*((1+Inputs!$D$7)^BT$2)),((INT(BT$2/$L13)-INT((BT$2-1)/$L13))*($T13*(1-$F13)+$S13*(1-$G13))*((1+Inputs!$D$7)^BT$2))),((Inputs!$D$8^((1-_xlfn.WEIBULL.DIST(BT$2,$M13,$L13,FALSE))/_xlfn.WEIBULL.DIST(BT$2,$M13,$L13,FALSE))*($T13*(1-$F13)+$S13*(1-$G13))*((1+Inputs!$D$7)^BT$2)))))))) -> 0.10601226 | BU13: =MAX(AE13,($E13*IF(BU$2>Inputs!$D$5,0,IF(BU$2>VLOOKUP($H13,Lists!$P$3:$Q$7,2),IF($N13=Lists!$K$3,IF($L13<1,(($U13/$L13)*((1+Inputs!$D$7)^BU$2)),((INT(BU$2/$L13)-INT((BU$2-1)/$L13))*$U13*((1+Inputs!$D$7)^BU$2))),(Inputs!$D$8^((1-_xlfn.WEIBULL.DIST(BU$2,$M13,$L13,FALSE))/_xlfn.WEIBULL.DIST(BU$2,$M13,$L13,FALSE))*$U13*((1+Inputs!$D$7)^BU$2))),IF($N13=Lists!$K$3,IF($L13<1,((($T13*(1-$F13)+$S13*(1-$G13))/$L13)*((1+Inputs!$D$7)^BU$2)),((INT(BU$2/$L13)-INT((BU$2-1)/$L13))*($T13*(1-$F13)+$S13*(1-$G13))*((1+Inputs!$D$7)^BU$2))),((Inputs!$D$8^((1-_xlfn.WEIBULL.DIST(BU$2,$M13,$L13,FALSE))/_xlfn.WEIBULL.DIST(BU$2,$M13,$L13,FALSE))*($T13*(1-$F13)+$S13*(1-$G13))*((1+Inputs!$D$7)^BU$2)))))))) -> 0.16829872 | BV13: =MAX(AF13,($E13*IF(BV$2>Inputs!$D$5,0,IF(BV$2>VLOOKUP($H13,Lists!$P$3:$Q$7,2),IF($N13=Lists!$K$3,IF($L13<1,(($U13/$L13)*((1+Inputs!$D$7)^BV$2)),((INT(BV$2/$L13)-INT((BV$2-1)/$L13))*$U13*((1+Inputs!$D$7)^BV$2))),(Inputs!$D$8^((1-_xlfn.WEIBULL.DIST(BV$2,$M13,$L13,FALSE))/_xlfn.WEIBULL.DIST(BV$2,$M13,$L13,FALSE))*$U13*((1+Inputs!$D$7)^BV$2))),IF($N13=Lists!$K$3,IF($L13<1,((($T13*(1-$F13)+$S13*(1-$G13))/$L13)*((1+Inputs!$D$7)^BV$2)),((INT(BV$2/$L13)-INT((BV$2-1)/$L13))*($T13*(1-$F13)+$S13*(1-$G13))*((1+Inputs!$D$7)^BV$2))),((Inputs!$D$8^((1-_xlfn.WEIBULL.DIST(BV$2,$M13,$L13,FALSE))/_xlfn.WEIBULL.DIST(BV$2,$M13,$L13,FALSE))*($T13*(1-$F13)+$S13*(1-$G13))*((1+Inputs!$D$7)^BV$2)))))))) -> 0.24576167 | BW13: =MAX(AG13,($E13*IF(BW$2>Inputs!$D$5,0,IF(BW$2>VLOOKUP($H13,Lists!$P$3:$Q$7,2),IF($N13=Lists!$K$3,IF($L13<1,(($U13/$L13)*((1+Inputs!$D$7)^BW$2)),((INT(BW$2/$L13)-INT((BW$2-1)/$L13))*$U13*((1+Inputs!$D$7)^BW$2))),(Inputs!$D$8^((1-_xlfn.WEIBULL.DIST(BW$2,$M13,$L13,FALSE))/_xlfn.WEIBULL.DIST(BW$2,$M13,$L13,FALSE))*$U13*((1+Inputs!$D$7)^BW$2))),IF($N13=Lists!$K$3,IF($L13<1,((($T13*(1-$F13)+$S13*(1-$G13))/$L13)*((1+Inputs!$D$7)^BW$2)),((INT(BW$2/$L13)-INT((BW$2-1)/$L13))*($T13*(1-$F13)+$S13*(1-$G13))*((1+Inputs!$D$7)^BW$2))),((Inputs!$D$8^((1-_xlfn.WEIBULL.DIST(BW$2,$M13,$L13,FALSE))/_xlfn.WEIBULL.DIST(BW$2,$M13,$L13,FALSE))*($T13*(1-$F13)+$S13*(1-$G13))*((1+Inputs!$D$7)^BW$2)))))))) -> 0.33843709 | BX13: =MAX(AH13,($E13*IF(BX$2>Inputs!$D$5,0,IF(BX$2>VLOOKUP($H13,Lists!$P$3:$Q$7,2),IF($N13=Lists!$K$3,IF($L13<1,(($U13/$L13)*((1+Inputs!$D$7)^BX$2)),((INT(BX$2/$L13)-INT((BX$2-1)/$L13))*$U13*((1+Inputs!$D$7)^BX$2))),(Inputs!$D$8^((1-_xlfn.WEIBULL.DIST(BX$2,$M13,$L13,FALSE))/_xlfn.WEIBULL.DIST(BX$2,$M13,$L13,FALSE))*$U13*((1+Inputs!$D$7)^BX$2))),IF($N13=Lists!$K$3,IF($L13<1,((($T13*(1-$F13)+$S13*(1-$G13))/$L13)*((1+Inputs!$D$7)^BX$2)),((INT(BX$2/$L13)-INT((BX$2-1)/$L13))*($T13*(1-$F13)+$S13*(1-$G13))*((1+Inputs!$D$7)^BX$2))),((Inputs!$D$8^((1-_xlfn.WEIBULL.DIST(BX$2,$M13,$L13,FALSE))/_xlfn.WEIBULL.DIST(BX$2,$M13,$L13,FALSE))*($T13*(1-$F13)+$S13*(1-$G13))*((1+Inputs!$D$7)^BX$2)))))))) -> 0.44603063 | ... DD13: =MAX(BN13,($E13*IF(DD$2>Inputs!$D$5,0,IF(DD$2>VLOOKUP($H13,Lists!$P$3:$Q$7,2),IF($N13=Lists!$K$3,IF($L13<1,(($U13/$L13)*((1+Inputs!$D$7)^DD$2)),((INT(DD$2/$L13)-INT((DD$2-1)/$L13))*$U13*((1+Inputs!$D$7)^DD$2))),(Inputs!$D$8^((1-_xlfn.WEIBULL.DIST(DD$2,$M13,$L13,FALSE))/_xlfn.WEIBULL.DIST(DD$2,$M13,$L13,FALSE))*$U13*((1+Inputs!$D$7)^DD$2))),IF($N13=Lists!$K$3,IF($L13<1,((($T13*(1-$F13)+$S13*(1-$G13))/$L13)*((1+Inputs!$D$7)^DD$2)),((INT(DD$2/$L13)-INT((DD$2-1)/$L13))*($T13*(1-$F13)+$S13*(1-$G13))*((1+Inputs!$D$7)^DD$2))),((Inputs!$D$8^((1-_xlfn.WEIBULL.DIST(DD$2,$M13,$L13,FALSE))/_xlfn.WEIBULL.DIST(DD$2,$M13,$L13,FALSE))*($T13*(1-$F13)+$S13*(1-$G13))*((1+Inputs!$D$7)^DD$2)))))))) -> 0
A14: Locate underground AC wiring | B14: Corrective | C14: Repair | D14: AC Wiring | E14: =IF(Inputs!D41=Lists!I6,1,0)*IF(Inputs!D42=Lists!H4,1,0) -> 1 | F14: 0 | G14: 0 | H14: N/A | J14: Utilities locator | K14: =VLOOKUP(J14,'Labor Rates'!$A$1:$F$16,2) -> 25.549904 | L14: 25 | M14: 3 | N14: Weibull | O14: 1 | P14: 4 | Q14: =O14*P14/L14 -> 0.16 | R14: 0 | S14: =P14*O14*K14 -> 102.19962 | T14: =R14*O14 -> 0 | U14: =E14*(T14+S14) -> 102.19962 | X14: =AVERAGE(AA14:AT14) -> 2.9100016 | Y14: =NPV(Inputs!$D$6,AA14:BN14) -> 29.664866 | Z14: =Y14/SUM($Y$3:$Y$136) -> 1.3991399e-05 | AA14: =$E14*IF(AA$2>Inputs!$D$5,0,IF(AA$2>VLOOKUP($H14,Lists!$P$3:$Q$7,2),IF($N14=Lists!$K$3,IF($L14<1,(($U14/$L14)*((1+Inputs!$D$7)^AA$2)),((INT(AA$2/$L14)-INT((AA$2-1)/$L14))*$U14*((1+Inputs!$D$7)^AA$2))),(_xlfn.WEIBULL.DIST(AA$2,$M14,$L14,FALSE)*$U14*((1+Inputs!$D$7)^AA$2))),IF($N14=Lists!$K$3,IF($L14<1,((($T14*(1-$F14)+$S14*(1-$G14))/$L14)*((1+Inputs!$D$7)^AA$2)),((INT(AA$2/$L14)-INT((AA$2-1)/$L14))*($T14*(1-$F14)+$S14*(1-$G14))*((1+Inputs!$D$7)^AA$2))),((_xlfn.WEIBULL.DIST(AA$2,$M14,$L14,FALSE)*($T14*(1-$F14)+$S14*(1-$G14))*((1+Inputs!$D$7)^AA$2)))))) -> 0.020013492 | AB14: =$E14*IF(AB$2>Inputs!$D$5,0,IF(AB$2>VLOOKUP($H14,Lists!$P$3:$Q$7,2),IF($N14=Lists!$K$3,IF($L14<1,(($U14/$L14)*((1+Inputs!$D$7)^AB$2)),((INT(AB$2/$L14)-INT((AB$2-1)/$L14))*$U14*((1+Inputs!$D$7)^AB$2))),(_xlfn.WEIBULL.DIST(AB$2,$M14,$L14,FALSE)*$U14*((1+Inputs!$D$7)^AB$2))),IF($N14=Lists!$K$3,IF($L14<1,((($T14*(1-$F14)+$S14*(1-$G14))/$L14)*((1+Inputs!$D$7)^AB$2)),((INT(AB$2/$L14)-INT((AB$2-1)/$L14))*($T14*(1-$F14)+$S14*(1-$G14))*((1+Inputs!$D$7)^AB$2))),((_xlfn.WEIBULL.DIST(AB$2,$M14,$L14,FALSE)*($T14*(1-$F14)+$S14*(1-$G14))*((1+Inputs!$D$7)^AB$2)))))) -> 0.081618473 | AC14: =$E14*IF(AC$2>Inputs!$D$5,0,IF(AC$2>VLOOKUP($H14,Lists!$P$3:$Q$7,2),IF($N14=Lists!$K$3,IF($L14<1,(($U14/$L14)*((1+Inputs!$D$7)^AC$2)),((INT(AC$2/$L14)-INT((AC$2-1)/$L14))*$U14*((1+Inputs!$D$7)^AC$2))),(_xlfn.WEIBULL.DIST(AC$2,$M14,$L14,FALSE)*$U14*((1+Inputs!$D$7)^AC$2))),IF($N14=Lists!$K$3,IF($L14<1,((($T14*(1-$F14)+$S14*(1-$G14))/$L14)*((1+Inputs!$D$7)^AC$2)),((INT(AC$2/$L14)-INT((AC$2-1)/$L14))*($T14*(1-$F14)+$S14*(1-$G14))*((1+Inputs!$D$7)^AC$2))),((_xlfn.WEIBULL.DIST(AC$2,$M14,$L14,FALSE)*($T14*(1-$F14)+$S14*(1-$G14))*((1+Inputs!$D$7)^AC$2)))))) -> 0.18708676 | AD14: =$E14*IF(AD$2>Inputs!$D$5,0,IF(AD$2>VLOOKUP($H14,Lists!$P$3:$Q$7,2),IF($N14=Lists!$K$3,IF($L14<1,(($U14/$L14)*((1+Inputs!$D$7)^AD$2)),((INT(AD$2/$L14)-INT((AD$2-1)/$L14))*$U14*((1+Inputs!$D$7)^AD$2))),(_xlfn.WEIBULL.DIST(AD$2,$M14,$L14,FALSE)*$U14*((1+Inputs!$D$7)^AD$2))),IF($N14=Lists!$K$3,IF($L14<1,((($T14*(1-$F14)+$S14*(1-$G14))/$L14)*((1+Inputs!$D$7)^AD$2)),((INT(AD$2/$L14)-INT((AD$2-1)/$L14))*($T14*(1-$F14)+$S14*(1-$G14))*((1+Inputs!$D$7)^AD$2))),((_xlfn.WEIBULL.DIST(AD$2,$M14,$L14,FALSE)*($T14*(1-$F14)+$S14*(1-$G14))*((1+Inputs!$D$7)^AD$2)))))) -> 0.33844826 | AE14: =$E14*IF(AE$2>Inputs!$D$5,0,IF(AE$2>VLOOKUP($H14,Lists!$P$3:$Q$7,2),IF($N14=Lists!$K$3,IF($L14<1,(($U14/$L14)*((1+Inputs!$D$7)^AE$2)),((INT(AE$2/$L14)-INT((AE$2-1)/$L14))*$U14*((1+Inputs!$D$7)^AE$2))),(_xlfn.WEIBULL.DIST(AE$2,$M14,$L14,FALSE)*$U14*((1+Inputs!$D$7)^AE$2))),IF($N14=Lists!$K$3,IF($L14<1,((($T14*(1-$F14)+$S14*(1-$G14))/$L14)*((1+Inputs!$D$7)^AE$2)),((INT(AE$2/$L14)-INT((AE$2-1)/$L14))*($T14*(1-$F14)+$S14*(1-$G14))*((1+Inputs!$D$7)^AE$2))),((_xlfn.WEIBULL.DIST(AE$2,$M14,$L14,FALSE)*($T14*(1-$F14)+$S14*(1-$G14))*((1+Inputs!$D$7)^AE$2)))))) -> 0.5373002 | AF14: =$E14*IF(AF$2>Inputs!$D$5,0,IF(AF$2>VLOOKUP($H14,Lists!$P$3:$Q$7,2),IF($N14=Lists!$K$3,IF($L14<1,(($U14/$L14)*((1+Inputs!$D$7)^AF$2)),((INT(AF$2/$L14)-INT((AF$2-1)/$L14))*$U14*((1+Inputs!$D$7)^AF$2))),(_xlfn.WEIBULL.DIST(AF$2,$M14,$L14,FALSE)*$U14*((1+Inputs!$D$7)^AF$2))),IF($N14=Lists!$K$3,IF($L14<1,((($T14*(1-$F14)+$S14*(1-$G14))/$L14)*((1+Inputs!$D$7)^AF$2)),((INT(AF$2/$L14)-INT((AF$2-1)/$L14))*($T14*(1-$F14)+$S14*(1-$G14))*((1+Inputs!$D$7)^AF$2))),((_xlfn.WEIBULL.DIST(AF$2,$M14,$L14,FALSE)*($T14*(1-$F14)+$S14*(1-$G14))*((1+Inputs!$D$7)^AF$2)))))) -> 0.78460367 | AG14: =$E14*IF(AG$2>Inputs!$D$5,0,IF(AG$2>VLOOKUP($H14,Lists!$P$3:$Q$7,2),IF($N14=Lists!$K$3,IF($L14<1,(($U14/$L14)*((1+Inputs!$D$7)^AG$2)),((INT(AG$2/$L14)-INT((AG$2-1)/$L14))*$U14*((1+Inputs!$D$7)^AG$2))),(_xlfn.WEIBULL.DIST(AG$2,$M14,$L14,FALSE)*$U14*((1+Inputs!$D$7)^AG$2))),IF($N14=Lists!$K$3,IF($L14<1,((($T14*(1-$F14)+$S14*(1-$G14))/$L14)*((1+Inputs!$D$7)^AG$2)),((INT(AG$2/$L14)-INT((AG$2-1)/$L14))*($T14*(1-$F14)+$S14*(1-$G14))*((1+Inputs!$D$7)^AG$2))),((_xlfn.WEIBULL.DIST(AG$2,$M14,$L14,FALSE)*($T14*(1-$F14)+$S14*(1-$G14))*((1+Inputs!$D$7)^AG$2)))))) -> 1.0804736 | AH14: =$E14*IF(AH$2>Inputs!$D$5,0,IF(AH$2>VLOOKUP($H14,Lists!$P$3:$Q$7,2),IF($N14=Lists!$K$3,IF($L14<1,(($U14/$L14)*((1+Inputs!$D$7)^AH$2)),((INT(AH$2/$L14)-INT((AH$2-1)/$L14))*$U14*((1+Inputs!$D$7)^AH$2))),(_xlfn.WEIBULL.DIST(AH$2,$M14,$L14,FALSE)*$U14*((1+Inputs!$D$7)^AH$2))),IF($N14=Lists!$K$3,IF($L14<1,((($T14*(1-$F14)+$S14*(1-$G14))/$L14)*((1+Inputs!$D$7)^AH$2)),((INT(AH$2/$L14)-INT((AH$2-1)/$L14))*($T14*(1-$F14)+$S14*(1-$G14))*((1+Inputs!$D$7)^AH$2))),((_xlfn.WEIBULL.DIST(AH$2,$M14,$L14,FALSE)*($T14*(1-$F14)+$S14*(1-$G14))*((1+Inputs!$D$7)^AH$2)))))) -> 1.4239701 | ... BN14: =$E14*IF(BN$2>Inputs!$D$5,0,IF(BN$2>VLOOKUP($H14,Lists!$P$3:$Q$7,2),IF($N14=Lists!$K$3,IF($L14<1,(($U14/$L14)*((1+Inputs!$D$7)^BN$2)),((INT(BN$2/$L14)-INT((BN$2-1)/$L14))*$U14*((1+Inputs!$D$7)^BN$2))),(_xlfn.WEIBULL.DIST(BN$2,$M14,$L14,FALSE)*$U14*((1+Inputs!$D$7)^BN$2))),IF($N14=Lists!$K$3,IF($L14<1,((($T14*(1-$F14)+$S14*(1-$G14))/$L14)*((1+Inputs!$D$7)^BN$2)),((INT(BN$2/$L14)-INT((BN$2-1)/$L14))*($T14*(1-$F14)+$S14*(1-$G14))*((1+Inputs!$D$7)^BN$2))),((_xlfn.WEIBULL.DIST(BN$2,$M14,$L14,FALSE)*($T14*(1-$F14)+$S14*(1-$G14))*((1+Inputs!$D$7)^BN$2)))))) -> 0 | BO14: =NPV(Inputs!$D$6,BQ14:DD14) -> 83.529589 | BP14: =BO14/SUM($Y$3:$Y$136) -> 3.9396632e-05 | BQ14: =MAX(AA14,($E14*IF(BQ$2>Inputs!$D$5,0,IF(BQ$2>VLOOKUP($H14,Lists!$P$3:$Q$7,2),IF($N14=Lists!$K$3,IF($L14<1,(($U14/$L14)*((1+Inputs!$D$7)^BQ$2)),((INT(BQ$2/$L14)-INT((BQ$2-1)/$L14))*$U14*((1+Inputs!$D$7)^BQ$2))),(Inputs!$D$8^((1-_xlfn.WEIBULL.DIST(BQ$2,$M14,$L14,FALSE))/_xlfn.WEIBULL.DIST(BQ$2,$M14,$L14,FALSE))*$U14*((1+Inputs!$D$7)^BQ$2))),IF($N14=Lists!$K$3,IF($L14<1,((($T14*(1-$F14)+$S14*(1-$G14))/$L14)*((1+Inputs!$D$7)^BQ$2)),((INT(BQ$2/$L14)-INT((BQ$2-1)/$L14))*($T14*(1-$F14)+$S14*(1-$G14))*((1+Inputs!$D$7)^BQ$2))),((Inputs!$D$8^((1-_xlfn.WEIBULL.DIST(BQ$2,$M14,$L14,FALSE))/_xlfn.WEIBULL.DIST(BQ$2,$M14,$L14,FALSE))*($T14*(1-$F14)+$S14*(1-$G14))*((1+Inputs!$D$7)^BQ$2)))))))) -> 0.020013492 | BR14: =MAX(AB14,($E14*IF(BR$2>Inputs!$D$5,0,IF(BR$2>VLOOKUP($H14,Lists!$P$3:$Q$7,2),IF($N14=Lists!$K$3,IF($L14<1,(($U14/$L14)*((1+Inputs!$D$7)^BR$2)),((INT(BR$2/$L14)-INT((BR$2-1)/$L14))*$U14*((1+Inputs!$D$7)^BR$2))),(Inputs!$D$8^((1-_xlfn.WEIBULL.DIST(BR$2,$M14,$L14,FALSE))/_xlfn.WEIBULL.DIST(BR$2,$M14,$L14,FALSE))*$U14*((1+Inputs!$D$7)^BR$2))),IF($N14=Lists!$K$3,IF($L14<1,((($T14*(1-$F14)+$S14*(1-$G14))/$L14)*((1+Inputs!$D$7)^BR$2)),((INT(BR$2/$L14)-INT((BR$2-1)/$L14))*($T14*(1-$F14)+$S14*(1-$G14))*((1+Inputs!$D$7)^BR$2))),((Inputs!$D$8^((1-_xlfn.WEIBULL.DIST(BR$2,$M14,$L14,FALSE))/_xlfn.WEIBULL.DIST(BR$2,$M14,$L14,FALSE))*($T14*(1-$F14)+$S14*(1-$G14))*((1+Inputs!$D$7)^BR$2)))))))) -> 0.081618473 | BS14: =MAX(AC14,($E14*IF(BS$2>Inputs!$D$5,0,IF(BS$2>VLOOKUP($H14,Lists!$P$3:$Q$7,2),IF($N14=Lists!$K$3,IF($L14<1,(($U14/$L14)*((1+Inputs!$D$7)^BS$2)),((INT(BS$2/$L14)-INT((BS$2-1)/$L14))*$U14*((1+Inputs!$D$7)^BS$2))),(Inputs!$D$8^((1-_xlfn.WEIBULL.DIST(BS$2,$M14,$L14,FALSE))/_xlfn.WEIBULL.DIST(BS$2,$M14,$L14,FALSE))*$U14*((1+Inputs!$D$7)^BS$2))),IF($N14=Lists!$K$3,IF($L14<1,((($T14*(1-$F14)+$S14*(1-$G14))/$L14)*((1+Inputs!$D$7)^BS$2)),((INT(BS$2/$L14)-INT((BS$2-1)/$L14))*($T14*(1-$F14)+$S14*(1-$G14))*((1+Inputs!$D$7)^BS$2))),((Inputs!$D$8^((1-_xlfn.WEIBULL.DIST(BS$2,$M14,$L14,FALSE))/_xlfn.WEIBULL.DIST(BS$2,$M14,$L14,FALSE))*($T14*(1-$F14)+$S14*(1-$G14))*((1+Inputs!$D$7)^BS$2)))))))) -> 0.18708676 | BT14: =MAX(AD14,($E14*IF(BT$2>Inputs!$D$5,0,IF(BT$2>VLOOKUP($H14,Lists!$P$3:$Q$7,2),IF($N14=Lists!$K$3,IF($L14<1,(($U14/$L14)*((1+Inputs!$D$7)^BT$2)),((INT(BT$2/$L14)-INT((BT$2-1)/$L14))*$U14*((1+Inputs!$D$7)^BT$2))),(Inputs!$D$8^((1-_xlfn.WEIBULL.DIST(BT$2,$M14,$L14,FALSE))/_xlfn.WEIBULL.DIST(BT$2,$M14,$L14,FALSE))*$U14*((1+Inputs!$D$7)^BT$2))),IF($N14=Lists!$K$3,IF($L14<1,((($T14*(1-$F14)+$S14*(1-$G14))/$L14)*((1+Inputs!$D$7)^BT$2)),((INT(BT$2/$L14)-INT((BT$2-1)/$L14))*($T14*(1-$F14)+$S14*(1-$G14))*((1+Inputs!$D$7)^BT$2))),((Inputs!$D$8^((1-_xlfn.WEIBULL.DIST(BT$2,$M14,$L14,FALSE))/_xlfn.WEIBULL.DIST(BT$2,$M14,$L14,FALSE))*($T14*(1-$F14)+$S14*(1-$G14))*((1+Inputs!$D$7)^BT$2)))))))) -> 0.33844826 | BU14: =MAX(AE14,($E14*IF(BU$2>Inputs!$D$5,0,IF(BU$2>VLOOKUP($H14,Lists!$P$3:$Q$7,2),IF($N14=Lists!$K$3,IF($L14<1,(($U14/$L14)*((1+Inputs!$D$7)^BU$2)),((INT(BU$2/$L14)-INT((BU$2-1)/$L14))*$U14*((1+Inputs!$D$7)^BU$2))),(Inputs!$D$8^((1-_xlfn.WEIBULL.DIST(BU$2,$M14,$L14,FALSE))/_xlfn.WEIBULL.DIST(BU$2,$M14,$L14,FALSE))*$U14*((1+Inputs!$D$7)^BU$2))),IF($N14=Lists!$K$3,IF($L14<1,((($T14*(1-$F14)+$S14*(1-$G14))/$L14)*((1+Inputs!$D$7)^BU$2)),((INT(BU$2/$L14)-INT((BU$2-1)/$L14))*($T14*(1-$F14)+$S14*(1-$G14))*((1+Inputs!$D$7)^BU$2))),((Inputs!$D$8^((1-_xlfn.WEIBULL.DIST(BU$2,$M14,$L14,FALSE))/_xlfn.WEIBULL.DIST(BU$2,$M14,$L14,FALSE))*($T14*(1-$F14)+$S14*(1-$G14))*((1+Inputs!$D$7)^BU$2)))))))) -> 0.5373002 | BV14: =MAX(AF14,($E14*IF(BV$2>Inputs!$D$5,0,IF(BV$2>VLOOKUP($H14,Lists!$P$3:$Q$7,2),IF($N14=Lists!$K$3,IF($L14<1,(($U14/$L14)*((1+Inputs!$D$7)^BV$2)),((INT(BV$2/$L14)-INT((BV$2-1)/$L14))*$U14*((1+Inputs!$D$7)^BV$2))),(Inputs!$D$8^((1-_xlfn.WEIBULL.DIST(BV$2,$M14,$L14,FALSE))/_xlfn.WEIBULL.DIST(BV$2,$M14,$L14,FALSE))*$U14*((1+Inputs!$D$7)^BV$2))),IF($N14=Lists!$K$3,IF($L14<1,((($T14*(1-$F14)+$S14*(1-$G14))/$L14)*((1+Inputs!$D$7)^BV$2)),((INT(BV$2/$L14)-INT((BV$2-1)/$L14))*($T14*(1-$F14)+$S14*(1-$G14))*((1+Inputs!$D$7)^BV$2))),((Inputs!$D$8^((1-_xlfn.WEIBULL.DIST(BV$2,$M14,$L14,FALSE))/_xlfn.WEIBULL.DIST(BV$2,$M14,$L14,FALSE))*($T14*(1-$F14)+$S14*(1-$G14))*((1+Inputs!$D$7)^BV$2)))))))) -> 0.78460367 | BW14: =MAX(AG14,($E14*IF(BW$2>Inputs!$D$5,0,IF(BW$2>VLOOKUP($H14,Lists!$P$3:$Q$7,2),IF($N14=Lists!$K$3,IF($L14<1,(($U14/$L14)*((1+Inputs!$D$7)^BW$2)),((INT(BW$2/$L14)-INT((BW$2-1)/$L14))*$U14*((1+Inputs!$D$7)^BW$2))),(Inputs!$D$8^((1-_xlfn.WEIBULL.DIST(BW$2,$M14,$L14,FALSE))/_xlfn.WEIBULL.DIST(BW$2,$M14,$L14,FALSE))*$U14*((1+Inputs!$D$7)^BW$2))),IF($N14=Lists!$K$3,IF($L14<1,((($T14*(1-$F14)+$S14*(1-$G14))/$L14)*((1+Inputs!$D$7)^BW$2)),((INT(BW$2/$L14)-INT((BW$2-1)/$L14))*($T14*(1-$F14)+$S14*(1-$G14))*((1+Inputs!$D$7)^BW$2))),((Inputs!$D$8^((1-_xlfn.WEIBULL.DIST(BW$2,$M14,$L14,FALSE))/_xlfn.WEIBULL.DIST(BW$2,$M14,$L14,FALSE))*($T14*(1-$F14)+$S14*(1-$G14))*((1+Inputs!$D$7)^BW$2)))))))) -> 1.0804736 | BX14: =MAX(AH14,($E14*IF(BX$2>Inputs!$D$5,0,IF(BX$2>VLOOKUP($H14,Lists!$P$3:$Q$7,2),IF($N14=Lists!$K$3,IF($L14<1,(($U14/$L14)*((1+Inputs!$D$7)^BX$2)),((INT(BX$2/$L14)-INT((BX$2-1)/$L14))*$U14*((1+Inputs!$D$7)^BX$2))),(Inputs!$D$8^((1-_xlfn.WEIBULL.DIST(BX$2,$M14,$L14,FALSE))/_xlfn.WEIBULL.DIST(BX$2,$M14,$L14,FALSE))*$U14*((1+Inputs!$D$7)^BX$2))),IF($N14=Lists!$K$3,IF($L14<1,((($T14*(1-$F14)+$S14*(1-$G14))/$L14)*((1+Inputs!$D$7)^BX$2)),((INT(BX$2/$L14)-INT((BX$2-1)/$L14))*($T14*(1-$F14)+$S14*(1-$G14))*((1+Inputs!$D$7)^BX$2))),((Inputs!$D$8^((1-_xlfn.WEIBULL.DIST(BX$2,$M14,$L14,FALSE))/_xlfn.WEIBULL.DIST(BX$2,$M14,$L14,FALSE))*($T14*(1-$F14)+$S14*(1-$G14))*((1+Inputs!$D$7)^BX$2)))))))) -> 1.4239701 | ... DD14: =MAX(BN14,($E14*IF(DD$2>Inputs!$D$5,0,IF(DD$2>VLOOKUP($H14,Lists!$P$3:$Q$7,2),IF($N14=Lists!$K$3,IF($L14<1,(($U14/$L14)*((1+Inputs!$D$7)^DD$2)),((INT(DD$2/$L14)-INT((DD$2-1)/$L14))*$U14*((1+Inputs!$D$7)^DD$2))),(Inputs!$D$8^((1-_xlfn.WEIBULL.DIST(DD$2,$M14,$L14,FALSE))/_xlfn.WEIBULL.DIST(DD$2,$M14,$L14,FALSE))*$U14*((1+Inputs!$D$7)^DD$2))),IF($N14=Lists!$K$3,IF($L14<1,((($T14*(1-$F14)+$S14*(1-$G14))/$L14)*((1+Inputs!$D$7)^DD$2)),((INT(DD$2/$L14)-INT((DD$2-1)/$L14))*($T14*(1-$F14)+$S14*(1-$G14))*((1+Inputs!$D$7)^DD$2))),((Inputs!$D$8^((1-_xlfn.WEIBULL.DIST(DD$2,$M14,$L14,FALSE))/_xlfn.WEIBULL.DIST(DD$2,$M14,$L14,FALSE))*($T14*(1-$F14)+$S14*(1-$G14))*((1+Inputs!$D$7)^DD$2)))))))) -> 0
A15: Repair line-to-line fault | B15: Corrective | C15: Repair | D15: AC Wiring | E15: 1 | F15: 0 | G15: 0 | H15: N/A | J15: Master electrician | K15: =VLOOKUP(J15,'Labor Rates'!$A$1:$F$16,2) -> 32.012019 | L15: 25 | M15: 3 | N15: Weibull | O15: 1 | P15: 1 | Q15: =O15*P15/L15 -> 0.04 | R15: 20 | S15: =P15*O15*K15 -> 32.012019 | T15: =R15*O15 -> 20 | U15: =E15*(T15+S15) -> 52.012019 | X15: =AVERAGE(AA15:AT15) -> 1.4809748 | Y15: =NPV(Inputs!$D$6,AA15:BN15) -> 15.097215 | Z15: =Y15/SUM($Y$3:$Y$136) -> 7.1205838e-06 | AA15: =$E15*IF(AA$2>Inputs!$D$5,0,IF(AA$2>VLOOKUP($H15,Lists!$P$3:$Q$7,2),IF($N15=Lists!$K$3,IF($L15<1,(($U15/$L15)*((1+Inputs!$D$7)^AA$2)),((INT(AA$2/$L15)-INT((AA$2-1)/$L15))*$U15*((1+Inputs!$D$7)^AA$2))),(_xlfn.WEIBULL.DIST(AA$2,$M15,$L15,FALSE)*$U15*((1+Inputs!$D$7)^AA$2))),IF($N15=Lists!$K$3,IF($L15<1,((($T15*(1-$F15)+$S15*(1-$G15))/$L15)*((1+Inputs!$D$7)^AA$2)),((INT(AA$2/$L15)-INT((AA$2-1)/$L15))*($T15*(1-$F15)+$S15*(1-$G15))*((1+Inputs!$D$7)^AA$2))),((_xlfn.WEIBULL.DIST(AA$2,$M15,$L15,FALSE)*($T15*(1-$F15)+$S15*(1-$G15))*((1+Inputs!$D$7)^AA$2)))))) -> 0.010185382 | AB15: =$E15*IF(AB$2>Inputs!$D$5,0,IF(AB$2>VLOOKUP($H15,Lists!$P$3:$Q$7,2),IF($N15=Lists!$K$3,IF($L15<1,(($U15/$L15)*((1+Inputs!$D$7)^AB$2)),((INT(AB$2/$L15)-INT((AB$2-1)/$L15))*$U15*((1+Inputs!$D$7)^AB$2))),(_xlfn.WEIBULL.DIST(AB$2,$M15,$L15,FALSE)*$U15*((1+Inputs!$D$7)^AB$2))),IF($N15=Lists!$K$3,IF($L15<1,((($T15*(1-$F15)+$S15*(1-$G15))/$L15)*((1+Inputs!$D$7)^AB$2)),((INT(AB$2/$L15)-INT((AB$2-1)/$L15))*($T15*(1-$F15)+$S15*(1-$G15))*((1+Inputs!$D$7)^AB$2))),((_xlfn.WEIBULL.DIST(AB$2,$M15,$L15,FALSE)*($T15*(1-$F15)+$S15*(1-$G15))*((1+Inputs!$D$7)^AB$2)))))) -> 0.041537745 | AC15: =$E15*IF(AC$2>Inputs!$D$5,0,IF(AC$2>VLOOKUP($H15,Lists!$P$3:$Q$7,2),IF($N15=Lists!$K$3,IF($L15<1,(($U15/$L15)*((1+Inputs!$D$7)^AC$2)),((INT(AC$2/$L15)-INT((AC$2-1)/$L15))*$U15*((1+Inputs!$D$7)^AC$2))),(_xlfn.WEIBULL.DIST(AC$2,$M15,$L15,FALSE)*$U15*((1+Inputs!$D$7)^AC$2))),IF($N15=Lists!$K$3,IF($L15<1,((($T15*(1-$F15)+$S15*(1-$G15))/$L15)*((1+Inputs!$D$7)^AC$2)),((INT(AC$2/$L15)-INT((AC$2-1)/$L15))*($T15*(1-$F15)+$S15*(1-$G15))*((1+Inputs!$D$7)^AC$2))),((_xlfn.WEIBULL.DIST(AC$2,$M15,$L15,FALSE)*($T15*(1-$F15)+$S15*(1-$G15))*((1+Inputs!$D$7)^AC$2)))))) -> 0.095213276 | AD15: =$E15*IF(AD$2>Inputs!$D$5,0,IF(AD$2>VLOOKUP($H15,Lists!$P$3:$Q$7,2),IF($N15=Lists!$K$3,IF($L15<1,(($U15/$L15)*((1+Inputs!$D$7)^AD$2)),((INT(AD$2/$L15)-INT((AD$2-1)/$L15))*$U15*((1+Inputs!$D$7)^AD$2))),(_xlfn.WEIBULL.DIST(AD$2,$M15,$L15,FALSE)*$U15*((1+Inputs!$D$7)^AD$2))),IF($N15=Lists!$K$3,IF($L15<1,((($T15*(1-$F15)+$S15*(1-$G15))/$L15)*((1+Inputs!$D$7)^AD$2)),((INT(AD$2/$L15)-INT((AD$2-1)/$L15))*($T15*(1-$F15)+$S15*(1-$G15))*((1+Inputs!$D$7)^AD$2))),((_xlfn.WEIBULL.DIST(AD$2,$M15,$L15,FALSE)*($T15*(1-$F15)+$S15*(1-$G15))*((1+Inputs!$D$7)^AD$2)))))) -> 0.17224505 | AE15: =$E15*IF(AE$2>Inputs!$D$5,0,IF(AE$2>VLOOKUP($H15,Lists!$P$3:$Q$7,2),IF($N15=Lists!$K$3,IF($L15<1,(($U15/$L15)*((1+Inputs!$D$7)^AE$2)),((INT(AE$2/$L15)-INT((AE$2-1)/$L15))*$U15*((1+Inputs!$D$7)^AE$2))),(_xlfn.WEIBULL.DIST(AE$2,$M15,$L15,FALSE)*$U15*((1+Inputs!$D$7)^AE$2))),IF($N15=Lists!$K$3,IF($L15<1,((($T15*(1-$F15)+$S15*(1-$G15))/$L15)*((1+Inputs!$D$7)^AE$2)),((INT(AE$2/$L15)-INT((AE$2-1)/$L15))*($T15*(1-$F15)+$S15*(1-$G15))*((1+Inputs!$D$7)^AE$2))),((_xlfn.WEIBULL.DIST(AE$2,$M15,$L15,FALSE)*($T15*(1-$F15)+$S15*(1-$G15))*((1+Inputs!$D$7)^AE$2)))))) -> 0.27344592 | AF15: =$E15*IF(AF$2>Inputs!$D$5,0,IF(AF$2>VLOOKUP($H15,Lists!$P$3:$Q$7,2),IF($N15=Lists!$K$3,IF($L15<1,(($U15/$L15)*((1+Inputs!$D$7)^AF$2)),((INT(AF$2/$L15)-INT((AF$2-1)/$L15))*$U15*((1+Inputs!$D$7)^AF$2))),(_xlfn.WEIBULL.DIST(AF$2,$M15,$L15,FALSE)*$U15*((1+Inputs!$D$7)^AF$2))),IF($N15=Lists!$K$3,IF($L15<1,((($T15*(1-$F15)+$S15*(1-$G15))/$L15)*((1+Inputs!$D$7)^AF$2)),((INT(AF$2/$L15)-INT((AF$2-1)/$L15))*($T15*(1-$F15)+$S15*(1-$G15))*((1+Inputs!$D$7)^AF$2))),((_xlfn.WEIBULL.DIST(AF$2,$M15,$L15,FALSE)*($T15*(1-$F15)+$S15*(1-$G15))*((1+Inputs!$D$7)^AF$2)))))) -> 0.39930504 | AG15: =$E15*IF(AG$2>Inputs!$D$5,0,IF(AG$2>VLOOKUP($H15,Lists!$P$3:$Q$7,2),IF($N15=Lists!$K$3,IF($L15<1,(($U15/$L15)*((1+Inputs!$D$7)^AG$2)),((INT(AG$2/$L15)-INT((AG$2-1)/$L15))*$U15*((1+Inputs!$D$7)^AG$2))),(_xlfn.WEIBULL.DIST(AG$2,$M15,$L15,FALSE)*$U15*((1+Inputs!$D$7)^AG$2))),IF($N15=Lists!$K$3,IF($L15<1,((($T15*(1-$F15)+$S15*(1-$G15))/$L15)*((1+Inputs!$D$7)^AG$2)),((INT(AG$2/$L15)-INT((AG$2-1)/$L15))*($T15*(1-$F15)+$S15*(1-$G15))*((1+Inputs!$D$7)^AG$2))),((_xlfn.WEIBULL.DIST(AG$2,$M15,$L15,FALSE)*($T15*(1-$F15)+$S15*(1-$G15))*((1+Inputs!$D$7)^AG$2)))))) -> 0.54988085 | AH15: =$E15*IF(AH$2>Inputs!$D$5,0,IF(AH$2>VLOOKUP($H15,Lists!$P$3:$Q$7,2),IF($N15=Lists!$K$3,IF($L15<1,(($U15/$L15)*((1+Inputs!$D$7)^AH$2)),((INT(AH$2/$L15)-INT((AH$2-1)/$L15))*$U15*((1+Inputs!$D$7)^AH$2))),(_xlfn.WEIBULL.DIST(AH$2,$M15,$L15,FALSE)*$U15*((1+Inputs!$D$7)^AH$2))),IF($N15=Lists!$K$3,IF($L15<1,((($T15*(1-$F15)+$S15*(1-$G15))/$L15)*((1+Inputs!$D$7)^AH$2)),((INT(AH$2/$L15)-INT((AH$2-1)/$L15))*($T15*(1-$F15)+$S15*(1-$G15))*((1+Inputs!$D$7)^AH$2))),((_xlfn.WEIBULL.DIST(AH$2,$M15,$L15,FALSE)*($T15*(1-$F15)+$S15*(1-$G15))*((1+Inputs!$D$7)^AH$2)))))) -> 0.72469511 | ... BN15: =$E15*IF(BN$2>Inputs!$D$5,0,IF(BN$2>VLOOKUP($H15,Lists!$P$3:$Q$7,2),IF($N15=Lists!$K$3,IF($L15<1,(($U15/$L15)*((1+Inputs!$D$7)^BN$2)),((INT(BN$2/$L15)-INT((BN$2-1)/$L15))*$U15*((1+Inputs!$D$7)^BN$2))),(_xlfn.WEIBULL.DIST(BN$2,$M15,$L15,FALSE)*$U15*((1+Inputs!$D$7)^BN$2))),IF($N15=Lists!$K$3,IF($L15<1,((($T15*(1-$F15)+$S15*(1-$G15))/$L15)*((1+Inputs!$D$7)^BN$2)),((INT(BN$2/$L15)-INT((BN$2-1)/$L15))*($T15*(1-$F15)+$S15*(1-$G15))*((1+Inputs!$D$7)^BN$2))),((_xlfn.WEIBULL.DIST(BN$2,$M15,$L15,FALSE)*($T15*(1-$F15)+$S15*(1-$G15))*((1+Inputs!$D$7)^BN$2)))))) -> 0 | BO15: =NPV(Inputs!$D$6,BQ15:DD15) -> 42.510362 | BP15: =BO15/SUM($Y$3:$Y$136) -> 2.0049962e-05 | BQ15: =MAX(AA15,($E15*IF(BQ$2>Inputs!$D$5,0,IF(BQ$2>VLOOKUP($H15,Lists!$P$3:$Q$7,2),IF($N15=Lists!$K$3,IF($L15<1,(($U15/$L15)*((1+Inputs!$D$7)^BQ$2)),((INT(BQ$2/$L15)-INT((BQ$2-1)/$L15))*$U15*((1+Inputs!$D$7)^BQ$2))),(Inputs!$D$8^((1-_xlfn.WEIBULL.DIST(BQ$2,$M15,$L15,FALSE))/_xlfn.WEIBULL.DIST(BQ$2,$M15,$L15,FALSE))*$U15*((1+Inputs!$D$7)^BQ$2))),IF($N15=Lists!$K$3,IF($L15<1,((($T15*(1-$F15)+$S15*(1-$G15))/$L15)*((1+Inputs!$D$7)^BQ$2)),((INT(BQ$2/$L15)-INT((BQ$2-1)/$L15))*($T15*(1-$F15)+$S15*(1-$G15))*((1+Inputs!$D$7)^BQ$2))),((Inputs!$D$8^((1-_xlfn.WEIBULL.DIST(BQ$2,$M15,$L15,FALSE))/_xlfn.WEIBULL.DIST(BQ$2,$M15,$L15,FALSE))*($T15*(1-$F15)+$S15*(1-$G15))*((1+Inputs!$D$7)^BQ$2)))))))) -> 0.010185382 | BR15: =MAX(AB15,($E15*IF(BR$2>Inputs!$D$5,0,IF(BR$2>VLOOKUP($H15,Lists!$P$3:$Q$7,2),IF($N15=Lists!$K$3,IF($L15<1,(($U15/$L15)*((1+Inputs!$D$7)^BR$2)),((INT(BR$2/$L15)-INT((BR$2-1)/$L15))*$U15*((1+Inputs!$D$7)^BR$2))),(Inputs!$D$8^((1-_xlfn.WEIBULL.DIST(BR$2,$M15,$L15,FALSE))/_xlfn.WEIBULL.DIST(BR$2,$M15,$L15,FALSE))*$U15*((1+Inputs!$D$7)^BR$2))),IF($N15=Lists!$K$3,IF($L15<1,((($T15*(1-$F15)+$S15*(1-$G15))/$L15)*((1+Inputs!$D$7)^BR$2)),((INT(BR$2/$L15)-INT((BR$2-1)/$L15))*($T15*(1-$F15)+$S15*(1-$G15))*((1+Inputs!$D$7)^BR$2))),((Inputs!$D$8^((1-_xlfn.WEIBULL.DIST(BR$2,$M15,$L15,FALSE))/_xlfn.WEIBULL.DIST(BR$2,$M15,$L15,FALSE))*($T15*(1-$F15)+$S15*(1-$G15))*((1+Inputs!$D$7)^BR$2)))))))) -> 0.041537745 | BS15: =MAX(AC15,($E15*IF(BS$2>Inputs!$D$5,0,IF(BS$2>VLOOKUP($H15,Lists!$P$3:$Q$7,2),IF($N15=Lists!$K$3,IF($L15<1,(($U15/$L15)*((1+Inputs!$D$7)^BS$2)),((INT(BS$2/$L15)-INT((BS$2-1)/$L15))*$U15*((1+Inputs!$D$7)^BS$2))),(Inputs!$D$8^((1-_xlfn.WEIBULL.DIST(BS$2,$M15,$L15,FALSE))/_xlfn.WEIBULL.DIST(BS$2,$M15,$L15,FALSE))*$U15*((1+Inputs!$D$7)^BS$2))),IF($N15=Lists!$K$3,IF($L15<1,((($T15*(1-$F15)+$S15*(1-$G15))/$L15)*((1+Inputs!$D$7)^BS$2)),((INT(BS$2/$L15)-INT((BS$2-1)/$L15))*($T15*(1-$F15)+$S15*(1-$G15))*((1+Inputs!$D$7)^BS$2))),((Inputs!$D$8^((1-_xlfn.WEIBULL.DIST(BS$2,$M15,$L15,FALSE))/_xlfn.WEIBULL.DIST(BS$2,$M15,$L15,FALSE))*($T15*(1-$F15)+$S15*(1-$G15))*((1+Inputs!$D$7)^BS$2)))))))) -> 0.095213276 | BT15: =MAX(AD15,($E15*IF(BT$2>Inputs!$D$5,0,IF(BT$2>VLOOKUP($H15,Lists!$P$3:$Q$7,2),IF($N15=Lists!$K$3,IF($L15<1,(($U15/$L15)*((1+Inputs!$D$7)^BT$2)),((INT(BT$2/$L15)-INT((BT$2-1)/$L15))*$U15*((1+Inputs!$D$7)^BT$2))),(Inputs!$D$8^((1-_xlfn.WEIBULL.DIST(BT$2,$M15,$L15,FALSE))/_xlfn.WEIBULL.DIST(BT$2,$M15,$L15,FALSE))*$U15*((1+Inputs!$D$7)^BT$2))),IF($N15=Lists!$K$3,IF($L15<1,((($T15*(1-$F15)+$S15*(1-$G15))/$L15)*((1+Inputs!$D$7)^BT$2)),((INT(BT$2/$L15)-INT((BT$2-1)/$L15))*($T15*(1-$F15)+$S15*(1-$G15))*((1+Inputs!$D$7)^BT$2))),((Inputs!$D$8^((1-_xlfn.WEIBULL.DIST(BT$2,$M15,$L15,FALSE))/_xlfn.WEIBULL.DIST(BT$2,$M15,$L15,FALSE))*($T15*(1-$F15)+$S15*(1-$G15))*((1+Inputs!$D$7)^BT$2)))))))) -> 0.17224505 | BU15: =MAX(AE15,($E15*IF(BU$2>Inputs!$D$5,0,IF(BU$2>VLOOKUP($H15,Lists!$P$3:$Q$7,2),IF($N15=Lists!$K$3,IF($L15<1,(($U15/$L15)*((1+Inputs!$D$7)^BU$2)),((INT(BU$2/$L15)-INT((BU$2-1)/$L15))*$U15*((1+Inputs!$D$7)^BU$2))),(Inputs!$D$8^((1-_xlfn.WEIBULL.DIST(BU$2,$M15,$L15,FALSE))/_xlfn.WEIBULL.DIST(BU$2,$M15,$L15,FALSE))*$U15*((1+Inputs!$D$7)^BU$2))),IF($N15=Lists!$K$3,IF($L15<1,((($T15*(1-$F15)+$S15*(1-$G15))/$L15)*((1+Inputs!$D$7)^BU$2)),((INT(BU$2/$L15)-INT((BU$2-1)/$L15))*($T15*(1-$F15)+$S15*(1-$G15))*((1+Inputs!$D$7)^BU$2))),((Inputs!$D$8^((1-_xlfn.WEIBULL.DIST(BU$2,$M15,$L15,FALSE))/_xlfn.WEIBULL.DIST(BU$2,$M15,$L15,FALSE))*($T15*(1-$F15)+$S15*(1-$G15))*((1+Inputs!$D$7)^BU$2)))))))) -> 0.27344592 | BV15: =MAX(AF15,($E15*IF(BV$2>Inputs!$D$5,0,IF(BV$2>VLOOKUP($H15,Lists!$P$3:$Q$7,2),IF($N15=Lists!$K$3,IF($L15<1,(($U15/$L15)*((1+Inputs!$D$7)^BV$2)),((INT(BV$2/$L15)-INT((BV$2-1)/$L15))*$U15*((1+Inputs!$D$7)^BV$2))),(Inputs!$D$8^((1-_xlfn.WEIBULL.DIST(BV$2,$M15,$L15,FALSE))/_xlfn.WEIBULL.DIST(BV$2,$M15,$L15,FALSE))*$U15*((1+Inputs!$D$7)^BV$2))),IF($N15=Lists!$K$3,IF($L15<1,((($T15*(1-$F15)+$S15*(1-$G15))/$L15)*((1+Inputs!$D$7)^BV$2)),((INT(BV$2/$L15)-INT((BV$2-1)/$L15))*($T15*(1-$F15)+$S15*(1-$G15))*((1+Inputs!$D$7)^BV$2))),((Inputs!$D$8^((1-_xlfn.WEIBULL.DIST(BV$2,$M15,$L15,FALSE))/_xlfn.WEIBULL.DIST(BV$2,$M15,$L15,FALSE))*($T15*(1-$F15)+$S15*(1-$G15))*((1+Inputs!$D$7)^BV$2)))))))) -> 0.39930504 | BW15: =MAX(AG15,($E15*IF(BW$2>Inputs!$D$5,0,IF(BW$2>VLOOKUP($H15,Lists!$P$3:$Q$7,2),IF($N15=Lists!$K$3,IF($L15<1,(($U15/$L15)*((1+Inputs!$D$7)^BW$2)),((INT(BW$2/$L15)-INT((BW$2-1)/$L15))*$U15*((1+Inputs!$D$7)^BW$2))),(Inputs!$D$8^((1-_xlfn.WEIBULL.DIST(BW$2,$M15,$L15,FALSE))/_xlfn.WEIBULL.DIST(BW$2,$M15,$L15,FALSE))*$U15*((1+Inputs!$D$7)^BW$2))),IF($N15=Lists!$K$3,IF($L15<1,((($T15*(1-$F15)+$S15*(1-$G15))/$L15)*((1+Inputs!$D$7)^BW$2)),((INT(BW$2/$L15)-INT((BW$2-1)/$L15))*($T15*(1-$F15)+$S15*(1-$G15))*((1+Inputs!$D$7)^BW$2))),((Inputs!$D$8^((1-_xlfn.WEIBULL.DIST(BW$2,$M15,$L15,FALSE))/_xlfn.WEIBULL.DIST(BW$2,$M15,$L15,FALSE))*($T15*(1-$F15)+$S15*(1-$G15))*((1+Inputs!$D$7)^BW$2)))))))) -> 0.54988085 | BX15: =MAX(AH15,($E15*IF(BX$2>Inputs!$D$5,0,IF(BX$2>VLOOKUP($H15,Lists!$P$3:$Q$7,2),IF($N15=Lists!$K$3,IF($L15<1,(($U15/$L15)*((1+Inputs!$D$7)^BX$2)),((INT(BX$2/$L15)-INT((BX$2-1)/$L15))*$U15*((1+Inputs!$D$7)^BX$2))),(Inputs!$D$8^((1-_xlfn.WEIBULL.DIST(BX$2,$M15,$L15,FALSE))/_xlfn.WEIBULL.DIST(BX$2,$M15,$L15,FALSE))*$U15*((1+Inputs!$D$7)^BX$2))),IF($N15=Lists!$K$3,IF($L15<1,((($T15*(1-$F15)+$S15*(1-$G15))/$L15)*((1+Inputs!$D$7)^BX$2)),((INT(BX$2/$L15)-INT((BX$2-1)/$L15))*($T15*(1-$F15)+$S15*(1-$G15))*((1+Inputs!$D$7)^BX$2))),((Inputs!$D$8^((1-_xlfn.WEIBULL.DIST(BX$2,$M15,$L15,FALSE))/_xlfn.WEIBULL.DIST(BX$2,$M15,$L15,FALSE))*($T15*(1-$F15)+$S15*(1-$G15))*((1+Inputs!$D$7)^BX$2)))))))) -> 0.72469511 | ... DD15: =MAX(BN15,($E15*IF(DD$2>Inputs!$D$5,0,IF(DD$2>VLOOKUP($H15,Lists!$P$3:$Q$7,2),IF($N15=Lists!$K$3,IF($L15<1,(($U15/$L15)*((1+Inputs!$D$7)^DD$2)),((INT(DD$2/$L15)-INT((DD$2-1)/$L15))*$U15*((1+Inputs!$D$7)^DD$2))),(Inputs!$D$8^((1-_xlfn.WEIBULL.DIST(DD$2,$M15,$L15,FALSE))/_xlfn.WEIBULL.DIST(DD$2,$M15,$L15,FALSE))*$U15*((1+Inputs!$D$7)^DD$2))),IF($N15=Lists!$K$3,IF($L15<1,((($T15*(1-$F15)+$S15*(1-$G15))/$L15)*((1+Inputs!$D$7)^DD$2)),((INT(DD$2/$L15)-INT((DD$2-1)/$L15))*($T15*(1-$F15)+$S15*(1-$G15))*((1+Inputs!$D$7)^DD$2))),((Inputs!$D$8^((1-_xlfn.WEIBULL.DIST(DD$2,$M15,$L15,FALSE))/_xlfn.WEIBULL.DIST(DD$2,$M15,$L15,FALSE))*($T15*(1-$F15)+$S15*(1-$G15))*((1+Inputs!$D$7)^DD$2)))))))) -> 0
A16: Replace broken/crushed AC wiring conduit and fittings | B16: Corrective | C16: Repair | D16: AC wiring | E16: 1 | F16: 0 | G16: 0 | H16: N/A | I16: strings | J16: Journeyman electrician | K16: =VLOOKUP(J16,'Labor Rates'!$A$1:$F$16,2) -> 19.903846 | L16: 25 | M16: 3 | N16: Weibull | O16: =Inputs!$D$25 -> 2341.9204 | P16: 0.25 | Q16: =O16*P16/L16 -> 23.419204 | R16: 10 | S16: =P16*O16*K16 -> 11653.306 | T16: =R16*O16 -> 23419.204 | U16: =E16*(T16+S16) -> 35072.509 | X16: =AVERAGE(AA16:AT16) -> 998.64425 | Y16: =NPV(Inputs!$D$6,AA16:BN16) -> 10180.286 | Z16: =Y16/SUM($Y$3:$Y$136) -> 0.0048015198 | AA16: =$E16*IF(AA$2>Inputs!$D$5,0,IF(AA$2>VLOOKUP($H16,Lists!$P$3:$Q$7,2),IF($N16=Lists!$K$3,IF($L16<1,(($U16/$L16)*((1+Inputs!$D$7)^AA$2)),((INT(AA$2/$L16)-INT((AA$2-1)/$L16))*$U16*((1+Inputs!$D$7)^AA$2))),(_xlfn.WEIBULL.DIST(AA$2,$M16,$L16,FALSE)*$U16*((1+Inputs!$D$7)^AA$2))),IF($N16=Lists!$K$3,IF($L16<1,((($T16*(1-$F16)+$S16*(1-$G16))/$L16)*((1+Inputs!$D$7)^AA$2)),((INT(AA$2/$L16)-INT((AA$2-1)/$L16))*($T16*(1-$F16)+$S16*(1-$G16))*((1+Inputs!$D$7)^AA$2))),((_xlfn.WEIBULL.DIST(AA$2,$M16,$L16,FALSE)*($T16*(1-$F16)+$S16*(1-$G16))*((1+Inputs!$D$7)^AA$2)))))) -> 6.8681607 | AB16: =$E16*IF(AB$2>Inputs!$D$5,0,IF(AB$2>VLOOKUP($H16,Lists!$P$3:$Q$7,2),IF($N16=Lists!$K$3,IF($L16<1,(($U16/$L16)*((1+Inputs!$D$7)^AB$2)),((INT(AB$2/$L16)-INT((AB$2-1)/$L16))*$U16*((1+Inputs!$D$7)^AB$2))),(_xlfn.WEIBULL.DIST(AB$2,$M16,$L16,FALSE)*$U16*((1+Inputs!$D$7)^AB$2))),IF($N16=Lists!$K$3,IF($L16<1,((($T16*(1-$F16)+$S16*(1-$G16))/$L16)*((1+Inputs!$D$7)^AB$2)),((INT(AB$2/$L16)-INT((AB$2-1)/$L16))*($T16*(1-$F16)+$S16*(1-$G16))*((1+Inputs!$D$7)^AB$2))),((_xlfn.WEIBULL.DIST(AB$2,$M16,$L16,FALSE)*($T16*(1-$F16)+$S16*(1-$G16))*((1+Inputs!$D$7)^AB$2)))))) -> 28.009544 | AC16: =$E16*IF(AC$2>Inputs!$D$5,0,IF(AC$2>VLOOKUP($H16,Lists!$P$3:$Q$7,2),IF($N16=Lists!$K$3,IF($L16<1,(($U16/$L16)*((1+Inputs!$D$7)^AC$2)),((INT(AC$2/$L16)-INT((AC$2-1)/$L16))*$U16*((1+Inputs!$D$7)^AC$2))),(_xlfn.WEIBULL.DIST(AC$2,$M16,$L16,FALSE)*$U16*((1+Inputs!$D$7)^AC$2))),IF($N16=Lists!$K$3,IF($L16<1,((($T16*(1-$F16)+$S16*(1-$G16))/$L16)*((1+Inputs!$D$7)^AC$2)),((INT(AC$2/$L16)-INT((AC$2-1)/$L16))*($T16*(1-$F16)+$S16*(1-$G16))*((1+Inputs!$D$7)^AC$2))),((_xlfn.WEIBULL.DIST(AC$2,$M16,$L16,FALSE)*($T16*(1-$F16)+$S16*(1-$G16))*((1+Inputs!$D$7)^AC$2)))))) -> 64.203785 | AD16: =$E16*IF(AD$2>Inputs!$D$5,0,IF(AD$2>VLOOKUP($H16,Lists!$P$3:$Q$7,2),IF($N16=Lists!$K$3,IF($L16<1,(($U16/$L16)*((1+Inputs!$D$7)^AD$2)),((INT(AD$2/$L16)-INT((AD$2-1)/$L16))*$U16*((1+Inputs!$D$7)^AD$2))),(_xlfn.WEIBULL.DIST(AD$2,$M16,$L16,FALSE)*$U16*((1+Inputs!$D$7)^AD$2))),IF($N16=Lists!$K$3,IF($L16<1,((($T16*(1-$F16)+$S16*(1-$G16))/$L16)*((1+Inputs!$D$7)^AD$2)),((INT(AD$2/$L16)-INT((AD$2-1)/$L16))*($T16*(1-$F16)+$S16*(1-$G16))*((1+Inputs!$D$7)^AD$2))),((_xlfn.WEIBULL.DIST(AD$2,$M16,$L16,FALSE)*($T16*(1-$F16)+$S16*(1-$G16))*((1+Inputs!$D$7)^AD$2)))))) -> 116.1475 | AE16: =$E16*IF(AE$2>Inputs!$D$5,0,IF(AE$2>VLOOKUP($H16,Lists!$P$3:$Q$7,2),IF($N16=Lists!$K$3,IF($L16<1,(($U16/$L16)*((1+Inputs!$D$7)^AE$2)),((INT(AE$2/$L16)-INT((AE$2-1)/$L16))*$U16*((1+Inputs!$D$7)^AE$2))),(_xlfn.WEIBULL.DIST(AE$2,$M16,$L16,FALSE)*$U16*((1+Inputs!$D$7)^AE$2))),IF($N16=Lists!$K$3,IF($L16<1,((($T16*(1-$F16)+$S16*(1-$G16))/$L16)*((1+Inputs!$D$7)^AE$2)),((INT(AE$2/$L16)-INT((AE$2-1)/$L16))*($T16*(1-$F16)+$S16*(1-$G16))*((1+Inputs!$D$7)^AE$2))),((_xlfn.WEIBULL.DIST(AE$2,$M16,$L16,FALSE)*($T16*(1-$F16)+$S16*(1-$G16))*((1+Inputs!$D$7)^AE$2)))))) -> 184.38882 | AF16: =$E16*IF(AF$2>Inputs!$D$5,0,IF(AF$2>VLOOKUP($H16,Lists!$P$3:$Q$7,2),IF($N16=Lists!$K$3,IF($L16<1,(($U16/$L16)*((1+Inputs!$D$7)^AF$2)),((INT(AF$2/$L16)-INT((AF$2-1)/$L16))*$U16*((1+Inputs!$D$7)^AF$2))),(_xlfn.WEIBULL.DIST(AF$2,$M16,$L16,FALSE)*$U16*((1+Inputs!$D$7)^AF$2))),IF($N16=Lists!$K$3,IF($L16<1,((($T16*(1-$F16)+$S16*(1-$G16))/$L16)*((1+Inputs!$D$7)^AF$2)),((INT(AF$2/$L16)-INT((AF$2-1)/$L16))*($T16*(1-$F16)+$S16*(1-$G16))*((1+Inputs!$D$7)^AF$2))),((_xlfn.WEIBULL.DIST(AF$2,$M16,$L16,FALSE)*($T16*(1-$F16)+$S16*(1-$G16))*((1+Inputs!$D$7)^AF$2)))))) -> 269.25757 | AG16: =$E16*IF(AG$2>Inputs!$D$5,0,IF(AG$2>VLOOKUP($H16,Lists!$P$3:$Q$7,2),IF($N16=Lists!$K$3,IF($L16<1,(($U16/$L16)*((1+Inputs!$D$7)^AG$2)),((INT(AG$2/$L16)-INT((AG$2-1)/$L16))*$U16*((1+Inputs!$D$7)^AG$2))),(_xlfn.WEIBULL.DIST(AG$2,$M16,$L16,FALSE)*$U16*((1+Inputs!$D$7)^AG$2))),IF($N16=Lists!$K$3,IF($L16<1,((($T16*(1-$F16)+$S16*(1-$G16))/$L16)*((1+Inputs!$D$7)^AG$2)),((INT(AG$2/$L16)-INT((AG$2-1)/$L16))*($T16*(1-$F16)+$S16*(1-$G16))*((1+Inputs!$D$7)^AG$2))),((_xlfn.WEIBULL.DIST(AG$2,$M16,$L16,FALSE)*($T16*(1-$F16)+$S16*(1-$G16))*((1+Inputs!$D$7)^AG$2)))))) -> 370.79316 | AH16: =$E16*IF(AH$2>Inputs!$D$5,0,IF(AH$2>VLOOKUP($H16,Lists!$P$3:$Q$7,2),IF($N16=Lists!$K$3,IF($L16<1,(($U16/$L16)*((1+Inputs!$D$7)^AH$2)),((INT(AH$2/$L16)-INT((AH$2-1)/$L16))*$U16*((1+Inputs!$D$7)^AH$2))),(_xlfn.WEIBULL.DIST(AH$2,$M16,$L16,FALSE)*$U16*((1+Inputs!$D$7)^AH$2))),IF($N16=Lists!$K$3,IF($L16<1,((($T16*(1-$F16)+$S16*(1-$G16))/$L16)*((1+Inputs!$D$7)^AH$2)),((INT(AH$2/$L16)-INT((AH$2-1)/$L16))*($T16*(1-$F16)+$S16*(1-$G16))*((1+Inputs!$D$7)^AH$2))),((_xlfn.WEIBULL.DIST(AH$2,$M16,$L16,FALSE)*($T16*(1-$F16)+$S16*(1-$G16))*((1+Inputs!$D$7)^AH$2)))))) -> 488.67313 | ... BN16: =$E16*IF(BN$2>Inputs!$D$5,0,IF(BN$2>VLOOKUP($H16,Lists!$P$3:$Q$7,2),IF($N16=Lists!$K$3,IF($L16<1,(($U16/$L16)*((1+Inputs!$D$7)^BN$2)),((INT(BN$2/$L16)-INT((BN$2-1)/$L16))*$U16*((1+Inputs!$D$7)^BN$2))),(_xlfn.WEIBULL.DIST(BN$2,$M16,$L16,FALSE)*$U16*((1+Inputs!$D$7)^BN$2))),IF($N16=Lists!$K$3,IF($L16<1,((($T16*(1-$F16)+$S16*(1-$G16))/$L16)*((1+Inputs!$D$7)^BN$2)),((INT(BN$2/$L16)-INT((BN$2-1)/$L16))*($T16*(1-$F16)+$S16*(1-$G16))*((1+Inputs!$D$7)^BN$2))),((_xlfn.WEIBULL.DIST(BN$2,$M16,$L16,FALSE)*($T16*(1-$F16)+$S16*(1-$G16))*((1+Inputs!$D$7)^BN$2)))))) -> 0 | BO16: =NPV(Inputs!$D$6,BQ16:DD16) -> 28665.395 | BP16: =BO16/SUM($Y$3:$Y$136) -> 0.01352 | BQ16: =MAX(AA16,($E16*IF(BQ$2>Inputs!$D$5,0,IF(BQ$2>VLOOKUP($H16,Lists!$P$3:$Q$7,2),IF($N16=Lists!$K$3,IF($L16<1,(($U16/$L16)*((1+Inputs!$D$7)^BQ$2)),((INT(BQ$2/$L16)-INT((BQ$2-1)/$L16))*$U16*((1+Inputs!$D$7)^BQ$2))),(Inputs!$D$8^((1-_xlfn.WEIBULL.DIST(BQ$2,$M16,$L16,FALSE))/_xlfn.WEIBULL.DIST(BQ$2,$M16,$L16,FALSE))*$U16*((1+Inputs!$D$7)^BQ$2))),IF($N16=Lists!$K$3,IF($L16<1,((($T16*(1-$F16)+$S16*(1-$G16))/$L16)*((1+Inputs!$D$7)^BQ$2)),((INT(BQ$2/$L16)-INT((BQ$2-1)/$L16))*($T16*(1-$F16)+$S16*(1-$G16))*((1+Inputs!$D$7)^BQ$2))),((Inputs!$D$8^((1-_xlfn.WEIBULL.DIST(BQ$2,$M16,$L16,FALSE))/_xlfn.WEIBULL.DIST(BQ$2,$M16,$L16,FALSE))*($T16*(1-$F16)+$S16*(1-$G16))*((1+Inputs!$D$7)^BQ$2)))))))) -> 6.8681607 | BR16: =MAX(AB16,($E16*IF(BR$2>Inputs!$D$5,0,IF(BR$2>VLOOKUP($H16,Lists!$P$3:$Q$7,2),IF($N16=Lists!$K$3,IF($L16<1,(($U16/$L16)*((1+Inputs!$D$7)^BR$2)),((INT(BR$2/$L16)-INT((BR$2-1)/$L16))*$U16*((1+Inputs!$D$7)^BR$2))),(Inputs!$D$8^((1-_xlfn.WEIBULL.DIST(BR$2,$M16,$L16,FALSE))/_xlfn.WEIBULL.DIST(BR$2,$M16,$L16,FALSE))*$U16*((1+Inputs!$D$7)^BR$2))),IF($N16=Lists!$K$3,IF($L16<1,((($T16*(1-$F16)+$S16*(1-$G16))/$L16)*((1+Inputs!$D$7)^BR$2)),((INT(BR$2/$L16)-INT((BR$2-1)/$L16))*($T16*(1-$F16)+$S16*(1-$G16))*((1+Inputs!$D$7)^BR$2))),((Inputs!$D$8^((1-_xlfn.WEIBULL.DIST(BR$2,$M16,$L16,FALSE))/_xlfn.WEIBULL.DIST(BR$2,$M16,$L16,FALSE))*($T16*(1-$F16)+$S16*(1-$G16))*((1+Inputs!$D$7)^BR$2)))))))) -> 28.009544 | BS16: =MAX(AC16,($E16*IF(BS$2>Inputs!$D$5,0,IF(BS$2>VLOOKUP($H16,Lists!$P$3:$Q$7,2),IF($N16=Lists!$K$3,IF($L16<1,(($U16/$L16)*((1+Inputs!$D$7)^BS$2)),((INT(BS$2/$L16)-INT((BS$2-1)/$L16))*$U16*((1+Inputs!$D$7)^BS$2))),(Inputs!$D$8^((1-_xlfn.WEIBULL.DIST(BS$2,$M16,$L16,FALSE))/_xlfn.WEIBULL.DIST(BS$2,$M16,$L16,FALSE))*$U16*((1+Inputs!$D$7)^BS$2))),IF($N16=Lists!$K$3,IF($L16<1,((($T16*(1-$F16)+$S16*(1-$G16))/$L16)*((1+Inputs!$D$7)^BS$2)),((INT(BS$2/$L16)-INT((BS$2-1)/$L16))*($T16*(1-$F16)+$S16*(1-$G16))*((1+Inputs!$D$7)^BS$2))),((Inputs!$D$8^((1-_xlfn.WEIBULL.DIST(BS$2,$M16,$L16,FALSE))/_xlfn.WEIBULL.DIST(BS$2,$M16,$L16,FALSE))*($T16*(1-$F16)+$S16*(1-$G16))*((1+Inputs!$D$7)^BS$2)))))))) -> 64.203785 | BT16: =MAX(AD16,($E16*IF(BT$2>Inputs!$D$5,0,IF(BT$2>VLOOKUP($H16,Lists!$P$3:$Q$7,2),IF($N16=Lists!$K$3,IF($L16<1,(($U16/$L16)*((1+Inputs!$D$7)^BT$2)),((INT(BT$2/$L16)-INT((BT$2-1)/$L16))*$U16*((1+Inputs!$D$7)^BT$2))),(Inputs!$D$8^((1-_xlfn.WEIBULL.DIST(BT$2,$M16,$L16,FALSE))/_xlfn.WEIBULL.DIST(BT$2,$M16,$L16,FALSE))*$U16*((1+Inputs!$D$7)^BT$2))),IF($N16=Lists!$K$3,IF($L16<1,((($T16*(1-$F16)+$S16*(1-$G16))/$L16)*((1+Inputs!$D$7)^BT$2)),((INT(BT$2/$L16)-INT((BT$2-1)/$L16))*($T16*(1-$F16)+$S16*(1-$G16))*((1+Inputs!$D$7)^BT$2))),((Inputs!$D$8^((1-_xlfn.WEIBULL.DIST(BT$2,$M16,$L16,FALSE))/_xlfn.WEIBULL.DIST(BT$2,$M16,$L16,FALSE))*($T16*(1-$F16)+$S16*(1-$G16))*((1+Inputs!$D$7)^BT$2)))))))) -> 116.1475 | BU16: =MAX(AE16,($E16*IF(BU$2>Inputs!$D$5,0,IF(BU$2>VLOOKUP($H16,Lists!$P$3:$Q$7,2),IF($N16=Lists!$K$3,IF($L16<1,(($U16/$L16)*((1+Inputs!$D$7)^BU$2)),((INT(BU$2/$L16)-INT((BU$2-1)/$L16))*$U16*((1+Inputs!$D$7)^BU$2))),(Inputs!$D$8^((1-_xlfn.WEIBULL.DIST(BU$2,$M16,$L16,FALSE))/_xlfn.WEIBULL.DIST(BU$2,$M16,$L16,FALSE))*$U16*((1+Inputs!$D$7)^BU$2))),IF($N16=Lists!$K$3,IF($L16<1,((($T16*(1-$F16)+$S16*(1-$G16))/$L16)*((1+Inputs!$D$7)^BU$2)),((INT(BU$2/$L16)-INT((BU$2-1)/$L16))*($T16*(1-$F16)+$S16*(1-$G16))*((1+Inputs!$D$7)^BU$2))),((Inputs!$D$8^((1-_xlfn.WEIBULL.DIST(BU$2,$M16,$L16,FALSE))/_xlfn.WEIBULL.DIST(BU$2,$M16,$L16,FALSE))*($T16*(1-$F16)+$S16*(1-$G16))*((1+Inputs!$D$7)^BU$2)))))))) -> 184.38882 | BV16: =MAX(AF16,($E16*IF(BV$2>Inputs!$D$5,0,IF(BV$2>VLOOKUP($H16,Lists!$P$3:$Q$7,2),IF($N16=Lists!$K$3,IF($L16<1,(($U16/$L16)*((1+Inputs!$D$7)^BV$2)),((INT(BV$2/$L16)-INT((BV$2-1)/$L16))*$U16*((1+Inputs!$D$7)^BV$2))),(Inputs!$D$8^((1-_xlfn.WEIBULL.DIST(BV$2,$M16,$L16,FALSE))/_xlfn.WEIBULL.DIST(BV$2,$M16,$L16,FALSE))*$U16*((1+Inputs!$D$7)^BV$2))),IF($N16=Lists!$K$3,IF($L16<1,((($T16*(1-$F16)+$S16*(1-$G16))/$L16)*((1+Inputs!$D$7)^BV$2)),((INT(BV$2/$L16)-INT((BV$2-1)/$L16))*($T16*(1-$F16)+$S16*(1-$G16))*((1+Inputs!$D$7)^BV$2))),((Inputs!$D$8^((1-_xlfn.WEIBULL.DIST(BV$2,$M16,$L16,FALSE))/_xlfn.WEIBULL.DIST(BV$2,$M16,$L16,FALSE))*($T16*(1-$F16)+$S16*(1-$G16))*((1+Inputs!$D$7)^BV$2)))))))) -> 269.25757 | BW16: =MAX(AG16,($E16*IF(BW$2>Inputs!$D$5,0,IF(BW$2>VLOOKUP($H16,Lists!$P$3:$Q$7,2),IF($N16=Lists!$K$3,IF($L16<1,(($U16/$L16)*((1+Inputs!$D$7)^BW$2)),((INT(BW$2/$L16)-INT((BW$2-1)/$L16))*$U16*((1+Inputs!$D$7)^BW$2))),(Inputs!$D$8^((1-_xlfn.WEIBULL.DIST(BW$2,$M16,$L16,FALSE))/_xlfn.WEIBULL.DIST(BW$2,$M16,$L16,FALSE))*$U16*((1+Inputs!$D$7)^BW$2))),IF($N16=Lists!$K$3,IF($L16<1,((($T16*(1-$F16)+$S16*(1-$G16))/$L16)*((1+Inputs!$D$7)^BW$2)),((INT(BW$2/$L16)-INT((BW$2-1)/$L16))*($T16*(1-$F16)+$S16*(1-$G16))*((1+Inputs!$D$7)^BW$2))),((Inputs!$D$8^((1-_xlfn.WEIBULL.DIST(BW$2,$M16,$L16,FALSE))/_xlfn.WEIBULL.DIST(BW$2,$M16,$L16,FALSE))*($T16*(1-$F16)+$S16*(1-$G16))*((1+Inputs!$D$7)^BW$2)))))))) -> 370.79316 | BX16: =MAX(AH16,($E16*IF(BX$2>Inputs!$D$5,0,IF(BX$2>VLOOKUP($H16,Lists!$P$3:$Q$7,2),IF($N16=Lists!$K$3,IF($L16<1,(($U16/$L16)*((1+Inputs!$D$7)^BX$2)),((INT(BX$2/$L16)-INT((BX$2-1)/$L16))*$U16*((1+Inputs!$D$7)^BX$2))),(Inputs!$D$8^((1-_xlfn.WEIBULL.DIST(BX$2,$M16,$L16,FALSE))/_xlfn.WEIBULL.DIST(BX$2,$M16,$L16,FALSE))*$U16*((1+Inputs!$D$7)^BX$2))),IF($N16=Lists!$K$3,IF($L16<1,((($T16*(1-$F16)+$S16*(1-$G16))/$L16)*((1+Inputs!$D$7)^BX$2)),((INT(BX$2/$L16)-INT((BX$2-1)/$L16))*($T16*(1-$F16)+$S16*(1-$G16))*((1+Inputs!$D$7)^BX$2))),((Inputs!$D$8^((1-_xlfn.WEIBULL.DIST(BX$2,$M16,$L16,FALSE))/_xlfn.WEIBULL.DIST(BX$2,$M16,$L16,FALSE))*($T16*(1-$F16)+$S16*(1-$G16))*((1+Inputs!$D$7)^BX$2)))))))) -> 488.67313 | ... DD16: =MAX(BN16,($E16*IF(DD$2>Inputs!$D$5,0,IF(DD$2>VLOOKUP($H16,Lists!$P$3:$Q$7,2),IF($N16=Lists!$K$3,IF($L16<1,(($U16/$L16)*((1+Inputs!$D$7)^DD$2)),((INT(DD$2/$L16)-INT((DD$2-1)/$L16))*$U16*((1+Inputs!$D$7)^DD$2))),(Inputs!$D$8^((1-_xlfn.WEIBULL.DIST(DD$2,$M16,$L16,FALSE))/_xlfn.WEIBULL.DIST(DD$2,$M16,$L16,FALSE))*$U16*((1+Inputs!$D$7)^DD$2))),IF($N16=Lists!$K$3,IF($L16<1,((($T16*(1-$F16)+$S16*(1-$G16))/$L16)*((1+Inputs!$D$7)^DD$2)),((INT(DD$2/$L16)-INT((DD$2-1)/$L16))*($T16*(1-$F16)+$S16*(1-$G16))*((1+Inputs!$D$7)^DD$2))),((Inputs!$D$8^((1-_xlfn.WEIBULL.DIST(DD$2,$M16,$L16,FALSE))/_xlfn.WEIBULL.DIST(DD$2,$M16,$L16,FALSE))*($T16*(1-$F16)+$S16*(1-$G16))*((1+Inputs!$D$7)^DD$2)))))))) -> 0
A17: Replace MC connector lead to combiner box | B17: Corrective | C17: Repair | D17: DC wiring | E17: =IF(Inputs!$D$30=Lists!$M$4,1,0) -> 1 | F17: 1 | G17: 1 | H17: EPC | I17: modules | J17: PV module/array Specialist | K17: =VLOOKUP(J17,'Labor Rates'!$A$1:$F$16,2) -> 33.173077 | L17: 25 | M17: 1 | N17: Weibull | O17: =Inputs!$D$21 -> 32787 | P17: 0.1 | Q17: =O17*P17/L17 -> 131.148 | R17: 20 | S17: =P17*O17*K17 -> 108764.57 | T17: =R17*O17 -> 655740 | U17: =E17*(T17+S17) -> 764504.57 | X17: =AVERAGE(AA17:AT17) -> 23406.161 | Y17: =NPV(Inputs!$D$6,AA17:BN17) -> 267966.07 | Z17: =Y17/SUM($Y$3:$Y$136) -> 0.12638588 | AA17: =$E17*IF(AA$2>Inputs!$D$5,0,IF(AA$2>VLOOKUP($H17,Lists!$P$3:$Q$7,2),IF($N17=Lists!$K$3,IF($L17<1,(($U17/$L17)*((1+Inputs!$D$7)^AA$2)),((INT(AA$2/$L17)-INT((AA$2-1)/$L17))*$U17*((1+Inputs!$D$7)^AA$2))),(_xlfn.WEIBULL.DIST(AA$2,$M17,$L17,FALSE)*$U17*((1+Inputs!$D$7)^AA$2))),IF($N17=Lists!$K$3,IF($L17<1,((($T17*(1-$F17)+$S17*(1-$G17))/$L17)*((1+Inputs!$D$7)^AA$2)),((INT(AA$2/$L17)-INT((AA$2-1)/$L17))*($T17*(1-$F17)+$S17*(1-$G17))*((1+Inputs!$D$7)^AA$2))),((_xlfn.WEIBULL.DIST(AA$2,$M17,$L17,FALSE)*($T17*(1-$F17)+$S17*(1-$G17))*((1+Inputs!$D$7)^AA$2)))))) -> 0 | AB17: =$E17*IF(AB$2>Inputs!$D$5,0,IF(AB$2>VLOOKUP($H17,Lists!$P$3:$Q$7,2),IF($N17=Lists!$K$3,IF($L17<1,(($U17/$L17)*((1+Inputs!$D$7)^AB$2)),((INT(AB$2/$L17)-INT((AB$2-1)/$L17))*$U17*((1+Inputs!$D$7)^AB$2))),(_xlfn.WEIBULL.DIST(AB$2,$M17,$L17,FALSE)*$U17*((1+Inputs!$D$7)^AB$2))),IF($N17=Lists!$K$3,IF($L17<1,((($T17*(1-$F17)+$S17*(1-$G17))/$L17)*((1+Inputs!$D$7)^AB$2)),((INT(AB$2/$L17)-INT((AB$2-1)/$L17))*($T17*(1-$F17)+$S17*(1-$G17))*((1+Inputs!$D$7)^AB$2))),((_xlfn.WEIBULL.DIST(AB$2,$M17,$L17,FALSE)*($T17*(1-$F17)+$S17*(1-$G17))*((1+Inputs!$D$7)^AB$2)))))) -> 29369.521 | AC17: =$E17*IF(AC$2>Inputs!$D$5,0,IF(AC$2>VLOOKUP($H17,Lists!$P$3:$Q$7,2),IF($N17=Lists!$K$3,IF($L17<1,(($U17/$L17)*((1+Inputs!$D$7)^AC$2)),((INT(AC$2/$L17)-INT((AC$2-1)/$L17))*$U17*((1+Inputs!$D$7)^AC$2))),(_xlfn.WEIBULL.DIST(AC$2,$M17,$L17,FALSE)*$U17*((1+Inputs!$D$7)^AC$2))),IF($N17=Lists!$K$3,IF($L17<1,((($T17*(1-$F17)+$S17*(1-$G17))/$L17)*((1+Inputs!$D$7)^AC$2)),((INT(AC$2/$L17)-INT((AC$2-1)/$L17))*($T17*(1-$F17)+$S17*(1-$G17))*((1+Inputs!$D$7)^AC$2))),((_xlfn.WEIBULL.DIST(AC$2,$M17,$L17,FALSE)*($T17*(1-$F17)+$S17*(1-$G17))*((1+Inputs!$D$7)^AC$2)))))) -> 28782.284 | AD17: =$E17*IF(AD$2>Inputs!$D$5,0,IF(AD$2>VLOOKUP($H17,Lists!$P$3:$Q$7,2),IF($N17=Lists!$K$3,IF($L17<1,(($U17/$L17)*((1+Inputs!$D$7)^AD$2)),((INT(AD$2/$L17)-INT((AD$2-1)/$L17))*$U17*((1+Inputs!$D$7)^AD$2))),(_xlfn.WEIBULL.DIST(AD$2,$M17,$L17,FALSE)*$U17*((1+Inputs!$D$7)^AD$2))),IF($N17=Lists!$K$3,IF($L17<1,((($T17*(1-$F17)+$S17*(1-$G17))/$L17)*((1+Inputs!$D$7)^AD$2)),((INT(AD$2/$L17)-INT((AD$2-1)/$L17))*($T17*(1-$F17)+$S17*(1-$G17))*((1+Inputs!$D$7)^AD$2))),((_xlfn.WEIBULL.DIST(AD$2,$M17,$L17,FALSE)*($T17*(1-$F17)+$S17*(1-$G17))*((1+Inputs!$D$7)^AD$2)))))) -> 28206.789 | AE17: =$E17*IF(AE$2>Inputs!$D$5,0,IF(AE$2>VLOOKUP($H17,Lists!$P$3:$Q$7,2),IF($N17=Lists!$K$3,IF($L17<1,(($U17/$L17)*((1+Inputs!$D$7)^AE$2)),((INT(AE$2/$L17)-INT((AE$2-1)/$L17))*$U17*((1+Inputs!$D$7)^AE$2))),(_xlfn.WEIBULL.DIST(AE$2,$M17,$L17,FALSE)*$U17*((1+Inputs!$D$7)^AE$2))),IF($N17=Lists!$K$3,IF($L17<1,((($T17*(1-$F17)+$S17*(1-$G17))/$L17)*((1+Inputs!$D$7)^AE$2)),((INT(AE$2/$L17)-INT((AE$2-1)/$L17))*($T17*(1-$F17)+$S17*(1-$G17))*((1+Inputs!$D$7)^AE$2))),((_xlfn.WEIBULL.DIST(AE$2,$M17,$L17,FALSE)*($T17*(1-$F17)+$S17*(1-$G17))*((1+Inputs!$D$7)^AE$2)))))) -> 27642.8 | AF17: =$E17*IF(AF$2>Inputs!$D$5,0,IF(AF$2>VLOOKUP($H17,Lists!$P$3:$Q$7,2),IF($N17=Lists!$K$3,IF($L17<1,(($U17/$L17)*((1+Inputs!$D$7)^AF$2)),((INT(AF$2/$L17)-INT((AF$2-1)/$L17))*$U17*((1+Inputs!$D$7)^AF$2))),(_xlfn.WEIBULL.DIST(AF$2,$M17,$L17,FALSE)*$U17*((1+Inputs!$D$7)^AF$2))),IF($N17=Lists!$K$3,IF($L17<1,((($T17*(1-$F17)+$S17*(1-$G17))/$L17)*((1+Inputs!$D$7)^AF$2)),((INT(AF$2/$L17)-INT((AF$2-1)/$L17))*($T17*(1-$F17)+$S17*(1-$G17))*((1+Inputs!$D$7)^AF$2))),((_xlfn.WEIBULL.DIST(AF$2,$M17,$L17,FALSE)*($T17*(1-$F17)+$S17*(1-$G17))*((1+Inputs!$D$7)^AF$2)))))) -> 27090.089 | AG17: =$E17*IF(AG$2>Inputs!$D$5,0,IF(AG$2>VLOOKUP($H17,Lists!$P$3:$Q$7,2),IF($N17=Lists!$K$3,IF($L17<1,(($U17/$L17)*((1+Inputs!$D$7)^AG$2)),((INT(AG$2/$L17)-INT((AG$2-1)/$L17))*$U17*((1+Inputs!$D$7)^AG$2))),(_xlfn.WEIBULL.DIST(AG$2,$M17,$L17,FALSE)*$U17*((1+Inputs!$D$7)^AG$2))),IF($N17=Lists!$K$3,IF($L17<1,((($T17*(1-$F17)+$S17*(1-$G17))/$L17)*((1+Inputs!$D$7)^AG$2)),((INT(AG$2/$L17)-INT((AG$2-1)/$L17))*($T17*(1-$F17)+$S17*(1-$G17))*((1+Inputs!$D$7)^AG$2))),((_xlfn.WEIBULL.DIST(AG$2,$M17,$L17,FALSE)*($T17*(1-$F17)+$S17*(1-$G17))*((1+Inputs!$D$7)^AG$2)))))) -> 26548.429 | AH17: =$E17*IF(AH$2>Inputs!$D$5,0,IF(AH$2>VLOOKUP($H17,Lists!$P$3:$Q$7,2),IF($N17=Lists!$K$3,IF($L17<1,(($U17/$L17)*((1+Inputs!$D$7)^AH$2)),((INT(AH$2/$L17)-INT((AH$2-1)/$L17))*$U17*((1+Inputs!$D$7)^AH$2))),(_xlfn.WEIBULL.DIST(AH$2,$M17,$L17,FALSE)*$U17*((1+Inputs!$D$7)^AH$2))),IF($N17=Lists!$K$3,IF($L17<1,((($T17*(1-$F17)+$S17*(1-$G17))/$L17)*((1+Inputs!$D$7)^AH$2)),((INT(AH$2/$L17)-INT((AH$2-1)/$L17))*($T17*(1-$F17)+$S17*(1-$G17))*((1+Inputs!$D$7)^AH$2))),((_xlfn.WEIBULL.DIST(AH$2,$M17,$L17,FALSE)*($T17*(1-$F17)+$S17*(1-$G17))*((1+Inputs!$D$7)^AH$2)))))) -> 26017.599 | ... BN17: =$E17*IF(BN$2>Inputs!$D$5,0,IF(BN$2>VLOOKUP($H17,Lists!$P$3:$Q$7,2),IF($N17=Lists!$K$3,IF($L17<1,(($U17/$L17)*((1+Inputs!$D$7)^BN$2)),((INT(BN$2/$L17)-INT((BN$2-1)/$L17))*$U17*((1+Inputs!$D$7)^BN$2))),(_xlfn.WEIBULL.DIST(BN$2,$M17,$L17,FALSE)*$U17*((1+Inputs!$D$7)^BN$2))),IF($N17=Lists!$K$3,IF($L17<1,((($T17*(1-$F17)+$S17*(1-$G17))/$L17)*((1+Inputs!$D$7)^BN$2)),((INT(BN$2/$L17)-INT((BN$2-1)/$L17))*($T17*(1-$F17)+$S17*(1-$G17))*((1+Inputs!$D$7)^BN$2))),((_xlfn.WEIBULL.DIST(BN$2,$M17,$L17,FALSE)*($T17*(1-$F17)+$S17*(1-$G17))*((1+Inputs!$D$7)^BN$2)))))) -> 0 | BO17: =NPV(Inputs!$D$6,BQ17:DD17) -> 543394.88 | BP17: =BO17/SUM($Y$3:$Y$136) -> 0.25629155 | BQ17: =MAX(AA17,($E17*IF(BQ$2>Inputs!$D$5,0,IF(BQ$2>VLOOKUP($H17,Lists!$P$3:$Q$7,2),IF($N17=Lists!$K$3,IF($L17<1,(($U17/$L17)*((1+Inputs!$D$7)^BQ$2)),((INT(BQ$2/$L17)-INT((BQ$2-1)/$L17))*$U17*((1+Inputs!$D$7)^BQ$2))),(Inputs!$D$8^((1-_xlfn.WEIBULL.DIST(BQ$2,$M17,$L17,FALSE))/_xlfn.WEIBULL.DIST(BQ$2,$M17,$L17,FALSE))*$U17*((1+Inputs!$D$7)^BQ$2))),IF($N17=Lists!$K$3,IF($L17<1,((($T17*(1-$F17)+$S17*(1-$G17))/$L17)*((1+Inputs!$D$7)^BQ$2)),((INT(BQ$2/$L17)-INT((BQ$2-1)/$L17))*($T17*(1-$F17)+$S17*(1-$G17))*((1+Inputs!$D$7)^BQ$2))),((Inputs!$D$8^((1-_xlfn.WEIBULL.DIST(BQ$2,$M17,$L17,FALSE))/_xlfn.WEIBULL.DIST(BQ$2,$M17,$L17,FALSE))*($T17*(1-$F17)+$S17*(1-$G17))*((1+Inputs!$D$7)^BQ$2)))))))) -> 0 | BR17: =MAX(AB17,($E17*IF(BR$2>Inputs!$D$5,0,IF(BR$2>VLOOKUP($H17,Lists!$P$3:$Q$7,2),IF($N17=Lists!$K$3,IF($L17<1,(($U17/$L17)*((1+Inputs!$D$7)^BR$2)),((INT(BR$2/$L17)-INT((BR$2-1)/$L17))*$U17*((1+Inputs!$D$7)^BR$2))),(Inputs!$D$8^((1-_xlfn.WEIBULL.DIST(BR$2,$M17,$L17,FALSE))/_xlfn.WEIBULL.DIST(BR$2,$M17,$L17,FALSE))*$U17*((1+Inputs!$D$7)^BR$2))),IF($N17=Lists!$K$3,IF($L17<1,((($T17*(1-$F17)+$S17*(1-$G17))/$L17)*((1+Inputs!$D$7)^BR$2)),((INT(BR$2/$L17)-INT((BR$2-1)/$L17))*($T17*(1-$F17)+$S17*(1-$G17))*((1+Inputs!$D$7)^BR$2))),((Inputs!$D$8^((1-_xlfn.WEIBULL.DIST(BR$2,$M17,$L17,FALSE))/_xlfn.WEIBULL.DIST(BR$2,$M17,$L17,FALSE))*($T17*(1-$F17)+$S17*(1-$G17))*((1+Inputs!$D$7)^BR$2)))))))) -> 90383.289 | BS17: =MAX(AC17,($E17*IF(BS$2>Inputs!$D$5,0,IF(BS$2>VLOOKUP($H17,Lists!$P$3:$Q$7,2),IF($N17=Lists!$K$3,IF($L17<1,(($U17/$L17)*((1+Inputs!$D$7)^BS$2)),((INT(BS$2/$L17)-INT((BS$2-1)/$L17))*$U17*((1+Inputs!$D$7)^BS$2))),(Inputs!$D$8^((1-_xlfn.WEIBULL.DIST(BS$2,$M17,$L17,FALSE))/_xlfn.WEIBULL.DIST(BS$2,$M17,$L17,FALSE))*$U17*((1+Inputs!$D$7)^BS$2))),IF($N17=Lists!$K$3,IF($L17<1,((($T17*(1-$F17)+$S17*(1-$G17))/$L17)*((1+Inputs!$D$7)^BS$2)),((INT(BS$2/$L17)-INT((BS$2-1)/$L17))*($T17*(1-$F17)+$S17*(1-$G17))*((1+Inputs!$D$7)^BS$2))),((Inputs!$D$8^((1-_xlfn.WEIBULL.DIST(BS$2,$M17,$L17,FALSE))/_xlfn.WEIBULL.DIST(BS$2,$M17,$L17,FALSE))*($T17*(1-$F17)+$S17*(1-$G17))*((1+Inputs!$D$7)^BS$2)))))))) -> 84074.638 | BT17: =MAX(AD17,($E17*IF(BT$2>Inputs!$D$5,0,IF(BT$2>VLOOKUP($H17,Lists!$P$3:$Q$7,2),IF($N17=Lists!$K$3,IF($L17<1,(($U17/$L17)*((1+Inputs!$D$7)^BT$2)),((INT(BT$2/$L17)-INT((BT$2-1)/$L17))*$U17*((1+Inputs!$D$7)^BT$2))),(Inputs!$D$8^((1-_xlfn.WEIBULL.DIST(BT$2,$M17,$L17,FALSE))/_xlfn.WEIBULL.DIST(BT$2,$M17,$L17,FALSE))*$U17*((1+Inputs!$D$7)^BT$2))),IF($N17=Lists!$K$3,IF($L17<1,((($T17*(1-$F17)+$S17*(1-$G17))/$L17)*((1+Inputs!$D$7)^BT$2)),((INT(BT$2/$L17)-INT((BT$2-1)/$L17))*($T17*(1-$F17)+$S17*(1-$G17))*((1+Inputs!$D$7)^BT$2))),((Inputs!$D$8^((1-_xlfn.WEIBULL.DIST(BT$2,$M17,$L17,FALSE))/_xlfn.WEIBULL.DIST(BT$2,$M17,$L17,FALSE))*($T17*(1-$F17)+$S17*(1-$G17))*((1+Inputs!$D$7)^BT$2)))))))) -> 77912.742 | BU17: =MAX(AE17,($E17*IF(BU$2>Inputs!$D$5,0,IF(BU$2>VLOOKUP($H17,Lists!$P$3:$Q$7,2),IF($N17=Lists!$K$3,IF($L17<1,(($U17/$L17)*((1+Inputs!$D$7)^BU$2)),((INT(BU$2/$L17)-INT((BU$2-1)/$L17))*$U17*((1+Inputs!$D$7)^BU$2))),(Inputs!$D$8^((1-_xlfn.WEIBULL.DIST(BU$2,$M17,$L17,FALSE))/_xlfn.WEIBULL.DIST(BU$2,$M17,$L17,FALSE))*$U17*((1+Inputs!$D$7)^BU$2))),IF($N17=Lists!$K$3,IF($L17<1,((($T17*(1-$F17)+$S17*(1-$G17))/$L17)*((1+Inputs!$D$7)^BU$2)),((INT(BU$2/$L17)-INT((BU$2-1)/$L17))*($T17*(1-$F17)+$S17*(1-$G17))*((1+Inputs!$D$7)^BU$2))),((Inputs!$D$8^((1-_xlfn.WEIBULL.DIST(BU$2,$M17,$L17,FALSE))/_xlfn.WEIBULL.DIST(BU$2,$M17,$L17,FALSE))*($T17*(1-$F17)+$S17*(1-$G17))*((1+Inputs!$D$7)^BU$2)))))))) -> 71920.372 | BV17: =MAX(AF17,($E17*IF(BV$2>Inputs!$D$5,0,IF(BV$2>VLOOKUP($H17,Lists!$P$3:$Q$7,2),IF($N17=Lists!$K$3,IF($L17<1,(($U17/$L17)*((1+Inputs!$D$7)^BV$2)),((INT(BV$2/$L17)-INT((BV$2-1)/$L17))*$U17*((1+Inputs!$D$7)^BV$2))),(Inputs!$D$8^((1-_xlfn.WEIBULL.DIST(BV$2,$M17,$L17,FALSE))/_xlfn.WEIBULL.DIST(BV$2,$M17,$L17,FALSE))*$U17*((1+Inputs!$D$7)^BV$2))),IF($N17=Lists!$K$3,IF($L17<1,((($T17*(1-$F17)+$S17*(1-$G17))/$L17)*((1+Inputs!$D$7)^BV$2)),((INT(BV$2/$L17)-INT((BV$2-1)/$L17))*($T17*(1-$F17)+$S17*(1-$G17))*((1+Inputs!$D$7)^BV$2))),((Inputs!$D$8^((1-_xlfn.WEIBULL.DIST(BV$2,$M17,$L17,FALSE))/_xlfn.WEIBULL.DIST(BV$2,$M17,$L17,FALSE))*($T17*(1-$F17)+$S17*(1-$G17))*((1+Inputs!$D$7)^BV$2)))))))) -> 66118.949 | BW17: =MAX(AG17,($E17*IF(BW$2>Inputs!$D$5,0,IF(BW$2>VLOOKUP($H17,Lists!$P$3:$Q$7,2),IF($N17=Lists!$K$3,IF($L17<1,(($U17/$L17)*((1+Inputs!$D$7)^BW$2)),((INT(BW$2/$L17)-INT((BW$2-1)/$L17))*$U17*((1+Inputs!$D$7)^BW$2))),(Inputs!$D$8^((1-_xlfn.WEIBULL.DIST(BW$2,$M17,$L17,FALSE))/_xlfn.WEIBULL.DIST(BW$2,$M17,$L17,FALSE))*$U17*((1+Inputs!$D$7)^BW$2))),IF($N17=Lists!$K$3,IF($L17<1,((($T17*(1-$F17)+$S17*(1-$G17))/$L17)*((1+Inputs!$D$7)^BW$2)),((INT(BW$2/$L17)-INT((BW$2-1)/$L17))*($T17*(1-$F17)+$S17*(1-$G17))*((1+Inputs!$D$7)^BW$2))),((Inputs!$D$8^((1-_xlfn.WEIBULL.DIST(BW$2,$M17,$L17,FALSE))/_xlfn.WEIBULL.DIST(BW$2,$M17,$L17,FALSE))*($T17*(1-$F17)+$S17*(1-$G17))*((1+Inputs!$D$7)^BW$2)))))))) -> 60528.279 | BX17: =MAX(AH17,($E17*IF(BX$2>Inputs!$D$5,0,IF(BX$2>VLOOKUP($H17,Lists!$P$3:$Q$7,2),IF($N17=Lists!$K$3,IF($L17<1,(($U17/$L17)*((1+Inputs!$D$7)^BX$2)),((INT(BX$2/$L17)-INT((BX$2-1)/$L17))*$U17*((1+Inputs!$D$7)^BX$2))),(Inputs!$D$8^((1-_xlfn.WEIBULL.DIST(BX$2,$M17,$L17,FALSE))/_xlfn.WEIBULL.DIST(BX$2,$M17,$L17,FALSE))*$U17*((1+Inputs!$D$7)^BX$2))),IF($N17=Lists!$K$3,IF($L17<1,((($T17*(1-$F17)+$S17*(1-$G17))/$L17)*((1+Inputs!$D$7)^BX$2)),((INT(BX$2/$L17)-INT((BX$2-1)/$L17))*($T17*(1-$F17)+$S17*(1-$G17))*((1+Inputs!$D$7)^BX$2))),((Inputs!$D$8^((1-_xlfn.WEIBULL.DIST(BX$2,$M17,$L17,FALSE))/_xlfn.WEIBULL.DIST(BX$2,$M17,$L17,FALSE))*($T17*(1-$F17)+$S17*(1-$G17))*((1+Inputs!$D$7)^BX$2)))))))) -> 55166.308 | ... DD17: =MAX(BN17,($E17*IF(DD$2>Inputs!$D$5,0,IF(DD$2>VLOOKUP($H17,Lists!$P$3:$Q$7,2),IF($N17=Lists!$K$3,IF($L17<1,(($U17/$L17)*((1+Inputs!$D$7)^DD$2)),((INT(DD$2/$L17)-INT((DD$2-1)/$L17))*$U17*((1+Inputs!$D$7)^DD$2))),(Inputs!$D$8^((1-_xlfn.WEIBULL.DIST(DD$2,$M17,$L17,FALSE))/_xlfn.WEIBULL.DIST(DD$2,$M17,$L17,FALSE))*$U17*((1+Inputs!$D$7)^DD$2))),IF($N17=Lists!$K$3,IF($L17<1,((($T17*(1-$F17)+$S17*(1-$G17))/$L17)*((1+Inputs!$D$7)^DD$2)),((INT(DD$2/$L17)-INT((DD$2-1)/$L17))*($T17*(1-$F17)+$S17*(1-$G17))*((1+Inputs!$D$7)^DD$2))),((Inputs!$D$8^((1-_xlfn.WEIBULL.DIST(DD$2,$M17,$L17,FALSE))/_xlfn.WEIBULL.DIST(DD$2,$M17,$L17,FALSE))*($T17*(1-$F17)+$S17*(1-$G17))*((1+Inputs!$D$7)^DD$2)))))))) -> 0
